Workbook

Sheet Nomenclatura Campi
A1: Classe | B1: Sigla | C1: Definizione | D1: Data type | E1: Note
A2: Codice | B2: CD | C2: Identifica­ univocamente un og­get­to, una persona o altro. | D2: NUMBER/VARCHAR
A3: Descrizione | B3: DS | C3: Insieme di parole o nomi generici che descrivono qual­co­sa. | D3: VARCHAR | E3: Spesso abbinata ad un codice.
A4: Tipo | B4: TP | C4: Tipologia normalmente associata una lista di valori. | D4: VARCHAR
A5: Data | B5: DT | C5: Data del calendario. | D5: DATE (YYYY-MM-DD)
A6: Data e Orario | B6: TS | C6: Timestamp del giorno. | D6: TIMESTAMP
A7: Importo in euro | B7: EU | C7: Importo espresso in unità di euro. | D7: NUMBER | E7: Numerico con due decimali.
A8: Indicatore Flag | B8: FL | C8: Indicatore logico | D8: VARCHAR | E8: Rigorosamente a 2 valori. "S" o "N"
A9: Quantità numerica | B9: NM | C9: Valutazione di ordine quantitativo non monetario: è un numero asso­luto su cui ha senso fare dei calcoli come ad esempio delle somme. | D9: NUMBER
A10: Percentuale | B10: PC | C10: Quantità numerica riferita a 100. | D10: NUMBER
A11: Progressivo | B11: PR | C11: E’ un numero che viene generato sommando 1 all’ultimo presente. | D11: NUMBER | E11: In molti casi CD è preferibile se partecipa ad una chiave primaria. Tipico all’interno di un altro codice (es: pr_riga_ordine).
A12: Generico | B12: GN_ | C12: Utilizzato per i campi Variant. | D12: VARIANT | E12: Non dovrebbe servire in L2 ma solo su L1

Sheet Nomenclatura Frequenza Tabelle
A1: Classe | B1: Sigla/Suffisso | C1: Definizione | D1: Example | E1: Note
A2: Giornaliera | C2: Tabella con frequenza gironaliera | D2: PRATICA
A3: Settimanale | B3: _W | C3: Tabella con frequenza Settimanale | D3: PRATICA_W
A4: Mensile | B4: _M | C4: Tabella con frequenza Mensile | D4: PRATICA_M
A5: Trimestrale | B5: _T | C5: Tabella con frequenza Trimestrale | D5: PRATICA_T
A6: Quadrimestrale | B6: _Q | C6: Tabella con frequenza Quadrimestrale | D6: PRATICA_Q
A7: Semestrale | B7: _S | C7: Tabella con frequenza Semestrale | D7: PRATICA_S
A8: Annuale | B8: _Y | C8: Tabella con frequenza Annuale | D8: PRATICA_Y
A9: On Demand | B9: _O | C9: Tabella con frequenza a richiesta | D9: PRATICA_O

Sheet Nomenclatura SubjectArea Tabell
A1: Subject Area | B1: Suffisso Subject Area (COD) | C1: Definizione | D1: Example | E1: Note
A2: S.A. - ANAGRAFICA CONTROPARTE | B2: ANA_CNT | D2: L2_ANA_CNT.CONTROPARTE
A3: S.A. - ANAGRAFICA STRUTTURA COMMERCIALE | B3: ANA_COM | D3: L2_ANA_COM
A4: S.A. - HR | B4: HR | D4: L2_HR
A5: S.A. - VOICE OF CUSTOMER | B5: CNT_VOC | D5: L2_CNT_VOC
A6: S.A. - CONTATTI | B6: CNT | D6: L2_CNT
A7: S.A. - AREA RISERVATA WEB&APP | B7: DGT_ARI | D7: L2_DGT_ARI
A8: S.A. - FORM & PREVENTIVATORI | B8: DGT_FRP | D8: L2_DGT_FRP
A9: S.A. - TRACCIATURA DIGITAL | B9: DGT_TRC | D9: L2_DGT_TRC
A10: S.A. - PREVENTION | B10: GNS_PRV | D10: L2_GNS_PRV
A11: S.A. - RECOVERY | B11: GNS_RCV | D11: L2_GNS_RCV
A12: S.A. - CQS | B12: PRD_CQS | D12: L2_PRD_CQS
A13: S.A. - PAGAMENTI E CONTABILITA' | B13: PRD_PGM | D13: L2_PRD_PGM
... A31: S.A. - FINSTOCK | B31: PRD_FNS | D31: L2_PRD_FNS

Sheet Catalogo Entità
A1: Entità DM Nome | E1: "L2" -> entità L2 "LT" -> entità Layer tecnico (lookup e tabelle di conf) | M1: valorizzare S se c'è dipendenza con altre ENTITA L2, N altrimenti (NB: il campo non può essere NON valorizzato) | N1: riportare l'entità L2 con cui è presente la dipendenza (possono essere anche più di 1) | O1: valorizzare S se c'è dipendenza con altre ENTITA L2 di altre AREE di Analisi, N altrimenti (NB: il campo non può essere NON valorizzato) | P1: riportare l'AREA L2 con cui è presente la dipendenza (possono essere anche più di 1, in tal caso compilare in modo che sia chiaro il legame ENTITA COLLEGATA - AREA COLLEGATA ----->AREA COLLEGATA.ENTITA L2 COLLEGATA )
A2: Nome Entità | B2: Macro Area | C2: Subject Area | D2: ID_ENTITA | E2: TP_ENTITA | F2: DESCRIZIONE BREVE | G2: DEFINIZIONE FUNZIONALE PERIMETRO | H2: SORGENTI L1/L2 in JOIN sul campo opportuno | I2: Note | J2: ENTITA DI INTERESSE IFRS9 | K2: Regola Tecnica Perimetro (Nome tabella/e Main) | L2: Regola Tecnica Perimetro (eventuali filtri su tabella Main, chiavi o regole di join) | M2: DIPENDENZA DA ALTRE ENTITA L2 | N2: ENTITA L2 COLLEGATA | O2: DIPENDENZA DA ALTRE AREE di Analisi | P2: ALTRA AREA/SA COLLEGATA | Q2: STORICIZZAZIONE ENTITA FINALE E ARCHIVI SORGENTI | R2: PROFONDITA STORICA (a compilazione temporanea solo per area Rischi)
A3: PRATICA | B3: PRODOTTO | C3: MAIN | D3: IDL2_1 | E3: L2 | F3: Contiene le informazioni di testata delle pratiche afferenti alle procedure Consumo, Carte e CQS. Il dettaglio delle singole pratiche è disponibile nelle rispettive tabelle di procedura (Consumo, Carta e CQS), che riportano gli attributi specifici di ciascun ambito. | G3: Union delle pratiche presenti in L1.PLPRAT, L1.CRCAR, L1.QSPRA. La tabella deve essere storicizzata. | J3: N | K3: PLPRAT CRCAR QSPRA | L3: SELECT * FROM PLPRAT UNION ALL SELECT * FROM CRCAR UNION ALL SELECT * FROM QSPRA | M3: N | N3: NA | O3: N | P3: NA | Q3: S4 [L1]PLPRAT -> B2 [L1]CRCAR -> B2 [L1]QSPRA -> B2
A4: CONSUMO | B4: PRODOTTO | C4: MAIN | D4: IDL2_2 | E4: L2 | F4: Tabella che contiene il dettaglio informativo delle pratiche di tipo Consumo, integrando e specializzando le informazioni di testata presenti nella tabella delle pratiche multiprocedura. | G4: Perimetro delle pratiche provenienti dal PLPRAT | K4: PLPRAT | L4: SELECT * FROM PLPRAT | M4: N | N4: NA | O4: N | P4: NA | Q4: S4 [L1]PLPRAT -> B2
A5: CONSUMO_M | B5: PRODOTTO | C5: MAIN | F5: Tabelle delle Pratiche consumo consolidata sul fine mese. E' la versione consolidata dell'entità "CONSUMO" | G5: Perimetro delle pratiche provenienti dal PLPRAT | K5: PLPRAT | L5: SELECT * FROM PLPRAT | M5: N | N5: NA | O5: N | P5: NA | Q5: S3 [L1]PLPRAT-> B2
A6: CARTA | B6: PRODOTTO | C6: MAIN | D6: IDL2_3 | E6: L2 | F6: Tabella che contiene il dettaglio informativo delle pratiche di tipo Carta, integrando e specializzando le informazioni di testata presenti nella tabella delle pratiche multiprocedura. | G6: Perimetro delle pratiche provenienti dal CRCAR | K6: CRCAR | L6: SELECT * FROM CRCAR | M6: N | N6: NA | O6: N | P6: NA | Q6: S4 [L1]CRCAR-> B2
A7: CARTA_M | B7: PRODOTTO | C7: MAIN | F7: Tabelle delle Pratiche revolving consolidata sul fine mese. E' la versione consolidata dell'entità "CARTA" | G7: Perimetro delle pratiche provenienti dal CRCAR | K7: CRCAR | L7: SELECT * FROM CRCAR | M7: N | N7: NA | O7: N | P7: NA | Q7: S3 [L1]CRCAR-> B2
A8: CQS | B8: PRODOTTO | C8: MAIN | D8: IDL2_4 | E8: L2 | F8: Tabella che contiene il dettaglio informativo delle pratiche di tipo CQS, integrando e specializzando le informazioni di testata presenti nella tabella delle pratiche multiprocedura. | G8: Perimetro delle pratiche provenienti dal QSPRA | K8: QSPRA | L8: SELECT * FROM QSPRA | M8: N | N8: NA | O8: N | P8: NA | Q8: S4 [L1]QSPRA-> B2
A9: CQS_M | B9: PRODOTTO | C9: MAIN | F9: Tabelle delle Pratiche CCQS consolidata sul fine mese. E' la versione consolidata dell'entità "CQS" | G9: Perimetro delle pratiche provenienti dal QSPRA | K9: QSPRA | L9: SELECT * FROM QSPRA | M9: N | N9: NA | O9: N | P9: NA | Q9: S3 [L1]QSPRA-> B2
A10: VARIAZIONI_ANAGRAFICHE | B10: ANAGRAFICA​ | C10: ANAGRAFICA CONTROPARTE​ | D10: IDL2_5 | E10: L2 | F10: Tabella che contiene tutte le informazioni e le variazioni relative alle Controparti di Agos. | G10: Controparti presenti in L1.CCANALOG. | H10: CCANALOG; CCCRETCI; CCANATNA; CCANATAT; CCANATSA; CCANATPR; CCANATRE; CCANATPO | J10: Y | K10: [L1] CCANALOG | L10: SELECT AL_CODICE FROM CCANALOG | M10: N | N10: NA | O10: N | P10: NA | Q10: Cluster archivi sorgente: CCANALOG --> A1 CCCRETCI --> C CCANATNA --> C CCANATAT --> C CCANATRA --> C CCANATSA --> C CCANATPR --> C CCANATRE --> C CCANATPO --> C Storicizzazione: S1
A11: ANA_STRUTTURA_INTERNA | B11: ANAGRAFICA​ | C11: ANAGRAFICA STRUTTURA COMMERCIALE | D11: IDL2_6 | E11: L2 | F11: Tabella riassuntiva delle principali informazioni legate alla struttura interna così come è riproposta da L1. Entità necessaria per poter ricondurre la struttura interna con le entità che ragionano per filiale OCS, come provvigioni etc.. | G11: Filiali e struttura interna di riferimento proveniente dal CCANATFI | H11: JOIN1: CCANATFI.ANATFI_AREA = CCTABARE.TABARE_AREA JOIN2: CCANATFI.ANATFI_DISTRETTO = CCANATDI.ANATDI_DISTRETTO | K11: CCANATFI | L11: N | M11: N | N11: NA | O11: N | P11: NA | Q11: [L1] CCANATFI -> B2 --> S4, S3 [L1] CCANATDI -> C-->S1 [L1] CCTABARE -> C-->S1
A12: CATENE_INTERMEDIAZIONE_AGG | B12: PRODOTTO | C12: MAIN | D12: IDL2_8 | E12: L2 | F12: Tabella che associa le catene di intermediazione agggiuntive alle pratiche Agos | G12: Pratiche che hanno una catena di intermediazione aggiuntiva associata proveniente dal BAPRATINT | H12: BAPRATINT.BAINT_PUNTO_VENDITA = CCANAIPV. IPV_CODICE | K12: BAPRATINT (L1) | L12: SELECT * FROM BAPRATINT WHERE BAPRATINT.BAINT_PROGRESSIVO >=1 | M12: N | N12: NA | O12: N | P12: NA | Q12: S4 [L1] BAPRATINT -> B2
A13: SALDO_GESTIONALE_M | B13: RISCHI E ADEMPIMENTI​ | C13: SALDI​ | D13: IDL2_9 | E13: L2 | F13: Tabella dei Saldi a fine mese (End Of Month) mostra la vista gestionale | G13: Pratiche in L1.OXDRFPRA | H13: OXDRFPRA OXIAFCOMPE | I13: Dati Storico -> OP 429 + OP 516 | J13: Y | K13: SELECT * FROM OXDRFPRA | L13: SELECT * FROM OXDRFPRA WHERE DRPRA_DATA_ESTRAZIONE=LAST_DAY(DATEADD('month', -1, CURRENT_DATE())) | M13: N | N13: N | O13: N | P13: NA | Q13: S3
A14: SALDO_CONTABILE_M | B14: RISCHI E ADEMPIMENTI​ | C14: SALDI​ | D14: IDL2_147 | E14: L2 | F14: Tabella dei Saldi a fine mese (End Of Month) mostra la vista contabile | G14: Pratiche in L1.OXDRFPRA | H14: OXDRFPRA OXIAFCOMPE | J14: Y | K14: SELECT * FROM OXDRFPRA | L14: SELECT * FROM OXDRFPRA WHERE DRPRA_DATA_ESTRAZIONE=LAST_DAY(DATEADD('month', -1, CURRENT_DATE())) | M14: N | N14: N | O14: N | P14: NA | Q14: S3
A15: RIMBORSI | B15: PRODOTTO | C15: PAGAMENTI E CONTABILITA​ | D15: IDL2_10 | E15: L2 | F15: Tabella dei Rimborsi | G15: Elenco dei Rimborsi avvenuti sulle pratiche presenti in L1.PLPRAT, L1.CRCAR, L1.QSPRA | I15: DRAFT, in attesa sviluppi OCS. Il perimetro di questa entità dovrebbe essere individuato a partire da un report prodotto da OCS riguardante, nello specifico, i rimborsi. | J15: N
A16: SCARTI | B16: PRODOTTO | C16: PAGAMENTI E CONTABILITA​ | D16: IDL2_11 | E16: L2 | F16: Tabella degli Scarti: Rimborsi che non vengono effettuati | G16: Elenco degli Scarti sulle pratiche presenti in L1.PLPRAT, L1.CRCAR, L1.QSPRA | I16: DRAFT, in attesa sviluppi OCS. Il perimetro di questa entità dovrebbe essere individuato a partire da un report prodotto da OCS riguardante, nello specifico, gli scarti. | J16: N
A17: DOMINIO_SCARTO | B17: PRODOTTO | C17: PAGAMENTI E CONTABILITA​ | D17: IDL2_12 | E17: L2 | F17: Tabella con tutte le tipologie di Motivo Scarto con codice, descrizione e gerarchia dello scarto. | I17: DRAFT, in attesa sviluppi OCS | J17: N
A18: PRATICA_M | B18: PRODOTTO | C18: MAIN | D18: IDL2_15 | E18: L2 | F18: Tabelle delle Pratiche consolidata sul fine mese. E' la versione consolidata dell'entità "PRATICA" | G18: Union delle pratiche presenti in L1.PLPRAT, L1.CRCAR, L1.QSPRA. La tabella deve essere storicizzata. | J18: Y | K18: PLPRAT CRCAR QSPRA | L18: SELECT * FROM PLPRAT UNION ALL SELECT * FROM CRCAR SELECT * FROM QSPRA | M18: N | N18: NA | O18: N | P18: NA | Q18: S3 [L1]PLPRAT -> B2 [L1]CRCAR -> B2 [L1]QSPRA -> B2
A19: SVALUTAZIONI_M | B19: RISCHI E ADEMPIMENTI​ | C19: RISCHI​ | D19: IDL2_16 | E19: L2 | F19: Tabelle delle Pratiche in svalutazioni con annessi importi sulle dinamiche (per tutte le pratiche, comprese casistiche fuori bilancio o enti finanziari) | G19: Lista delle Pratiche oggetto di svalutazione nel mese M (In attesa mappatura OCS). La tabella contiene le pratiche a livello originator, con eventuale integrazione delle componenti cartolarizzate, schiacciando gli importi quando entrambe sono presenti. | J19: Y | K19: SVESFCRSC | L19: SELECT SVCRSC_PRATICA, SVCRSC_PROCEDURA, SVCRSC_ANNO_ESTRAZIONE, SVCRSC_MESE_ESTRAZIONE FROM SVESFCRSC | M19: N | N19: NA | O19: N | P19: NA | Q19: [L1] SVESFCRSC --> B1 --> S1 | R19: chiedere a migrazione: finance (almeno tutti i dicembre/fine anno disponibili - dati di fine anno precedente)
A20: FORBEARANCE_M | B20: RISCHI E ADEMPIMENTI​ | C20: RISCHI​ | D20: IDL2_17 | E20: L2 | F20: Tabella che registra informazioni sulle pratiche in forbearance | G20: Lista delle Pratiche entrate, rimaste o uscite dallo stato di forbearance nel mese M (In attesa mappatura OCS) | J20: Y | K20: OXDRFPRA | L20: SELECT * FROM OXDRFPRA | M20: N | N20: NA | O20: N | P20: NA | Q20: [L1] OXDRFPRA --> A1 --> S3 | R20: tutto quello che c'è
A21: INCASSI_BOLLETTINI | B21: PRODOTTO | C21: PAGAMENTI E CONTABILITA​ | D21: IDL2_18 | E21: L2 | F21: Tabella che registra gli incassi tramite Bollettino | G21: Lista dei bollettini incassati: L1.CRCCPTES, L1.CRCCPDET, L1.BACCPDET, L1.BACCPTES | H21: CAINFBPDT, CGEVNT | J21: N | K21: [L1]BACCPDET | M21: N | N21: NA | O21: N | P21: NA | Q21: [L1]BACCPDET->A1
A22: INCASSI_CAMBIALI | B22: PRODOTTO | C22: PAGAMENTI E CONTABILITA​ | D22: IDL2_19 | E22: L2 | F22: Tabella che registra gli incassi tramite Cambiale (si ritengono incluse anche cambiali future) | G22: Lista dei bollettini cambiali: GAEFARC + archivi in sviluppo | H22: EFEXFINCDE? | J22: N/Y approfondimenti in corso | K22: [L1]GAEFARC | M22: N | N22: NA | O22: N | P22: NA | Q22: [L1]GAEFARC->A2
A23: INCASSI_BONIFICI | B23: PRODOTTO | C23: PAGAMENTI E CONTABILITA​ | D23: IDL2_20 | E23: L2 | F23: Tabella che registra gli incassi tramite Bonifico | G23: LIsta dei bonifici: CCBONISET | I23: Manca campo sorgente per CD_TERZO_ORDINANTE | J23: N | K23: [L1]CCBONISET | M23: N | N23: NA | O23: N | P23: NA | Q23: [L1]CCBONISET->A1
A24: INCASSI_SDD | B24: PRODOTTO | C24: PAGAMENTI E CONTABILITA​ | D24: IDL2_21 | E24: L2 | F24: Tabella che registra gli incassi tramite SDD | G24: Lista degli SDD: CCCASTE | H24: CCNEWABI | J24: N | K24: [L1]CCNEWABI | M24: N | N24: NA | O24: N | P24: NA | Q24: [L1]CCCASTE->A2 [L1] CCNEWABI ->C
A25: MANDATI_INCASSI_SDD | B25: PRODOTTO | C25: PAGAMENTI E CONTABILITA​ | D25: IDL2_22 | E25: L2 | F25: Tabella che registra i mandati SDD e RID | G25: Lista dei mandati SDD: ICMAFMAN | H25: BNPTCUC_CODICE_SIA | J25: N | K25: [L1]ICMAFMAN | M25: N | N25: NA | O25: N | P25: NA | Q25: [L1]CMAFMAN->A2
A26: INCASSI | B26: PRODOTTO | C26: PAGAMENTI E CONTABILITA​ | D26: IDL2_23 | E26: L2 | F26: Tabella degli incassi che registra movimenti in ingresso effettuati con qualsiasi metodologia di pagamento | G26: Lista degli incassi cross sulla tipologia di pagamento: Aspettiamo approfondimento con OCS | J26: Y
A27: INCASSI_TESTATA | B27: PRODOTTO | C27: PAGAMENTI E CONTABILITA​ | D27: IDL_159 | E27: L2 | F27: Tabella degli incassi che registra informazioni generiche sui movimenti in ingresso | G27: OXINFREPT | I27: Manca campo sorgente per DT_INIZIO_VALIDITà e DT_FINE_VALIDITà | J27: Y | K27: [l1] OXINFREPT | M27: S | N27: INCASSI_DETTAGLIO | O27: N | P27: NA | Q27: [L1]OXINFREPT->A2
A28: INCASSI_DETTAGLIO | B28: PRODOTTO | C28: PAGAMENTI E CONTABILITA​ | D28: IDL_160 | E28: L2 | F28: Tabella degli incassi che registra informazioni specifiche sui movimenti in ingresso | G28: OXINFREPD | I28: Manca campo sorgente per DT_INIZIO_VALIDITà e DT_FINE_VALIDITà | J28: Y | K28: [l1] OXINFREPD | M28: S | N28: INCASSI_TESTATA | O28: N | P28: NA | Q28: [l1] OXINFREPD -> A2
A29: PAGAMENTI | B29: PRODOTTO | C29: PAGAMENTI E CONTABILITA​ | D29: IDL2_24 | E29: L2 | F29: Tabella dei pagamenti che registra movimenti in uscita effettuati con qualsiasi metodologia di pagamento | G29: Lista dei pagementi cross sulla tipologia di pagamento: CCBONWK + archivi in sviluppo per Vidaut | J29: N
A30: PAGAMENTI_TESTATA | B30: PRODOTTO | C30: PAGAMENTI E CONTABILITA​ | D30: IDL_161 | E30: L2 | F30: Tabella dei pagamenti che registra informazioni generiche sui movimenti in uscita | G30: CCRIMBO | J30: N | M30: S | N30: PAGAMENTI_TESTATA, PAGAMENTI_VIDAUT | P30: NA | Q30: ?
A31: PAGAMENTI_BONIFCI | B31: PRODOTTO | C31: PAGAMENTI E CONTABILITA​ | D31: IDL_162 | E31: L2 | F31: Tabella dei pagamenti che registra movimenti in uscita di tipologia bonifico | G31: CCBONWK | I31: Campo EU_COMMISSIONI in validazione per Campioni | J31: N | K31: [L1] CCBONWK | M31: S | N31: PAGAMENTI_TESTATA | O31: N | P31: NA | Q31: [L1] CCBONWK->A2
A32: PAGAMENTI_VIDAUT | B32: PRODOTTO | C32: PAGAMENTI E CONTABILITA​ | D32: IDL_163 | E32: L2 | F32: Tabella dei pagamenti che registra movimenti in uscita di tipologia vidaut
A33: LEGAME_CARTOLARIZZAZIONI | B33: RISCHI E ADEMPIMENTI​ | C33: RISCHI​ | D33: IDL2_26 | E33: L2 | F33: Tabella di legame per la pratica cartolarizzata e la pratica OCS. Utilizzata per centralizzare le regole per le pratiche cartolarizzate | G33: Lista delle pratiche cartolarizzate associate alle pratiche originali | K33: OXDRFPRA | L33: SELECT * FROM OXDRFPRA | M33: N | N33: NA | O33: N | P33: NA | Q33: [L1] OXDRFPRA --> A1 --> S3 | R33: --
A34: STATO_CREDITIZIO_M | B34: RISCHI E ADEMPIMENTI​ | C34: RISCHI​ | D34: IDL2_27 | E34: L2 | F34: Tabella che registra le variazioni sulla qualità creditizia delle pratiche. Include informazioni sulla qualità creditizia, stage e default eba | G34: Lista delle pratiche per le quali è valorizzato lo stato creditizio | J34: Y | K34: OXDRFPRA | L34: SELECT * FROM OXDRFPRA | M34: Y | N34: LEGAME_PRAT_CONTR | O34: Y | P34: ANAGRAFICA CONTROPARTE​ | Q34: [L1] OXDRFPRA --> A1 --> S3 | R34: --
A35: GESTIONE_TRUFFE | B35: SCORING & DATA ENRICHMENT​ | C35: ANTIFRODE​ | D35: IDL2_28 | E35: L2 | F35: Tabella che registra la marchiatura delle pratiche come truffa | G35: Pratiche per cui è stata registrata una truffa | I35: In attesa di mappatura da parte di OCS -> OP Jira di riferimento : AGXDMW1-394 Valutare di cambiare il nome per evitare la ridondanza e fuorvianza di "PRATICHE" nel nome. | J35: Y | K35: OXTRFTRU | L35: SELECT *FROM OXTRFTRU | M35: N | N35: N | O35: N | P35: NA | Q35: A2--> S2
A36: DOC_ISTRUTTORIA | B36: PRODOTTO | C36: ONBOARDING​ | D36: IDL2_29 | E36: L2 | F36: Tabella che associa alle pratiche i documenti richiesti in checklist documentale e riporta lo stato riguardo il rientro della suddetta documentazione. Oltre alle checklist documentali per l'istruttoria di una pratica, sono riportate in questa tabella anche le checklist documentali relative al convenzionamento di un partner. | G36: Perimetro dati coincidente con OXDOFD | H36: OXDOFT OXDOFTPR OXDOFTCV OXTBFDOC OXDOFTBST OXDOFTSEDO PLTBFDOCR CADOFTDO QSTABDRI OXDOFTSI | I36: In attesa di mappatura da parte di OCS -> OP Jira di riferimento : AGXDMW1-394 | J36: N | K36: OXDOFD | L36: Select * from OXDOFD | M36: NA | N36: NA | O36: NA | P36: NA | Q36: S4 Le tabelle sono tutte delle C ma le attualizziamo, prendiamo solo la finestra valida MAIN -> OXDOFD OXDOFT OXDOFTPR OXDOFTCV OXTBFDOC OXDOFTBST OXDOFTSEDO PLTBFDOCR CADOFTDO QSTABDRI OXDOFTSI
A37: ANA_INTERMEDIARI_BASE | B37: ANAGRAFICA​ | C37: ANAGRAFICA STRUTTURA COMMERCIALE | D37: IDL2_31 | E37: L2 | F37: Tabella anagrafica base riassuntiva delle principali informazioni legate alle catene di intermediaizone e intermediari. | J37: S | K37: CCANAIAG | L37: N | M37: N | N37: NA | O37: N | P37: NA | Q37: [L1] CCANAGR -> B1 --> S1 [L1] CCANAIAG -> B1 [L1] CCANAICV -> B1 [L1] CCANAIPV -> B1 [L1] CCANAISA -> B1 [L1] CCANAIVE -> B1
A38: SERVIZI_ASSICURATIVI_SINISTRI | B38: PRODOTTO | C38: ASSICURAZIONI​ | D38: IDL2_32 | E38: L2 | F38: Tabella che registra l'avvenimento dei sinistri sui servizi | I38: In attesa di mappatura da parte di OCS -> OP Jira di riferimento : AGXDMW1-394 | J38: N | M38: N | N38: N | O38: N | P38: N | Q38: OP. Entità ancora in sviluppo da parte di OCS
A39: CARTE_LIMITAZIONI_OPERATIVITA | B39: PRODOTTO | C39: CARTE​ | D39: IDL2_14 | E39: L2 | F39: Proprietà dei blocchi delle carte. Contiene il dettaglio dei blocchi. I dettagli sono raggiungibili facendo JOIN tra BLOCCHI_CARTE che contiene riferimento (FK) a questa tabella. | K39: CRCARBLO | L39: CRCARBLO | M39: Y | N39: VARIAZIONI_STATO_PRAT | Q39: [L1] CRCARBLO --> A2 [L2] VARIAZIONI_STATO_PRAT
A40: CARTE_UTILIZZI | B40: PRODOTTO | C40: CARTE​ | D40: IDL2_33 | E40: L2 | F40: Entità core degli utilizzi delle carte, dove verranno censite solamente le informazioni principali degli avvenuti utilizzi della carta. Le transazioni approvate. Le informazioni del POS di fine giornata provenienti dai circuiti internazionali. Le informazioni delle eventuali promozioni legate all’utilizzo della carta | I40: In attesa di mappatura da parte di OCS -> OP Jira di riferimento : AGXDMW1-394 | J40: Y/N da approfondire se effettivamente la usiamo in senso attivo | K40: CRVOUF | L40: CRVOUF | M40: N | N40: N | O40: N | P40: N | Q40: CRVOUF --> C --> S1 CRVOUA --> C --> S1 CRINSTANT --> C --> S1 CRCROSVOU --> C --> S1 CRCAR ROTBFCAU -> C --> S1 CRTABCAM --> C --> S1 CRCAMP --> A2 --> S2 PSINTACQ --> A2 --> S2 PSSICCOD --> C --> S1 CRAUT --> C --> S1
A41: MANUAL_ADJUSTMENT_O | B41: LT | C41: LT | D41: IDL2_34 | E41: LT | F41: Tabella contenete i manual adjustment utilizzabili in formule per effettuare operazioni/calcoli in DWHX. Aggiornamento una Tantum a seguito di richiesta Business di Aggiornamento | G41: Valori costanti definiti da Business | H41: NA | J41: Y setta date TF + soglie sicr | K41: NA | L41: NA | M41: NA | N41: NA | O41: NA | P41: NA | Q41: S1
A42: ARCHIVIO_TESSERE | B42: SCORING & DATA ENRICHMENT​ | C42: ANTIFRODE​ | D42: IDL2_36 | E42: L2 | F42: Entità contenente l'architettura del PAN delle carte utilizzabile somandete dall'ufficio di antifrode | G42: Tutte le carte attive | K42: CACTFPAN | M42: N | N42: N | O42: N | P42: NA | Q42: A2--> S2
A43: LOOKUP_PRODOTTO_BENE_CACF_O | B43: LT | C43: LT | D43: IDL2_39 | E43: LT | F43: Lookup per conversione di tipologia configurazione prodotto agos in configurazione prodotto CACF | J43: Y (approfondirne l'utilizzo)
A44: LOOKUP_CANALE_CACF_O | B44: LT | C44: LT | D44: IDL2_40 | E44: LT | F44: Lookup per conversione di tipologia canale acquisizione agos in canale acquisizione CACF | J44: Y (approfondirne l'utilizzo)
A45: INDICE_RISCHIO_M | B45: RISCHI E ADEMPIMENTI​ | C45: RISCHI​ | D45: IDL2_42 | E45: L2 | F45: Tabella mensile che contiene a livello di pratica i campi necessari per il calcolo degli indicatori SIR e IR relativi al processo Indice di Rischio. | G45: Tutte le pratiche Consumo e Revolving del portafoglio | H45: PLPRAT, CRCAR, OXSSFSSIM | I45: In attesa di mappatura da parte di OCS e di validazione da parte di Agos | K45: PRATICA_M | L45: SELECT * FROM PRATICA_M WHENRE DT_OSSERVAZIONE = EOMONTH(GETDATE(), -1) | M45: Y | N45: PRATICA_M | O45: Y | P45: PRODOTTO CONSUMO | Q45: [L1] PLPRAT --> B2 --> S3 [L1] OXSSFSSIM --> A1 --> S3 | R45: chiedere a migrazione: tutta la storia o almeno 10 anni (orisk.indice_rischio)
A46: ANAGRAFICA_PRODOTTO_ASSIC | B46: PRODOTTO | C46: ASSICURAZIONI​ | D46: IDL2_43 | E46: L2 | F46: Tabella contente le anagrafiche dei prodotti venduti e le relative filiali associate | K46: tblprodottiversioni tblnodi | L46: SELECT PV.idProdottoVersione, FROM tblprodottiversioni PV | M46: N | N46: N | O46: N | P46: N | Q46: S4 tblprodottiversioni --> C
A47: APPUNTAMENTO | B47: CONTATTI​ | C47: MAIN | D47: IDL2_44 | E47: L2 | F47: Entità giornaliera che contiene tutte le informazioni relative alla presa appuntamento e all’esito dell’appuntamento. | J47: N
A48: SERVIZI_ASSICURATIVI | B48: PRODOTTO | C48: ASSICURAZIONI​ | D48: IDL2_45 | E48: L2 | F48: Tabella che contiene tutte le informazioni relative alle assicurazioni vendute in abbinata alle pratiche e ai servizi assicurativi legati alle PNF (rinnovi di polizze accessorie che si scollegano rispetto al finanziamento di origine). | G48: Tutti i servizi/pacchetti assicurativi venduti contestualmente alla stipula di un contratto di finanziamento (Consumo e Carte, escluso il prodotto CQS). | J48: N | K48: PLPRTASERV UNION ALL CCTABSER | M48: N | N48: N | O48: N | P48: N | Q48: S4 [L1] PLPRATSERV -> B2 [L1] CASRFSER -> B2 [L1] CCTABSER -> C [L1] CCTABPACC -> C [L1] PLPRAT -> B2 [L1] CCANAGR -> B1 [L1] OXSRFSERD -> B2
A49: SERVIZI_ASSICURATIVI_M | B49: PRODOTTO | C49: ASSICURAZIONI​ | D49: IDL2_116 | E49: L2 | F49: Tabella mensile che contiene tutte le informazioni relative alle assicurazioni vendute in abbinata alle pratiche e ai servizi assicurativi legati alle PNF (rinnovi di polizze accessorie che si scollegano rispetto al finanziamento di origine) consolidate per ogni fine mese. Pensata per collegare le pratiche consolidate mensilmente (PRATICA_M) alle assicurazioni in modo opportuno | K49: PLPRTASERV (mensile) UNION ALL CCTABSER (mensile) | Q49: S3
A50: POLIZZE_STANDALONE | B50: PRODOTTO | C50: ASSICURAZIONI​ | D50: IDL2_46 | E50: L2 | F50: Tabella che contiene tutte le informazioni relative alle polizze Stand Alone vendute sull'applicativo FEA. | G50: Tutte le polizze assicurative vendute e gestite tramite FEA e che risultano indipendenti dal momento di stipula di un contrato di finanziamento. | K50: ACEDRV_TBLPREVENTIVO | L50: SELECT * FROM ACEDRV_TBLPREVENTIVO | M50: N | N50: N | O50: N | P50: N | Q50: S4 [L1] ACEDRV_TBLPREVENTIVO -> C [L1] TBLPRODOTTIVERSIONI -> C [L1] TBLANAGRAFICA -> C [L1] TBLPRODOTTI -> C [L1] TBLNODI -> C [L1] TBLCAMPAGNE -> C
A51: AZIONI_POSTVENDITA | B51: PRODOTTO | C51: MAIN | D51: IDL2_47 | E51: L2 | F51: Tabella che registra lo storico delle diverse azioni di post-vendita richieste sulle pratiche dopo la liquidazione, consentendo il tracciamento degli eventi nel tempo. | G51: Ogni riga rappresenta un'azione di post-vendita registrata dal sistema su una qualsiasi pratica Consumo, revolving o Cqs | H51: CCPSVT | J51: N | K51: CCPSVT | L51: SELECT * FROM CCPSVT | M51: N | N51: NA | O51: N | P51: NA | Q51: S4 [L1] CCPSVT-> A2
A52: CONTATTO_NGS | B52: CONTATTI​ | C52: MAIN | D52: IDL2_48 | E52: LT | I52: Marketing Automation
A53: CONTACT_HISTORY | B53: CONTATTI​ | C53: MAIN | D53: IDL2_49 | E53: L2 | F53: Archivio che contiene tutti gli estratti per una determinata campagne e l'esito del contatto. | G53: Per ogni estratto relativo ad una campagna sono riportati tutti i contatti avvenuti e l'esito del contatto. | J53: N
A54: ANA_GERARCHIA_TERRITORIALE | B54: ANAGRAFICA​ | C54: ANAGRAFICA STRUTTURA COMMERCIALE | D54: IDL2_50 | E54: L2 | F54: Entità contenente la struttura gerarchia territoriale di Agos, per quanto riguarda i livelli in cui è suddivisa la struttura interna | H54: - | K54: CCANATFI | L54: N | M54: N | N54: NA | O54: N | P54: NA | Q54: [L1] CCANATFI -> B2 --> S4, S3 [L1] CCANAININ -> B1 [L1] CCANAIAG-> B1 [L1] CCANAISA-> B1
A55: PREVENTIVI | B55: CONTATTI​ | C55: MAIN | D55: IDL2_52 | E55: L2 | F55: Tabella che contiene i preventivi (incluso FEA) dei clienti. | I55: In attesa di archivi/mappatura da parte di OCS e di validazione da parte di Agos M.A. PRODOTTO e S.A. (generica per pratica ?) | J55: N | K55: PCCOCOO | M55: N | N55: N | O55: N | P55: N | Q55: [L1] PCCOFCON -> C [L1] PCCOCOO -> C
A56: ANA_UTENTI | B56: ANAGRAFICA​ | C56: ANAGRAFICA STRUTTURA COMMERCIALE | D56: IDL2_53 | E56: L2 | F56: Entità di legame per poter utilizzare il ruolo del responsabile all’interno dell’anagrafica intermediari e della gerarchia territoriali | G56: Il perimetro devono essere le parametrizzazioni e salesforce che contengono al loro interno le chaivi di connessione | I56: OP | K56: CCINTTRS ACTIVE DIRECTORY | L56: N | M56: N | N56: NA | O56: N | P56: NA | Q56: [L1] CCINTTRS -> C ACTIVE DIRECTORY
A57: ANA_GERARCHIA_TERRITORIALE_M | B57: ANAGRAFICA​ | C57: ANAGRAFICA STRUTTURA COMMERCIALE | D57: IDL2_54 | E57: L2 | F57: Entità contenente la struttura gerarchia territoriale di Agos, per quanto riguarda i livelli in cui è suddivisa la struttura interna. La struttura è con la storicizzazione mensile | K57: CCANATFI | L57: N | M57: N | N57: NA | O57: N | P57: NA | Q57: [L1] CCANATFI -> B2 --> S4, S3 [L1] CCANAININ -> B1 [L1] CCANAIAG-> B1 [L1] CCANAISA-> B1
A58: SURVEY_INPUT | B58: CONTATTI​ | C58: VOC | D58: IDL2_55 | E58: L2 | F58: Tabella che contiene le informazioni di input a Qualtrics ai fini dell'invio di survey ai clienti. | G58: Il perimentro è dato dall'insieme di informazioni relative allinvio della survey, al cliente a cui viene inviata e alla data in cui viene inviata. | J58: N | K58: QUALTRICS_INPUT | M58: N | N58: N | O58: N | P58: N
A59: SURVEY_OUTPUT | B59: CONTATTI​ | C59: VOC | D59: IDL2_56 | E59: L2 | F59: Tabella che contiene le risposte relative alla survey di Qualtrics (sia anonime che non anonime) | G59: Il perimentro è dato dall'insieme di informazioni relative al post-ricezione delle survey, e quindi all'evidenza dell'eventuale risposta o meno del cliente alla survey, ai tempi di risposta, dettagli sulla risposta, ecc. | J59: N | K59: QUALTRICS_OUTPUT | M59: N | N59: N | O59: N | P59: N
A60: RECENSIONI | B60: CONTATTI​ | C60: VOC | D60: IDL2_57 | E60: L2 | F60: Tabella che contiene tutte le recensioni rilasciate dai clienti su Trustpilot e Google Review. | G60: Il perimetro è dato da tutte quelle informazioni relative alle recensioni lasciate dai Clienti (anonime e non) su Trustpilot e Google Review | J60: N
A61: SOCIODEMO_SCORE | B61: SCORING & DATA ENRICHMENT​ | C61: SCORING​ | D61: IDL2_58 | E61: L2 | F61: insieme di informazioni che descrivono le caratteristiche sociali e demografiche di una persona. Comprendono tutte le informazioni relative al cliente, e all’eventuale coobbligato, inserite al momento del caricamento della pratica. Dati inseriti al momento di istruttoria. Questi dati rimangono fissi nel tempo, a differenza di quanto può accadere nell'anagrafica cliente che si aggiorna con gli aggiornamenti dell'anagrafica Agos - non devono quindi essere previsti controaggiornamenti per una stessa pratica | G61: Modulo BAPRA | I61: In attesa di archivi/mappatura da parte di OCS per il processo Campioni | J61: Y (non lettura diretta) | K61: L1_E_CDE.CDE | Q61: S4
A62: CESSIONI | B62: GESTIONE CREDITI​ | C62: MAIN | D62: IDL2_59 | E62: L2 | F62: Archivio che registra le pratiche cedute per le procedure Carte (CA) e Consumo (CO) | G62: Log delle cessioni gestite da agos sulle pratiche consumo e revolving. Union delle cessioni cesnite in CACSFCES e PLCHICES | J62: Y | Q62: PLCHICES -> S4 CACSFCES -> S4
A63: PASSAGGI_A_PERDITA | B63: GESTIONE CREDITI​ | C63: MAIN | D63: IDL2_60 | E63: L2 | F63: Archivio che registra le pratiche passate a perdita per le procedure Carte (CA) e Consumo (CO) | G63: Log dei passaggi a perdita gestiti da agos sulle pratiche consumo e revolving. Union dei passaggi a perdita censiti in CACHFPER e PLCHIPERD | J63: Y | Q63: PLCHIPERD -> S4 CCTABTPP -> S4 CACHFPER -> S4 CCTABTPP -> S4
A64: CONSOLIDAMENTI | B64: RISCHI E ADEMPIMENTI​ | C64: RISCHI​ | D64: IDL2_62 | E64: L2 | F64: L'archivio rappresenta la testata del conteggio di onsolidamenti, che è logicamente collegata al nuovo contratto generato a fronte dello stesso. | G64: OXCOFCOCD RIfinanziamento - Dettaglio OXCOFCOCT RIfinanziamento - Testata | H64: chiave di aggancio tra le due tabelle, il campo NUM_CONS | J64: Y | K64: OXCOFCOCT | L64: SELECT * FROM OXCOFCOCT | M64: N | N64: NA | O64: N | P64: NA | Q64: [L1] OXCOFCOCT --> A2 --> S2 [L1] OXCOFCOCD --> A2 --> S2 [L1] QSPRAAL --> A2 --> S2 | R64: Da 07/2010
A65: CONTANTE | B65: PRODOTTO | C65: PAGAMENTI E CONTABILITA​ | D65: IDL2_38 | E65: L2 | F65: L'archivio rappresenta il dettaglio delle informaizoni degli INCASSI tramite CONTANTE | G65: CCRIC | J65: N
A66: POS | B66: PRODOTTO | C66: PAGAMENTI E CONTABILITA​ | D66: IDL2_63 | E66: L2 | F66: L'archivio rappresenta il dettaglio delle informaizoni degli INCASSI tramite POSdi un terminale di una filiale? | G66: CRAUT | J66: N
A67: ASSEGNO | B67: PRODOTTO | C67: PAGAMENTI E CONTABILITA​ | D67: IDL2_64 | E67: L2 | F67: L'archivio rappresenta il dettaglio delle informaizoni degli INCASSI tramite ASSEGNO | G67: CRVOA | J67: N
A68: SALDO_OFF_M | B68: RISCHI E ADEMPIMENTI​ | C68: SALDI​ | D68: IDL2_65 | E68: L2 | F68: Tabella dei Saldo Off Balance a fine mese (End Of Month) | G68: Pratiche in L1.OXDRFEXT + pratiche in OXDRFPRA con saldo Off Balance | H68: OXDRFPRA OXDRFEXT | J68: Y | K68: SELECT * FROM OXDRFEXT WHERE DREXT_TIPOLOGIA ='CIM' UNION ALL SELECT * FROM OXDRFPRA WHERE DRPRA_TIPO='AN' AND (DRPRA_FINANZIATO_ORIG - DRPRA_SALDO) > 0 | L68: SELECT * FROM OXDRFEXT WHERE DREXT_TIPOLOGIA ='CIM' UNION ALL SELECT * FROM OXDRFPRA WHERE DRPRA_TIPO='AN' AND (DRPRA_FINANZIATO_ORIG - DRPRA_SALDO) > 0 | M68: N | N68: N | O68: N | P68: NA | Q68: S3
A69: LEGAME_DITTE_INDIVIDUALI | B69: ANAGRAFICA​ | C69: ANAGRAFICA CONTROPARTE​ | D69: IDL2_66 | E69: L2 | F69: Tabella Legame Codice controparte e relativo codice controparte Ditta individuale | G69: Controparti di tipo "privato" che hanno anche una ditta individuale associata | H69: Entità L2 CONTROPARTE | J69: Y (non lettura diretta) | K69: [L2] CONTROPARTE | L69: SELECT p.CD_CONTROPARTE FROM CONTROPARTE p INNER JOIN CONTROPARTE f ON p.CD_FISCALE = f.CD_FISCALE AND p.CD_CONTROPARTE != f.CD_CONTROPARTE WHERE p.TP_CONTROPARTE = 'P' AND (p.CD_PARTITA_IVA IS NULL OR p.CD_PARTITA_IVA = '') AND f.TP_CONTROPARTE = 'F' AND f.CD_PARTITA_IVA IS NOT NULL AND f.CD_PARTITA_IVA != '' | M69: S | N69: CONTROPARTE | O69: N | P69: N | Q69: CONTROPARTE --> S1 Storicizzazione: S2
A70: PERFORMING_M | B70: RISCHI E ADEMPIMENTI​ | C70: RISCHI​ | D70: IDL2_67 | E70: L2 | F70: Tabella sulla situazione di dettaglio rispetto ai movimenti dei diversi stati della Forbearance. Presenta in una struttura diversa dalla FORBEARANCE_M poichè i diversi stati della forbearance sono individuati a livello di controparte (se una pratica avrà più ristrutturazioni nel mese osservato si registrerà sula controparte la situazione di forbearance legata alla ristrutturazione peggiore) | G70: Clienti e pratiche, rimasti o usciti dallo stato di forbearance nel mese M | I70: in corso sviluppi OCS | J70: Y | K70: OXDRFPRA | L70: SELECT DRPRA_CLIENTE DRPRA_DATA_ESTRAZIONE FROM OXDRFPRA | M70: Y | N70: SEGNALAZIONE_ANAGRAFICHE STATO_CREDITIZIO_M | O70: Y | P70: ANAGRAFICA CONTROPARTE​ | Q70: [L1] OXDRFPRA --> A1 --> S3 [L1] OXCTFFBT --> B2 -->S3 [L1] OXCTFFBL --> A2 --> S2 [L1] OXCTFFBP --> B2 -->S3 [L1] YQNGRANT --> A1 --> S3 | R70: tutto quello che c'è
A71: RISTRUTTURAZIONI_O | B71: RISCHI E ADEMPIMENTI​ | C71: RISCHI​ | D71: IDL2_68 | E71: L1+L2 | F71: Tabella di lookup delle tipologie di ristrutturazioni | G71: Tipologie di ristrutturazioni | H71: sviluppo in corso lato OCS | I71: Tabella ad aggiornamento manuale | J71: Y | K71: sviluppo in corso lato OCS della tabella Main | L71: full tabella main | M71: N | N71: NA | O71: N | P71: NA | Q71: NA (si dovrà ereditare la situazione sulla main che è in sviluppo lato OCS) | R71: tutto quello che c'è
A72: LOOKUP_CQS_PRODOTTI_O | B72: LT | D72: IDL2_69 | E72: LT | F72: Tabella di lookup dei prodotti CQS con associata la tipologia (cessione o delega) e l'impiego (privato, pubblico, pensionato...) | G72: Tipologie prodotti CQS | H72: N.A. | I72: tabella ad agggiornamento manuale | J72: y
A73: PERDITE_MINIME | B73: GESTIONE CREDITI​ | C73: MAIN | D73: IDL2_71 | E73: L2 | F73: Pratiche chiuse per azzeramento in coda al piano. Sono di fatti delle perdite, che vengono chiamate perdite minime. | G73: Tutte le pratiche che OCS identifica come Abbuoni legati ad evento di chiusura. | J73: Y | Q73: CCPSVT -> S4 PLCHIEST -> S4 PLCHISTOR -> S4 PLPSFDABB -> S4 PLCHICHI -> S4 CQPSFDABB -> S4
A74: ELENCO_CONTI_SVAL_O | B74: RISCHI E ADEMPIMENTI​ | C74: RISCHI​ | D74: IDL2_72 | E74: LT+L2 | F74: Elenco Conti forniti dall'Ufficio Contabilità da gestire per le svalutazioni Stage 3 | G74: Conti da gestire ai fini delle Svalutazioni Stage 3 | H74: N.A. | I74: tabella ad agggiornamento manuale | J74: Y | K74: NA | L74: NA | M74: N | N74: NA | O74: N | P74: NA | Q74: NA | R74: tutto quello che c'è
A75: GIORNI_SCADUTO | B75: RISCHI E ADEMPIMENTI​ | C75: RISCHI​ | D75: IDL2_73 | E75: L2 | F75: Giorni scaduto per controparte, con dettaglio anche dei giorni scaduto EBA, impiego Eba e Scaduto Impagato Eba | G75: Controparti con un Numero di giorni scaduto >0 | J75: Y | K75: OXDRFPRA | L75: SELECT * FROM FROM OXDRFPRA WHERE DRPRA_GG_SCAD_IMPAGATO_CLI >0 OR DRPRA_GG_SCADUTO_CLI >0 OR DRPRA_GG_SCADUTO_CONT >0; | M75: N | N75: NA | O75: N | P75: NA | Q75: [L1] OXDRFPRA --> A1 --> S2 | R75: --
A76: MORATORIE_M | B76: RISCHI E ADEMPIMENTI​ | C76: RISCHI​ | D76: IDL2_74 | E76: L2 | F76: Moratorie nel mese di ossservazione | G76: pratiche che nel mese hanno una evento di moratoria in corso | J76: Y | K76: CCPSVT | L76: SELECT c.PSVT_PRATICA FROM CCPSVT c LEFT JOIN OXPSFRIO o ON o.oxpsrio_origine_richiesta = c.psvt_motivo_richiesta WHERE o.oxpsrio_origine_richiesta IS NOT NULL; | M76: N | N76: NA | O76: N | P76: NA | Q76: [L1] CCPSVT -> A2 -->S2 [L1] OXPSFRIO --> C --> S1 | R76: in analogia/continuità alla profondità del Forborne
A77: FLESSIBILITA_M | B77: RISCHI E ADEMPIMENTI​ | C77: RISCHI​ | D77: IDL2_76 | E77: L2 | F77: Flessibilità nel mese di ossservazione | G77: pratiche che nel mese hanno una evento di flessiblità in corso | J77: Y | K77: CCPSVT | L77: SELECT c.PSVT_PRATICA FROM CCPSVT c LEFT JOIN PLPSFDAIF p ON p.PLPSDAIF_EV_PSV_RIF = c.PSVT_PROGRESSIVO WHERE c.PSVT_STATO = '30' and c.PSVT_BLOCCO is not null and c.PSVT_AZIONE IN ('RID','RIF') and PSVT_ORIGINE_RICHIESTA = 'FLE' and p.PLPSDAIF_DATA_REG is null; | M77: N | N77: NA | O77: N | P77: NA | Q77: [L1] CCPSVT -> A2 -->S2 [L1] PLPSFDAIF -> A2 -->S2 | R77: in analogia/continuità alla profondità del Forborne
A78: RATE_M | B78: PRODOTTO | C78: PAGAMENTI E CONTABILITA​ | D78: IDL2_70 | E78: L2 | F78: Per ogni pratica è contenute il totale rate per ogni anno/mese di osservazione. E' una situazione del piano di ammortamento consolidata sul mese | G78: Pratiche che hanno rate in corso nel mese di osservazione | H78: OXDRFDET | I78: Inizialmente in "Gestione Crediti" | J78: Y (non lettura diretta) | K78: OXCTFPAFD | M78: N | P78: NA | Q78: OXCTFPAFD --> A2 --> S2
A79: RIMBORSI_M | B79: PRODOTTO | C79: PAGAMENTI E CONTABILITA​ | D79: IDL2_77 | E79: L2 | F79: entità L2 RIMBORSI consolidata sul fine mese | G79: pratiche in OXDRFPRA sul mese di osservazione su cui sono registrati dei rimborsi | J79: Y
A80: LEGAME_PRATICA_CONTROPARTE | B80: ANAGRAFICA​ | C80: ANAGRAFICA CONTROPARTE​ | D80: IDL2_78 | E80: L2 | F80: Entità creata allo scopo di censire la tipologia di rapporto esistente tra una pratica ed una controparte e arricchirlo con informazioni anagrafiche della controparte valide esclusivamente in relazione al rapporto stesso. | G80: Lista delle controparti associate a ciascuna pratica Agos. | H80: BAPRATCT | J80: Y | K80: [L1] BAPRATCT | L80: SELECT BAPCT_NUM_PRATICA FROM BAPRATCT | M80: N | N80: NA | O80: N | P80: NA | Q80: Cluster archivi sorgente: BAPRATCT -> B1 Storicizzazione: S2
A81: CARTE_BLOCCHI | B81: PRODOTTO | C81: CARTE​ | D81: IDL2_79 | E81: L2 | F81: Tabella che rappresenta i blocchi di una carta. Le informazioni sui blocchi, su OCS, sono ridondate su due tabelle: CRCAR e CRCARBLO. In CRCAR è presente uno shift register nel quale sono presenti gli ultimi 10 blocchi, numerati da 1 a 10, di cui il numero 1 è il più vecchio. QUESTA LOGICA NON E' RIPRODOTTA IN DATA WAREHOUSE. La gestione, qui, è sulla base di CRCARBLO, tabella nella quale è fatta l'associazione 1:n tra pratica e blocchi. | G81: Blocchi delle carte. | K81: CRCARBLO | L81: CRCARBLO | M81: N | N81: N | O81: N | P81: N | Q81: [L1] CRCARBLO --> A2 --> S2
A82: CARTOLARIZZAZIONI_M | B82: RISCHI E ADEMPIMENTI​ | C82: RISCHI​ | D82: IDL2_80 | E82: L2 | F82: Tabella che censisce le pratiche cartolarizzate | G82: Pratiche cartolarizzate | K82: LEGAME_CARTOLARIZZAZIONI | L82: SELECT p.SCPRA_NUM_PRATICA, FROM PLSECPRST p INNER JOIN OXDRFPRA o ON p.SCPRA_NUM_PRATICA + 7000000000 = o.DRPRA_PRATICA | M82: Y | N82: PRATICA_M FORBEARANCE_M | O82: Y | Q82: [L1] OXDRFPRA --> A1 --> S3 [L1] PLSECPRA --> B1 --> S1 [L1] PLSECPRST --> A2 --> S2 [L1] OXCNFTRAN --> C --> S1 | R82: in analogia/continuità alla profondità delle anagrafiche pratiche
A83: CFG_RETE_LIVELLI | B83: ANAGRAFICA​ | C83: ANAGRAFICA STRUTTURA COMMERCIALE | D83: IDL2_81 | E83: LT | F83: Tabelle contenente la valorizzazione dei livelli della gerarchia territoriale. La compilazione è in gestione a DMO | I83: OP | K83: NA | L83: NA | M83: N | N83: NA | O83: N | P83: NA | Q83: File Business OP
A84: BUDGET_PROD | B84: BUDGET​ | C84: TBD​ | D84: IDL2_82 | E84: L2 | F84: Tabella dei Budget popolata da file business periodicamente senza scheduling fisso
A85: BUDGET_PROD_RETE | B85: BUDGET​ | C85: TBD​ | D85: IDL2_83 | E85: L2 | F85: Tabella dei Budget popolata da file business periodicamente senza scheduling fisso con aggregazione del Budget a livello di RETE. Tipicamente valorizzato successivamente rispetto al Budget aggregato contenuto in BUDGET_PROD
A86: BUDGET_PROD_FILIALE | B86: BUDGET​ | C86: TBD​ | D86: IDL2_84 | E86: L2 | F86: Tabella dei Budget popolata da file business periodicamente senza scheduling fisso con aggregazione del Budget a livello di FILIALE. Tipicamente valorizzato successivamente rispetto al Budget aggregato contenuto in BUDGET_PROD_RETE
A87: BUDGET_ESTINZIONI_ANT | B87: BUDGET​ | C87: TBD​ | D87: IDL2_85 | E87: L2 | F87: Tabella dei Budget riguardanti le estinzioni anticipate popolata da file business periodicamente senza scheduling fisso.
A88: BUDGET_ESTINZIONI_ANT_RETE | B88: BUDGET​ | C88: TBD​ | D88: IDL2_86 | E88: L2 | F88: Tabella dei Budget popolata da file business periodicamente senza scheduling fisso con aggregazione del Budget a livello di RETE. Tipicamente valorizzato successivamente rispetto al Budget aggregato contenuto in BUDGET_PROD
A89: BUDGET_ESTINZIONI_ANT_FILIALE | B89: BUDGET​ | C89: TBD​ | D89: IDL2_87 | E89: L2 | F89: Tabella dei Budget popolata da file business periodicamente senza scheduling fisso con aggregazione del Budget a livello di FILIALE. Tipicamente valorizzato successivamente rispetto al Budget aggregato contenuto in BUDGET_PROD_RETE
A90: ESTINZIONI_ANTICIPATE_TOT | B90: GESTIONE CREDITI​ | C90: MAIN | D90: IDL2_88 | E90: L2 | F90: Tabelle delle Pratiche Estinte Anticipatamente contiene solo le estinzioni totali (non parziali). | G90: Pratiche Estinte Anticipatamente (PLC_STATO = 55) | I90: da assegnare all'area prodotto | K90: PLCHIEST | M90: N | N90: N | O90: N | P90: N | Q90: [L1] PLPRAT -> B2 [L1] PLCHIEST -> B2 CRCAR -> S4 CACHFEST -> S4
A91: PRESCREENING_INPUT | B91: SCORING & DATA ENRICHMENT​ | C91: SCORING​ | D91: IDL2_89 | E91: L2 | F91: Lista delle informazioni rilevanti in input al sotto processo PRESCREENING del motore CDE | G91: Contenuto dell'apposito sheet del XML prodotto quotidinamento dal CDE. | H91: XML CDE | I91: L'entità non è stata ancora modellata per legame con l'OP AGXDMW1-586 | K91: L1_E_CDE.CDE | L91: SELECT VALUE AS XML FROM L1_E_CDE.CDE WHERE XMLGET(XMLGET(XMLGET(VALUE, 'StrategyOneRequest'), 'Header'), 'ProcessCode'):"$"::VARCHAR = 'PRESCREENING' | M91: NA | N91: NA | O91: NA | P91: NA | Q91: S2
A92: PRECRIF_INPUT | B92: SCORING & DATA ENRICHMENT​ | C92: SCORING​ | D92: IDL2_90 | E92: L2 | F92: Lista delle informazioni rilevanti in input al sotto processo PRECRIF del motore CDE | G92: Contenuto dell'apposito sheet del XML prodotto quotidinamento dal CDE | H92: XML CDE | I92: L'entità non è stata ancora modellata per legame con l'OP AGXDMW1-586 | K92: L1_E_CDE.CDE | L92: SELECT VALUE AS XML FROM L1_E_CDE.CDE WHERE XMLGET(XMLGET(XMLGET(VALUE, 'StrategyOneRequest'), 'Header'), 'ProcessCode'):"$"::VARCHAR = 'PRECRIF' | M92: NA | N92: NA | O92: NA | P92: NA | Q92: S2
A93: SCORING_INPUT | B93: SCORING & DATA ENRICHMENT​ | C93: SCORING​ | D93: IDL2_91 | E93: L2 | F93: Lista delle informazioni rilevanti in input al sotto processo SCORING del motore CDE | G93: Contenuto dell'apposito sheet del XML prodotto quotidinamento dal CDE | H93: XML CDE | I93: L'entità non è stata ancora modellata per legame con l'OP AGXDMW1-586 | K93: L1_E_CDE.CDE | L93: SELECT VALUE AS XML FROM L1_E_CDE.CDE WHERE XMLGET(XMLGET(XMLGET(VALUE, 'StrategyOneRequest'), 'Header'), 'ProcessCode'):"$"::VARCHAR = 'SCORING' | M93: NA | N93: NA | O93: NA | P93: NA | Q93: S2
A94: DBRSCIPA_INPUT | B94: SCORING & DATA ENRICHMENT​ | C94: SCORING​ | D94: IDL2_92 | E94: L2 | F94: Lista delle informazioni rilevanti in input al sotto processo DBRSCIPA del motore CDE | G94: Contenuto dell'apposito sheet del XML prodotto quotidinamento dal CDE | H94: XML CDE | I94: L'entità non è stata ancora modellata per legame con l'OP AGXDMW1-586 | K94: L1_E_CDE.CDE | L94: SELECT VALUE AS XML FROM L1_E_CDE.CDE WHERE XMLGET(XMLGET(XMLGET(VALUE, 'StrategyOneRequest'), 'Header'), 'ProcessCode'):"$"::VARCHAR = 'DBRSCIPA' | M94: NA | N94: NA | O94: NA | P94: NA | Q94: S2
A95: ACCETTAZIONE_INPUT | B95: SCORING & DATA ENRICHMENT​ | C95: SCORING​ | D95: IDL2_152 | E95: L2 | F95: Lista delle informazioni rilevanti in input al sotto processo ACCETTAZIONE del motore CDE | G95: Contenuto dell'apposito sheet del XML prodotto quotidinamento dal CDE | H95: XML CDE | I95: L'entità non è stata ancora modellata per legame con l'OP AGXDMW1-586 | K95: L1_E_CDE.CDE | L95: SELECT VALUE AS XML FROM L1_E_CDE.CDE WHERE XMLGET(XMLGET(XMLGET(VALUE, 'StrategyOneRequest'), 'Header'), 'ProcessCode'):"$"::VARCHAR = 'TARGATO' | M95: NA | N95: NA | O95: NA | P95: NA | Q95: S2
A96: ACCETTAZIONE_INPUT_OB | B96: SCORING & DATA ENRICHMENT​ | C96: SCORING​ | D96: IDL2_153 | E96: L2 | F96: Lista delle informazioni rilevanti in output al sotto processo ACCETTAZIONE del motore CDE in merito alle policy rules. | G96: Contenuto dell'apposito sheet del XML prodotto quotidinamento dal CDE | H96: XML CDE | I96: L'entità non è stata ancora modellata per legame con l'OP AGXDMW1-586 | K96: L1_E_CDE.CDE | L96: SELECT VALUE AS XML FROM L1_E_CDE.CDE WHERE XMLGET(XMLGET(XMLGET(VALUE, 'StrategyOneRequest'), 'Header'), 'ProcessCode'):"$"::VARCHAR = 'TARGATO' | M96: NA | N96: NA | O96: NA | P96: NA | Q96: S2
A97: ACCETTAZIONE_INPUT_CAT_AGG | B97: SCORING & DATA ENRICHMENT​ | C97: SCORING​ | D97: IDL2_154 | E97: L2 | F97: Lista delle informazioni rilevanti in input al sotto processo ACCETTAZIONE del motore CDE | G97: Contenuto dell'apposito sheet del XML prodotto quotidinamento dal CDE | H97: XML CDE | I97: L'entità non è stata ancora modellata per legame con l'OP AGXDMW1-586 | K97: L1_E_CDE.CDE | L97: SELECT VALUE AS XML FROM L1_E_CDE.CDE WHERE XMLGET(XMLGET(XMLGET(VALUE, 'StrategyOneRequest'), 'Header'), 'ProcessCode'):"$"::VARCHAR = 'TARGATO' | M97: NA | N97: NA | O97: NA | P97: NA | Q97: S2
A98: ACCETTAZIONE_INPUT_PRAT_PREC | B98: SCORING & DATA ENRICHMENT​ | C98: SCORING​ | D98: IDL2_155 | E98: L2 | F98: Lista delle informazioni rilevanti in input al sotto processo ACCETTAZIONE del motore CDE | G98: Contenuto dell'apposito sheet del XML prodotto quotidinamento dal CDE | H98: XML CDE | I98: L'entità non è stata ancora modellata per legame con l'OP AGXDMW1-586 | K98: L1_E_CDE.CDE | L98: SELECT VALUE AS XML FROM L1_E_CDE.CDE WHERE XMLGET(XMLGET(XMLGET(VALUE, 'StrategyOneRequest'), 'Header'), 'ProcessCode'):"$"::VARCHAR = 'TARGATO' | M98: NA | N98: NA | O98: NA | P98: NA | Q98: S2
A99: RBPCORTO_INPUT | B99: SCORING & DATA ENRICHMENT​ | C99: SCORING​ | D99: IDL2_94 | E99: L2 | F99: Lista delle informazioni rilevanti in input al sotto processo AGRBPCORTO del motore CDE | G99: Contenuto dell'apposito sheet del XML prodotto quotidinamento dal CDE | H99: XML CDE | I99: L'entità non è stata ancora modellata per legame con l'OP AGXDMW1-586 | K99: L1_E_CDE.CDE | L99: SELECT VALUE AS XML FROM L1_E_CDE.CDE WHERE XMLGET(XMLGET(XMLGET(VALUE, 'StrategyOneRequest'), 'Header'), 'ProcessCode'):"$"::VARCHAR = 'RBPCORTO' | M99: NA | N99: NA | O99: NA | P99: NA | Q99: S2
A100: CUMRIS_INPUT | B100: SCORING & DATA ENRICHMENT​ | C100: SCORING​ | D100: IDL2_156 | E100: L2 | F100: Lista delle informazioni rilevanti in output al sotto processo DBRSCIPA del motore CDE | G100: Contenuto dell'apposito sheet del XML prodotto quotidinamento dal CDE | H100: XML CDE | I100: L'entità non è stata ancora modellata per legame con l'OP AGXDMW1-586 | K100: L1_E_CDE.CDE | L100: SELECT VALUE AS XML FROM L1_E_CDE.CDE WHERE XMLGET(XMLGET(XMLGET(VALUE, 'StrategyOneRequest'), 'Header'), 'ProcessCode'):"$"::VARCHAR = 'CUMRIS' | M100: NA | N100: NA | O100: NA | P100: NA | Q100: S2
...

Sheet SOCIODEMO_OLD
D1: Dominio del campo STATO: "Validato per processo X": campi che abbiamo validato e non ci aspettiamo di toccare più (nessun OP legato) "In Validazione per processo X": tutti gli altri stati N.B. è possibile inserire "Validato per processo generico"/ "In Validazione per processo generico" se il campo è emerso senza un legame con un processo specifico | E1: CONSUMO | H1: CARTE
A2: CATEGORIA CAMPO | B2: NOME CAMPO | C2: DESCRIZIONE | D2: STATO (CAMPO VALIDATO / IN VALIDAZIONE) | E2: SORGENTE TABELLA OCS L1 | F2: SORGENTE CAMPI OCS L1 | G2: REGOLA FUNZIONALE | H2: SORGENTE TABELLA OCS L1 | I2: SORGENTE CAMPI OCS L1 | J2: REGOLA FUNZIONALE | K2: NOTE
A3: Identificativo Pratica | B3: CD_PRATICA | C3: Codice Pratica | D3: Validato per Campioni, Monitoraggio Accettazione, validato per IFRS9 | K3: + OP 556 impatti IFRS9
B4: TP_PROCEDURA | C4: Tipologia procedura | D4: Validato per Campioni, Monitoraggio Accettazione, validato per IFRS9 | K4: + OP 556 impatti IFRS9
A5: Tempo | B5: DT_OSSERVAZIONE | C5: Periodo Osservazione | D5: Validato per Campioni, Monitoraggio Accettazione, validato per IFRS9 | K5: + OP 556 impatti IFRS9
A6: Identificativo Controparte | B6: CD_CONTROPARTE | C6: Codice Controparte | D6: Validato per Campioni, Monitoraggio Accettazione, validato per IFRS9 | K6: + OP 556 impatti IFRS9
B7: TP_RAPPORTO | C7: Tipologia Rapporto | D7: Validato per Campioni, Monitoraggio Accettazione, validato per IFRS9 | K7: + OP 556 impatti IFRS9
B8: TP_CONTROPARTE | C8: Tipologia Controparte | D8: Validato per Campioni, Monitoraggio Accettazione, validato per IFRS9 | K8: + OP 556 impatti IFRS9
A9: Cliente | B9: CD_CLIENTE_CTC | C9: Codice CTC Cliente | D9: Validato per Campioni, Monitoraggio Accettazione, validato per IFRS9 | K9: + OP 556 impatti IFRS9
B10: CD_COOBLIGATO_CTC | C10: Codice CTC Coobligato | D10: Validato per Campioni, Monitoraggio Accettazione, validato per IFRS9 | K10: + OP 556 impatti IFRS9
B11: CD_CLIENTE | C11: Codice Cliente Agos | D11: Validato per Campioni, Monitoraggio Accettazione, validato per IFRS9 | K11: + OP 556 impatti IFRS9
B12: CD_COOBLIGATO | C12: Codice Coobligato Agos | D12: Validato per Campioni, Monitoraggio Accettazione, validato per IFRS9 | K12: + OP 556 impatti IFRS9
A13: Date | B13: DT_CARIC_ULT_PP_REMOTO | C13: Data di caricamento ultima pratica di prestito personale dell’ambiente remoto | D13: Validato per Campioni, Monitoraggio Accettazione, validato per IFRS9 | K13: + OP 556 impatti IFRS9
B14: DT_ULTIMA_MORA | C14: Data ultima mora | D14: Validato per Campioni, Monitoraggio Accettazione, validato per IFRS9 | K14: + OP 556 impatti IFRS9
B15: DT_PRIMO_UTILIZZO | C15: Data di primo utilizzo | D15: Validato per Campioni, Monitoraggio Accettazione, validato per IFRS9 | E15: BAPRATPD | F15: BAPRATPD.BAP_DATA_U | H15: BAPRATPD | I15: BAPRATPD.BAP_DATA_U
B16: DT_INIZIO_RAPP_CLIE | C16: Data inizio rapporto cliente | D16: Validato per Campioni, Monitoraggio Accettazione, validato per IFRS9 | K16: + OP 556 impatti IFRS9
B17: DT_APERTURA_PRIMA_PRATICA | C17: Data apertura prima pratica | D17: In validazione per Monitoraggio Accettazione, validato per IFRS9 | K17: + OP 556 impatti IFRS9
A18: Dati Anagrafica (generici) | B18: CD_SESSO_CLIENTE | C18: Codice Sesso Cliente | D18: Validato per Campioni, Monitoraggio Accettazione, validato per IFRS9 | K18: + OP 556 impatti IFRS9
B19: CD_CITTADINANZA | C19: Codice cittadinanza cliente | D19: Validato per Campioni, Monitoraggio Accettazione, validato per IFRS9 | K19: + OP 556 impatti IFRS9
B20: NM_FAMILIARI | C20: Numero familiari | D20: Validato per Campioni, Monitoraggio Accettazione, validato per IFRS9 | K20: + OP 556 impatti IFRS9
B21: CD_STATO_CIVILE | C21: Codice stato civile cliente | D21: Validato per Campioni, Monitoraggio Accettazione, validato per IFRS9 | K21: + OP 556 impatti IFRS9
B22: CD_STATO_CIVILE_COOBLIGATO | C22: Codice Stato Civile Coobbligato | D22: Validato per Campioni, Monitoraggio Accettazione, validato per IFRS9 | K22: + OP 556 impatti IFRS9
B23: CD_CONIUGE_GARANTE | C23: Flag Coniuge garante | D23: Validato per Campioni, Monitoraggio Accettazione, validato per IFRS9 | K23: + OP 556 impatti IFRS9
B24: CD_FORMA_GIURIDICA | C24: Codice Forma Giuridica | D24: Validato per Campioni, Monitoraggio Accettazione, validato per IFRS9 | E24: OXANFVAN | F24: OXANFVAN.AC_FORMA_GIURIDICA | H24: OXANFVAN | I24: OXANFVAN.AC_FORMA_GIURIDICA
B25: DT_NASCITA_CLIENTE | C25: Data di nascita cliente | D25: Validato per Campioni, Monitoraggio Accettazione, validato per IFRS9 | K25: + OP 556 impatti IFRS9
B26: CD_PROVINCIA_NASCITA | C26: Codice Provincia Nascita cliente | D26: Validato per Campioni, Monitoraggio Accettazione, validato per IFRS9 | K26: + OP 556 impatti IFRS9
B27: CD_QUALITA_CLIE | C27: Codice Qualità Cliente | D27: Validato per Campioni, Monitoraggio Accettazione, validato per IFRS9 | K27: + OP 556 impatti IFRS9
B28: CD_QUALITA_CONV | C28: Codice Qualità Convenzionato | D28: Validato per Campioni, Monitoraggio Accettazione, validato per IFRS9 | K28: + OP 556 impatti IFRS9
B29: CD_TIPO_AZIENDA_CLI | C29: Tipo azienda cliente | D29: Validato per Campioni, Monitoraggio Accettazione, validato per IFRS9 | K29: + OP 556 impatti IFRS9
B30: DT_INIZIO_RAPP_BANCA | C30: Data inizio rapporto banca | D30: Validato per Campioni, Monitoraggio Accettazione, validato per IFRS9 | K30: + OP 556 impatti IFRS9
B31: TP_PRATICA_INTERNET | C31: Tipo Pratica Internet | D31: Validato per Campioni, Monitoraggio Accettazione, validato per IFRS9 | K31: + OP 556 impatti IFRS9
B32: NM_PRATICHE_CLIENTE | C32: Pratiche precedentemente liquidate per lo stesso cliente | D32: In validazione per Monitoraggio Accettazione, validato per IFRS9 | K32: + OP 556 impatti IFRS9
A33: Dati Anagrafica (attività) | B33: TP_ATTIVITA | C33: Tipo attività, lavoro del cliente: Autonomo, dipendente, Pensionato | D33: Validato per No Start, Monitoraggio Accettazione, validato per IFRS9 | E33: BAPRATCT | F33: BAPCT_QUALIFICA | H33: BAPRATCT | I33: BAPCT_QUALIFICA
B34: CD_SETT_ATTIVITA_COOBLIGATO | C34: settore attività coobligato | D34: Validato per Campioni, Monitoraggio Accettazione, validato per IFRS9 | K34: + OP 556 impatti IFRS9
B35: CD_SETT_ATTIVITA_CLIENTE | C35: settore attività cliente | D35: Validato per Campioni, Monitoraggio Accettazione, validato per IFRS9 | K35: + OP 556 impatti IFRS9
B36: CD_OCCUPAZIONE | C36: Codice Occupazione | D36: Validato per Campioni, Monitoraggio Accettazione, validato per IFRS9 | K36: + OP 556 impatti IFRS9
B37: DT_INIZIO_OCCUP | C37: data occupazione cliente | D37: Validato per Campioni, Monitoraggio Accettazione, validato per IFRS9 | K37: + OP 556 impatti IFRS9
B38: TP_CONTRATTO_LAVORO | C38: tipo contratto: tempo det/indet | D38: Validato per Campioni, Monitoraggio Accettazione, validato per IFRS9 | E38: BAPRATCT | F38: BAPCT_TIPO_CONTRATTO
B39: NM_MESI_DURATA | C39: Durata contratto lavoro | D39: Validato per Campioni, Monitoraggio Accettazione, validato per IFRS9 | K39: + OP 556 impatti IFRS9
B40: NM_MENSILITA_CLIENTE | C40: Numero mensilità cliente | D40: In validazione per Monitoraggio Accettazione, validato per IFRS9 | E40: BAPRATCT | F40: BAPCT_NUM_MENSILITA | H40: BAPRATCT | I40: BAPCT_NUM_MENSILITA
B41: NM_MENSILITA_COOBLIGATO | C41: Numero mensilità coobligato | D41: In validazione per Monitoraggio Accettazione, validato per IFRS9 | E41: BAPRATCT | F41: BAPCT_NUM_MENSILITA | H41: BAPRATCT | I41: BAPCT_NUM_MENSILITA
A42: Dati Anagrafica (abitazione e residenza) | B42: CD_ABITAZIONE | C42: codice abitazione Cliente | D42: Validato per Campioni, Monitoraggio Accettazione, validato per IFRS9 | K42: + OP 556 impatti IFRS9
B43: TP_ABITAZIONE | C43: Tipo Abitazione cliente | D43: Validato per Campioni, Monitoraggio Accettazione, validato per IFRS9 | K43: + OP 556 impatti IFRS9
B44: TP_LOCAZIONE | C44: Tipo Locazione | D44: Validato per Campioni, Monitoraggio Accettazione, validato per IFRS9 | K44: + OP 556 impatti IFRS9
B45: DT_INIZIO_INDIR | C45: data inizio validità indirizzo residenza | D45: Validato per Campioni, Monitoraggio Accettazione, validato per IFRS9 | K45: + OP 556 impatti IFRS9
B46: CD_PROVINCIA_RESIDENZA | C46: Codice Provincia Residenza cliente | D46: Validato per Campioni, Monitoraggio Accettazione, validato per IFRS9 | K46: + OP 556 impatti IFRS9
B47: CD_REGIONE_CLIENTE | C47: Codice Regione Residenza | D47: Validato per Campioni, Monitoraggio Accettazione, validato per IFRS9 | K47: + OP 556 impatti IFRS9
B48: CD_PROVEN_COMMERC | C48: Codice Provenienza Commerciale | D48: Validato per Campioni, Monitoraggio Accettazione, validato per IFRS9 | K48: + OP 556 impatti IFRS9
A49: Dati Anagrafica (postalizzazione) | B49: DS_COR_INDIRIZZO_1 | C49: Indirizzo di postalizzazione | D49: In validazione per Indirizzi da Monitorare, validato per IFRS9 | E49: BAPRATAG | F49: BAAG_COR_INDIRIZZO_1 | H49: BAPRATAG | I49: BAAG_COR_INDIRIZZO_1
B50: DS_COR_INDIRIZZO_2 | C50: Indirizzo di postalizzazione | D50: In validazione per Indirizzi da Monitorare, validato per IFRS9 | E50: BAPRATAG | F50: BAAG_COR_INDIRIZZO_2 | H50: BAPRATAG | I50: BAAG_COR_INDIRIZZO_2
B51: DS_COR_COMUNE | C51: Comune di postalizzazione | D51: In validazione per Indirizzi da Monitorare, validato per IFRS9 | E51: BAPRATAG | F51: BAAG_COR_LOCALITA | H51: BAPRATAG | I51: BAAG_COR_LOCALITA
B52: DS_COR_NAZIONE | C52: Nazione di postalizzazione | D52: In validazione per Indirizzi da Monitorare, validato per IFRS9 | E52: BAPRATAG | F52: BAAG_COR_NAZIONE | H52: BAPRATAG | I52: BAAG_COR_NAZIONE
A53: Dati Reddito | B53: EU_ALTRI_REDDITI | C53: Importo Altri Redditi | D53: Validato per Campioni, Monitoraggio Accettazione, validato per IFRS9 | K53: + OP 556 impatti IFRS9
B54: EU_REDDITO_ANNUO_CLIENTE | C54: Importo reddito annuo cliente | D54: Validato per Campioni, Monitoraggio Accettazione, validato per IFRS9 | K54: + OP 556 impatti IFRS9
B55: EU_REDDITO_COOBLIGATO | C55: Importo Reddito Coobligato | D55: Validato per Campioni, Monitoraggio Accettazione, validato per IFRS9 | K55: + OP 556 impatti IFRS9
B56: EU_REDDITO_FAMIGLIARE | C56: Importo redditi familiari | D56: Validato per Campioni, Monitoraggio Accettazione, validato per IFRS9 | K56: + OP 556 impatti IFRS9
B57: EU_ALTRI_REDDITI_COOBLIGATO | C57: Importo altri redditi coobligato | D57: Validato per Campioni, Monitoraggio Accettazione, validato per IFRS9 | K57: + OP 556 impatti IFRS9
A58: Flag | B58: FL_DEPOSITO_BANCARIO | C58: Flag Deposito Bancario cliente | D58: Validato per Campioni, Monitoraggio Accettazione, validato per IFRS9 | K58: + OP 556 impatti IFRS9
B59: FL_DEPOSITO_BANCARIO_COOBLIGATO | C59: Flag Deposito Bancario coobligato | D59: Validato per Campioni, Monitoraggio Accettazione, validato per IFRS9 | K59: + OP 556 impatti IFRS9
B60: FL_CONTO_BANCARIO | C60: Flag Conto Bancario | D60: Validato per Campioni, Monitoraggio Accettazione, validato per IFRS9 | K60: + OP 556 impatti IFRS9
B61: FL_CONTO_BANCARIO_COOBLIGATO | C61: Flag Conto Bancario Coobligato | D61: Validato per Campioni, Monitoraggio Accettazione, validato per IFRS9 | K61: + OP 556 impatti IFRS9
B62: FL_NUOVO_CLIENTE | C62: Clienti che hanno aperto un rapporto nell'anno corrente | D62: Validato per Campioni, Monitoraggio Accettazione, validato per IFRS9 | K62: + OP 556 impatti IFRS9
B63: FL_FIRMA_DOPPIA | C63: flag firma doppia (allo score) | D63: Validato per Campioni, Monitoraggio Accettazione, validato per IFRS9 | K63: + OP 556 impatti IFRS9
A64: Importi | B64: EU_CUMULO_RISCHIO_COOBLIGATO | C64: Importo Cumulo Rischio Agos (Coobbligato) | D64: Validato per Campioni, Monitoraggio Accettazione, validato per IFRS9 | K64: + OP 556 impatti IFRS9
B65: EU_CUMULO_RISCHIO_CLIENTE | C65: Importo Cumulo Rischio Agos (Cliente) attribuito, override | D65: Validato per Campioni, Monitoraggio Accettazione, validato per IFRS9 | K65: + OP 556 impatti IFRS9
B66: EU_CUMULO_RISCHIO_CRIF_CLIENTE | C66: Importo Cumulo Rischio Crif (Cliente) attribuito, override | D66: Validato per Campioni, Monitoraggio Accettazione, validato per IFRS9 | K66: + OP 556 impatti IFRS9
B67: EU_CUMULO_RISCHIO_CRIF_COOBLIGATO | C67: Importo Cumulo Rischio Crif (Coobligato) | D67: Validato per Campioni, Monitoraggio Accettazione, validato per IFRS9 | K67: + OP 556 impatti IFRS9
B68: EU_COMMISSIONE | C68: Importo Commissioni | D68: Validato per Campioni, Monitoraggio Accettazione, validato per IFRS9 | K68: + OP 556 impatti IFRS9
B69: EU_DEPOS_BANCA_COOBLIGATO | C69: Importo deposito bancario cocobligato | D69: Validato per Campioni, Monitoraggio Accettazione, validato per IFRS9 | K69: + OP 556 impatti IFRS9
B70: EU_FIDO | C70: Importo fido cliente | D70: Validato per Campioni, Monitoraggio Accettazione, validato per IFRS9 | K70: + OP 556 impatti IFRS9
B71: EU_FIDO_COOBLIGATO | C71: Importo fido coobligato | D71: Validato per Campioni, Monitoraggio Accettazione, validato per IFRS9 | K71: + OP 556 impatti IFRS9
B72: EU_FINANZIATO | C72: Importo finanziato | D72: Validato per Campioni, Monitoraggio Accettazione, validato per IFRS9 | K72: + OP 556 impatti IFRS9
B73: EU_FINANZIATO_COOBLIGATO | C73: Importo finanziato Coobligato | D73: Validato per Campioni, Monitoraggio Accettazione, validato per IFRS9 | K73: + OP 556 impatti IFRS9
B74: EU_IMPIEGHI_CLIENTE | C74: Impieghi Cliente | D74: Validato per Campioni, Monitoraggio Accettazione, validato per IFRS9 | K74: + OP 556 impatti IFRS9
B75: EU_IMPIEGHI_COOBLIGATO | C75: Impieghi coob | D75: Validato per Campioni, Monitoraggio Accettazione, validato per IFRS9 | K75: + OP 556 impatti IFRS9
B76: EU_RATA | C76: Importo rata primo periodo | D76: Validato per Campioni, Monitoraggio Accettazione, validato per IFRS9 | K76: + OP 556 impatti IFRS9
... B80: EU_RATA_CRIF_COOBLIGATO | C80: Importo rata Crif Coobligato | D80: Validato per Campioni, Monitoraggio Accettazione, validato per IFRS9 | K80: + OP 556 impatti IFRS9
B81: EU_ALTR_USC_CLI | C81: Somma delle uscite mensili del Cliente dichiarate in istruttoria esclusa l'eventuale rata e altri prestiti. Es. Affitto | D81: In validazione per Monitoraggio Accettazione, validato per IFRS9 | E81: BAPRATCT | F81: BAPCT_IMP_TIPO_USCITA_1 BAPCT_IMP_TIPO_USCITA_2 BAPCT_IMP_TIPO_USCITA_3 BAPCT_IMP_TIPO_USCITA_4 BAPCT_IMP_TIPO_USCITA_5 | G81: Somma dei campi | H81: BAPRATCT | I81: BAPCT_IMP_TIPO_USCITA_1 BAPCT_IMP_TIPO_USCITA_2 BAPCT_IMP_TIPO_USCITA_3 BAPCT_IMP_TIPO_USCITA_4 BAPCT_IMP_TIPO_USCITA_5 | J81: Somma dei campi
B82: EU_ALTR_USC_COBLGT | C82: Somma delle uscite mensili del Coobligato dichiarate in istruttoria esclusa l'eventuale rata e altri prestiti. Es. Affitto | D82: In validazione per Monitoraggio Accettazione, validato per IFRS9 | E82: BAPRATCT | F82: BAPCT_IMP_TIPO_USCITA_1 BAPCT_IMP_TIPO_USCITA_2 BAPCT_IMP_TIPO_USCITA_3 BAPCT_IMP_TIPO_USCITA_4 BAPCT_IMP_TIPO_USCITA_5 | G82: Somma dei campi | H82: BAPRATCT | I82: BAPCT_IMP_TIPO_USCITA_1 BAPCT_IMP_TIPO_USCITA_2 BAPCT_IMP_TIPO_USCITA_3 BAPCT_IMP_TIPO_USCITA_4 BAPCT_IMP_TIPO_USCITA_5 | J82: Somma dei campi
A83: Negatività (Svalutazioni, Morosità, Protesti e Insolvenze) | B83: NM_MOROSITA | C83: Numero morosità cliente | D83: Validato per Campioni, Monitoraggio Accettazione, validato per IFRS9 | K83: + OP 556 impatti IFRS9
B84: EU_MOROSITA | C84: Importo Morosità | D84: Validato per Campioni, Monitoraggio Accettazione, validato per IFRS9 | K84: + OP 556 impatti IFRS9
B85: EU_MOROSITA_COOBLIGATO | C85: Importo Morosità Coobligato | D85: Validato per Campioni, Monitoraggio Accettazione, validato per IFRS9 | K85: + OP 556 impatti IFRS9
B86: NM_PROTESTI | C86: Numero protesti cliente | D86: Validato per Campioni, Monitoraggio Accettazione, validato per IFRS9 | K86: + OP 556 impatti IFRS9
B87: NM_PROTESTI_COOBLIGATO | C87: Numero protesti coobligato | D87: Validato per Campioni, Monitoraggio Accettazione, validato per IFRS9 | K87: + OP 556 impatti IFRS9
B88: DT_ULTIMO_PROTESTO | C88: Data ultimo Protesto | D88: Validato per Campioni, Monitoraggio Accettazione, validato per IFRS9 | K88: + OP 556 impatti IFRS9
B89: EU_PROTESTI_CLIENTE | C89: Importo protesti (valore complessivo dei titoli di credito non pagati) | D89: Validato per Campioni, Monitoraggio Accettazione, validato per IFRS9 | K89: + OP 556 impatti IFRS9
B90: EU_PROTESTI_COOBLIGATO | C90: Importo protesti coobligato | D90: Validato per Campioni, Monitoraggio Accettazione, validato per IFRS9 | K90: + OP 556 impatti IFRS9
A91: Informazioni Carta | B91: TP_ORGANIZZAZIONE_CARTA | C91: Tipo organizzazione carta | D91: Validato per Campioni, Monitoraggio Accettazione, validato per IFRS9 | K91: + OP 556 impatti IFRS9
B92: CD_ORGANIZZAZIONE_CARTA | C92: Codice Organizzazione Carta | D92: Validato per Campioni, Monitoraggio Accettazione, validato per IFRS9 | K92: + OP 556 impatti IFRS9
B93: CD_BLOCCO | C93: Presenza di Blocco Carta | D93: Validato per Campioni, Monitoraggio Accettazione, validato per IFRS9 | H93: BAPRATCT | I93: BAPCT_BLOCCO
B94: DS_BLOCCO | C94: Tipologia di blocco da gestire | D94: Validato per Campioni, Monitoraggio Accettazione, validato per IFRS9 | H94: BAPRATCT | I94: BAPCT_TIPO_BLOCCO
A95: Modalità di pagamento | B95: NM_CESSIONE_BUSTA_PAGA_CLIENTE | C95: Numero cessione del quinto busta paga | D95: Validato per Campioni, Monitoraggio Accettazione, validato per IFRS9 | K95: + OP 556 impatti IFRS9
B96: TP_PAGAMENTO | C96: Tipo pagamento allo score | D96: Validato per Campioni, Monitoraggio Accettazione, validato per IFRS9 | K96: + OP 556 impatti IFRS9
B97: TP_RIPAGAMENTO | C97: Tipo Ripagamento allo score | D97: Validato per Campioni, Monitoraggio Accettazione, validato per IFRS9 | K97: + OP 556 impatti IFRS9
A98: Prodotto | B98: CD_TAB_FINANZ | C98: Tabella finanziaria rilevato in fase di sitruttoria | D98: Validato per Campioni, Monitoraggio Accettazione, validato per IFRS9 | K98: + OP 556 impatti IFRS9
B99: CD_TIPO_TASSO | C99: Tipo tasso rilevato in fase di sitruttoria | D99: Validato per Campioni, Monitoraggio Accettazione, validato per IFRS9 | K99: + OP 556 impatti IFRS9
B100: NM_RATE | C100: Numero rate / Numero rate primo periodo | D100: In validazione per Monitoraggio Accettazione, validato per IFRS9 | K100: + OP 556 impatti IFRS9
B101: NM_RATE_2 | C101: Numero rate secondo periodo | D101: In validazione per Monitoraggio Accettazione, validato per IFRS9 | K101: + OP 556 impatti IFRS9
A102: Score | B102: CD_CBSCORE_CRIF_CLIE | C102: CB score Crif Plus Cliente (da gen 2011 versione Perform) | D102: Validato per Campioni, Monitoraggio Accettazione, validato per IFRS9 | K102: + OP 556 impatti IFRS9
B103: CD_CBSCORE_CRIF_ULT_CO | C103: CB Score Crif Ultimo Contratto Consumo | D103: Validato per Campioni, Monitoraggio Accettazione, validato per IFRS9 | K103: + OP 556 impatti IFRS9
...

Sheet SOCIODEMO_SCORE_OLD
B1: ORE | D1: Dominio del campo STATO: "Validato per processo X": campi che abbiamo validato e non ci aspettiamo di toccare più (nessun OP legato) "In Validazione per processo X": tutti gli altri stati N.B. è possibile inserire "Validato per processo generico"/ "In Validazione per processo generico" se il campo è emerso senza un legame con un processo specifico | E1: CONSUMO | H1: CARTE
A2: CATEGORIA CAMPO | B2: NOME CAMPO | C2: DESCRIZIONE | D2: STATO (CAMPO VALIDATO / IN VALIDAZIONE) | E2: SORGENTE TABELLA OCS L1 | F2: SORGENTE CAMPI OCS L1 | G2: REGOLA FUNZIONALE | H2: SORGENTE TABELLA OCS L1 | I2: SORGENTE CAMPI OCS L1 | J2: REGOLA FUNZIONALE | K2: NOTE
A3: Identificativo Pratica | B3: CD_PRATICA | C3: Codice Pratica | D3: In Validazione per Campioni, Validato per IFRS9 | K3: + OP 556 impatti IFRS9
B4: TP_PROCEDURA | C4: Tipologia procedura | D4: In Validazione per Campioni, Validato per IFRS9 | K4: + OP 556 impatti IFRS9
A5: Tempo | B5: DT_OSSERVAZIONE | C5: Periodo Osservazione | D5: In Validazione per Campioni, Validato per IFRS9 | K5: + OP 556 impatti IFRS9
A6: Identificativo Controparte | B6: CD_CONTROPARTE | C6: Codice Controparte | D6: In Validazione per Campioni, Validato per IFRS9 | K6: + OP 556 impatti IFRS9
B7: TP_RAPPORTO | C7: Tipologia Rapporto | D7: In Validazione per Campioni, Validato per IFRS9 | K7: + OP 556 impatti IFRS9
B8: TP_CONTROPARTE | C8: Tipologia Controparte | D8: In Validazione per Campioni, Validato per IFRS9 | K8: + OP 556 impatti IFRS9
A9: Cliente | B9: CD_CLIENTE_CTC | C9: Codice CTC Cliente | D9: In Validazione per Campioni, Validato per IFRS9 | K9: + OP 556 impatti IFRS9
B10: CD_COOBLIGATO_CTC | C10: Codice CTC Coobligato | D10: In Validazione per Campioni, Validato per IFRS9 | K10: + OP 556 impatti IFRS9
B11: CD_CLIENTE | C11: Codice Cliente Agos | D11: In Validazione per Campioni, Validato per IFRS9 | K11: + OP 556 impatti IFRS9
B12: CD_COOBLIGATO | C12: Codice Coobligato Agos | D12: In Validazione per Campioni, Validato per IFRS9 | K12: + OP 556 impatti IFRS9
A13: Date | B13: DT_CARIC_ULT_PP_REMOTO | C13: Data di caricamento ultima pratica di prestito personale dell’ambiente remoto. Rappresenta l'informazione generata in istruttoria e non viene modificata in postvendita | D13: In Validazione per Campioni, Validato per IFRS9 | K13: + OP 556 impatti IFRS9
B14: DT_ULTIMA_MORA | C14: Data ultima mora. Rappresenta l'informazione generata in istruttoria e non viene modificata in postvendita | D14: In Validazione per Campioni, Validato per IFRS9 | K14: + OP 556 impatti IFRS9
B15: DT_PRIMO_UTILIZZO | C15: Data di primo utilizzo. Rappresenta l'informazione generata in istruttoria e non viene modificata in postvendita | D15: In Validazione per Campioni, Validato per IFRS9 | E15: BAPRATPD | F15: BAPRATPD.BAP_DATA_U | H15: BAPRATPD | I15: BAPRATPD.BAP_DATA_U
B16: DT_INIZIO_RAPP_CLIE | C16: Data inizio rapporto cliente. Rappresenta l'informazione generata in istruttoria e non viene modificata in postvendita | D16: In Validazione per Campioni, Validato per IFRS9 | K16: + OP 556 impatti IFRS9
B17: DT_APERTURA_PRIMA_PRATICA | C17: Data apertura prima pratica. Rappresenta l'informazione generata in istruttoria e non viene modificata in postvendita | D17: In validazione per Monitoraggio Accettazione, Validato per IFRS9 | K17: Legato a sviluppi che si faranno tra Febbraio e Giugno 26 + OP 556 impatti IFRS9
A18: Dati Anagrafica (generici) | B18: CD_SESSO_CLIENTE | C18: Codice Sesso Cliente. Rappresenta l'informazione generata in istruttoria e non viene modificata in postvendita | D18: In Validazione per Campioni, Validato per IFRS9 | K18: + OP 556 impatti IFRS9
B19: CD_CITTADINANZA | C19: Codice cittadinanza cliente. Rappresenta l'informazione generata in istruttoria e non viene modificata in postvendita | D19: In Validazione per Campioni, Monitoraggio Accettazione, Validato per IFRS9 | K19: + OP 556 impatti IFRS9
B20: NM_FAMILIARI | C20: Numero familiari. Rappresenta l'informazione generata in istruttoria e non viene modificata in postvendita | D20: In Validazione per Campioni, Validato per IFRS9 | K20: + OP 556 impatti IFRS9
B21: CD_STATO_CIVILE | C21: Codice stato civile cliente. Rappresenta l'informazione generata in istruttoria e non viene modificata in postvendita | D21: In Validazione per Campioni, Monitoraggio Accettazione, Validato per IFRS9 | K21: + OP 556 impatti IFRS9
B22: CD_STATO_CIVILE_COOBLIGATO | C22: Codice Stato Civile Coobbligato. Rappresenta l'informazione generata in istruttoria e non viene modificata in postvendita | D22: In Validazione per Campioni, Validato per IFRS9 | K22: + OP 556 impatti IFRS9
B23: CD_CONIUGE_GARANTE | C23: Flag Coniuge garante. Rappresenta l'informazione generata in istruttoria e non viene modificata in postvendita | D23: In Validazione per Campioni, Validato per IFRS9 | K23: + OP 556 impatti IFRS9
B24: CD_FORMA_GIURIDICA | C24: Codice Forma Giuridica. Rappresenta l'informazione generata in istruttoria e non viene modificata in postvendita | D24: In Validazione per Campioni, Validato per IFRS9 | E24: OXANFVAN | F24: OXANFVAN.AC_FORMA_GIURIDICA | H24: OXANFVAN | I24: OXANFVAN.AC_FORMA_GIURIDICA
B25: DT_NASCITA_CLIENTE | C25: Data di nascita cliente. Rappresenta l'informazione generata in istruttoria e non viene modificata in postvendita | D25: In Validazione per Campioni, Monitoraggio Accettazione, Validato per IFRS9 | K25: + OP 556 impatti IFRS9
B26: CD_PROVINCIA_NASCITA | C26: Codice Provincia Nascita cliente. Rappresenta l'informazione generata in istruttoria e non viene modificata in postvendita | D26: In Validazione per Campioni, Validato per IFRS9 | K26: + OP 556 impatti IFRS9
B27: CD_QUALITA_CLIE | C27: Codice Qualità Cliente. Rappresenta l'informazione generata in istruttoria e non viene modificata in postvendita | D27: In Validazione per Campioni, Monitoraggio Accettazione, Validato per IFRS9 | K27: + OP 556 impatti IFRS9
B28: CD_QUALITA_CONV | C28: Codice Qualità Convenzionato. Rappresenta l'informazione generata in istruttoria e non viene modificata in postvendita | D28: In Validazione per Campioni, Validato per IFRS9 | K28: + OP 556 impatti IFRS9
B29: CD_TIPO_AZIENDA_CLI | C29: Tipo azienda cliente. Rappresenta l'informazione generata in istruttoria e non viene modificata in postvendita | D29: In Validazione per Campioni, Validato per IFRS9 | K29: + OP 556 impatti IFRS9
B30: DT_INIZIO_RAPP_BANCA | C30: Data inizio rapporto banca. Rappresenta l'informazione generata in istruttoria e non viene modificata in postvendita | D30: In Validazione per Campioni, Validato per IFRS9 | K30: + OP 556 impatti IFRS9
B31: TP_PRATICA_INTERNET | C31: Tipo Pratica Internet. Rappresenta l'informazione generata in istruttoria e non viene modificata in postvendita | D31: In Validazione per Campioni, Validato per IFRS9 | K31: + OP 556 impatti IFRS9
B32: NM_PRATICHE_CLIENTE | C32: Pratiche precedentemente liquidate per lo stesso cliente. Rappresenta l'informazione generata in istruttoria e non viene modificata in postvendita | D32: In validazione per Monitoraggio Accettazione, Validato per IFRS9 | K32: Legato a sviluppi che si faranno tra Febbraio e Giugno 26 + O + OP 556 impatti IFRS9
A33: Dati Anagrafica (attività) | B33: TP_ATTIVITA | C33: Tipo attività, lavoro del cliente: Autonomo, dipendente, Pensionato. Rappresenta l'informazione generata in istruttoria e non viene modificata in postvendita | D33: Validato per No Start, Validato per IFRS9 | E33: BAPRATCT | F33: BAPCT_QUALIFICA | H33: BAPRATCT | I33: BAPCT_QUALIFICA
B34: TP_AMBITO_LAVORATIVO | D34: In Validazione per Vendite
B35: CD_SETT_ATTIVITA_COOBLIGATO | C35: settore attività coobligato. Rappresenta l'informazione generata in istruttoria e non viene modificata in postvendita | D35: In Validazione per Campioni, Monitoraggio Accettazione, Validato per IFRS9 | K35: + OP 556 impatti IFRS9
B36: CD_SETT_ATTIVITA_CLIENTE | C36: settore attività cliente. Rappresenta l'informazione generata in istruttoria e non viene modificata in postvendita | D36: In Validazione per Campioni, Monitoraggio Accettazione, Validato per IFRS9 | K36: + OP 556 impatti IFRS9
B37: CD_OCCUPAZIONE | C37: Codice Occupazione. Rappresenta l'informazione generata in istruttoria e non viene modificata in postvendita | D37: In Validazione per Campioni, Monitoraggio Accettazione, Validato per IFRS9 | K37: P 556 impatti IFRS9
B38: DT_INIZIO_OCCUP | C38: data occupazione cliente. Rappresenta l'informazione generata in istruttoria e non viene modificata in postvendita | D38: In Validazione per Campioni, Monitoraggio Accettazione, Validato per IFRS9 | K38: + OP 556 impatti IFRS9
B39: TP_CONTRATTO_LAVORO | C39: tipo contratto: tempo det/indet. Rappresenta l'informazione generata in istruttoria e non viene modificata in postvendita | D39: In Validazione per Campioni, Monitoraggio Accettazione, Validato per IFRS9 | E39: BAPRATCT | F39: BAPCT_TIPO_CONTRATTO
B40: NM_MESI_DURATA | C40: Durata contratto lavoro. Rappresenta l'informazione generata in istruttoria e non viene modificata in postvendita | D40: In Validazione per Campioni, Monitoraggio Accettazione, Validato per IFRS9 | K40: + OP 556 impatti IFRS9
B41: NM_MENSILITA_CLIENTE | C41: Numero mensilità cliente. Rappresenta l'informazione generata in istruttoria e non viene modificata in postvendita | D41: In validazione per Monitoraggio Accettazione, Validato per IFRS9 | E41: BAPRATCT | F41: BAPCT_NUM_MENSILITA | H41: BAPRATCT | I41: BAPCT_NUM_MENSILITA
B42: NM_MENSILITA_COOBLIGATO | C42: Numero mensilità coobligato. Rappresenta l'informazione generata in istruttoria e non viene modificata in postvendita | D42: In validazione per Monitoraggio Accettazione, Validato per IFRS9 | E42: BAPRATCT | F42: BAPCT_NUM_MENSILITA | H42: BAPRATCT | I42: BAPCT_NUM_MENSILITA
B43: FL_ACCREDITO_STIP_CLI | C43: Flag accredito stipendio, indica se viene accreditato stipendio nel conto | D43: In validazione per Monitoraggio Accettazione, | E43: BAPRATCT | F43: BAPCT_ACCREDITO_STIPENDIO | H43: BAPRATCT | I43: BAPCT_ACCREDITO_STIPENDIO | K43: OP 587 (Flag accredito stipendio per canale banco)
A44: Dati Anagrafica (abitazione e residenza) | B44: CD_ABITAZIONE | C44: codice abitazione Cliente. Rappresenta l'informazione generata in istruttoria e non viene modificata in postvendita | D44: In Validazione per Campioni, Validato per IFRS9 | K44: + OP 556 impatti IFRS9
B45: TP_ABITAZIONE | C45: Tipo Abitazione cliente. Rappresenta l'informazione generata in istruttoria e non viene modificata in postvendita | D45: In Validazione per Campioni, Monitoraggio Accettazione, Validato per IFRS9 | K45: + OP 556 impatti IFRS9
B46: TP_LOCAZIONE | C46: Tipo Locazione. Rappresenta l'informazione generata in istruttoria e non viene modificata in postvendita | D46: In Validazione per Campioni, Monitoraggio Accettazione, Validato per IFRS9 | K46: + OP 556 impatti IFRS9
B47: DT_INIZIO_INDIR | C47: data inizio validità indirizzo residenza. Rappresenta l'informazione generata in istruttoria e non viene modificata in postvendita | D47: In Validazione per Campioni, Validato per IFRS9 | K47: + OP 556 impatti IFRS9
B48: CD_PROVINCIA_RESIDENZA | C48: Codice Provincia Residenza cliente. Rappresenta l'informazione generata in istruttoria e non viene modificata in postvendita | D48: In Validazione per Campioni, Validato per IFRS9 | K48: + OP 556 impatti IFRS9
B49: CD_REGIONE_RESIDENZA | C49: Codice Regione Residenza. Rappresenta l'informazione generata in istruttoria e non viene modificata in postvendita | D49: In Validazione per Campioni, Monitoraggio Accettazione, Validato per IFRS9 | K49: + OP 556 impatti IFRS9
B50: CD_PROVEN_COMMERC | C50: Codice Provenienza Commerciale. Rappresenta l'informazione generata in istruttoria e non viene modificata in postvendita | D50: In Validazione per Campioni, Validato per IFRS9 | K50: + OP 556 impatti IFRS9
A51: Dati Reddito | B51: EU_ALTRI_REDDITI | C51: Importo Altri Redditi. Rappresenta l'informazione generata in istruttoria e non viene modificata in postvendita | D51: In Validazione per Campioni, Validato per IFRS9 | K51: + OP 556 impatti IFRS9
B52: EU_REDDITO_ANNUO_CLIENTE | C52: Importo reddito annuo cliente. Rappresenta l'informazione generata in istruttoria e non viene modificata in postvendita | D52: In Validazione per Campioni, Monitoraggio Accettazione,Validato per IFRS9 | K52: + OP 556 impatti IFRS9
B53: EU_REDDITO_COOBLIGATO | C53: Importo Reddito Coobligato. Rappresenta l'informazione generata in istruttoria e non viene modificata in postvendita | D53: In Validazione per Campioni, Monitoraggio Accettazione, Validato per IFRS9 | K53: + OP 556 impatti IFRS9
B54: EU_REDDITO_FAMIGLIARE | C54: Importo redditi familiari. Rappresenta l'informazione generata in istruttoria e non viene modificata in postvendita | D54: In Validazione per Campioni, Validato per IFRS9 | K54: + OP 556 impatti IFRS9
B55: EU_ALTRI_REDDITI_COOBLIGATO | C55: Importo altri redditi coobligato . Rappresenta l'informazione generata in istruttoria e non viene modificata in postvendita | D55: In Validazione per Campioni, Validato per IFRS9 | K55: + OP 556 impatti IFRS9
A56: Flag | B56: FL_DEPOSITO_BANCARIO | C56: Flag Deposito Bancario cliente. Rappresenta l'informazione generata in istruttoria e non viene modificata in postvendita | D56: In Validazione per Campioni, Validato per IFRS9 | K56: + OP 556 impatti IFRS9
B57: FL_DEPOSITO_BANCARIO_COOBLIGATO | C57: Flag Deposito Bancario coobligato. Rappresenta l'informazione generata in istruttoria e non viene modificata in postvendita | D57: In Validazione per Campioni, Validato per IFRS9 | K57: + OP 556 impatti IFRS9
B58: FL_CONTO_BANCARIO | C58: Flag Conto Bancario. Rappresenta l'informazione generata in istruttoria e non viene modificata in postvendita | D58: In Validazione per Campioni, Validato per IFRS9 | K58: + OP 556 impatti IFRS9
B59: FL_CONTO_BANCARIO_COOBLIGATO | C59: Flag Conto Bancario Coobligato. Rappresenta l'informazione generata in istruttoria e non viene modificata in postvendita | D59: In Validazione per Campioni, Validato per IFRS9 | K59: + OP 556 impatti IFRS9
B60: FL_NUOVO_CLIENTE | C60: Clienti che hanno aperto un rapporto nell'anno corrente. Rappresenta l'informazione generata in istruttoria e non viene modificata in postvendita | D60: In Validazione per Campioni, Monitoraggio Accettazione, Validato per IFRS9 | K60: + OP 556 impatti IFRS9 + OP 590 Mappatura info OCS (flag neo correntista per canale banco)
B61: FL_GIA_CLIENTE_BANCA | C61: Flag che identifica le pratiche associate a clienti già attivi e conosciuti provenienti dal canale banco. Vale solo per i correntisti dipendenti e pensionati che hanno l'accredito dello stipendio da almeno 7 mesi. Verrà inoltrato da Banco al momento dell’inserimento della pratica in OCS mediante richiamo di specifica transazione MASFE. | D61: In Validazione Monitoraggio Accettazione | E61: BAPRATCT | F61: BAPCT_GIA_CLIENTE_BANCA | H61: BAPRATCT | I61: BAPCT_GIA_CLIENTE_BANCA
B62: FL_FIRMA_DOPPIA | C62: flag firma doppia (allo score). Rappresenta l'informazione generata in istruttoria e non viene modificata in postvendita | D62: In Validazione per Campioni, Validato per IFRS9 | K62: + OP 556 impatti IFRS9
A63: Importi | B63: EU_CUMULO_RISCHIO_COOBLIGATO | C63: Importo Cumulo Rischio Agos (Coobbligato) . Rappresenta l'informazione generata in istruttoria e non viene modificata in postvendita | D63: In Validazione per Campioni, Monitoraggio Accettazione, Validato per IFRS9 | K63: + OP 556 impatti IFRS9
B64: EU_CUMULO_RISCHIO_CLIENTE | C64: Importo Cumulo Rischio Agos (Cliente) attribuito, override. Rappresenta l'informazione generata in istruttoria e non viene modificata in postvendita | D64: In Validazione per Campioni, Monitoraggio Accettazione, Validato per IFRS9 | K64: + OP 556 impatti IFRS9
B65: EU_CUMULO_RISCHIO_CRIF_CLIENTE | C65: Importo Cumulo Rischio Crif (Cliente) attribuito, override. Rappresenta l'informazione generata in istruttoria e non viene modificata in postvendita | D65: In Validazione per Campioni, Validato per IFRS9 | K65: + OP 556 impatti IFRS9
B66: EU_CUMULO_RISCHIO_CRIF_COOBLIGATO | C66: Importo Cumulo Rischio Crif (Coobligato) . Rappresenta l'informazione generata in istruttoria e non viene modificata in postvendita | D66: In Validazione per Campioni, Validato per IFRS9 | K66: + OP 556 impatti IFRS9
B67: EU_COMMISSIONE | C67: Importo Commissioni. Rappresenta l'informazione generata in istruttoria e non viene modificata in postvendita | D67: In Validazione per Campioni, Validato per IFRS9 | K67: + OP 556 impatti IFRS9
B68: EU_DEPOS_BANCA_COOBLIGATO | C68: Importo deposito bancario cocobligato. Rappresenta l'informazione generata in istruttoria e non viene modificata in postvendita | D68: In Validazione per Campioni, Validato per IFRS9 | K68: + OP 556 impatti IFRS9
B69: EU_FIDO | C69: Importo fido cliente. Rappresenta l'informazione generata in istruttoria e non viene modificata in postvendita | D69: In Validazione per Campioni, Monitoraggio Accettazione, Validato per IFRS9 | K69: + OP 556 impatti IFRS9
B70: EU_FIDO_COOBLIGATO | C70: Importo fido coobligato. Rappresenta l'informazione generata in istruttoria e non viene modificata in postvendita | D70: In Validazione per Campioni,Validato per IFRS9 | K70: + OP 556 impatti IFRS9
B71: EU_FINANZIATO | C71: Importo finanziato. Rappresenta l'informazione generata in istruttoria e non viene modificata in postvendita | D71: In Validazione per Campioni, Validato per IFRS9 | K71: + OP 556 impatti IFRS9
B72: EU_FINANZIATO_COOBLIGATO | C72: Importo finanziato Coobligato. Rappresenta l'informazione generata in istruttoria e non viene modificata in postvendita | D72: In Validazione per Campioni, Validato per IFRS9 | K72: + OP 556 impatti IFRS9
B73: EU_IMPIEGHI_CLIENTE | C73: Impieghi Cliente. Rappresenta l'informazione generata in istruttoria e non viene modificata in postvendita | D73: In Validazione per Campioni, Validato per IFRS9 | K73: + OP 556 impatti IFRS9
B74: EU_IMPIEGHI_COOBLIGATO | C74: Impieghi coob. Rappresenta l'informazione generata in istruttoria e non viene modificata in postvendita | D74: In Validazione per Campioni, Validato per IFRS9 | K74: + OP 556 impatti IFRS9
B75: EU_RATA | C75: Importo rata primo periodo. Rappresenta l'informazione generata in istruttoria e non viene modificata in postvendita | D75: In Validazione per Campioni, Monitoraggio Accettazione, Validato per IFRS9 | K75: + OP 556 impatti IFRS9
... B79: EU_RATA_CRIF_COOBLIGATO | C79: Importo rata Crif Coobligato. Rappresenta l'informazione generata in istruttoria e non viene modificata in postvendita | D79: In Validazione per Campioni, Monitoraggio Accettazione, Validato per IFRS9 | K79: + OP 556 impatti IFRS9
B80: EU_ALTR_USC_CLI | C80: Somma delle uscite mensili del Cliente dichiarate in istruttoria esclusa l'eventuale rata e altri prestiti. Es. Affitto. Rappresenta l'informazione generata in istruttoria e non viene modificata in postvendita | D80: In validazione per Monitoraggio Accettazione, Validato per IFRS9 | E80: BAPRATCT | F80: BAPCT_IMP_TIPO_USCITA_1 BAPCT_IMP_TIPO_USCITA_2 BAPCT_IMP_TIPO_USCITA_3 BAPCT_IMP_TIPO_USCITA_4 BAPCT_IMP_TIPO_USCITA_5 | G80: Somma dei campi | H80: BAPRATCT | I80: BAPCT_IMP_TIPO_USCITA_1 BAPCT_IMP_TIPO_USCITA_2 BAPCT_IMP_TIPO_USCITA_3 BAPCT_IMP_TIPO_USCITA_4 BAPCT_IMP_TIPO_USCITA_5 | J80: Somma dei campi
B81: EU_ALTR_USC_COBLGT | C81: Somma delle uscite mensili del Coobligato dichiarate in istruttoria esclusa l'eventuale rata e altri prestiti. Es. Affitto. Rappresenta l'informazione generata in istruttoria e non viene modificata in postvendita | D81: In validazione per Monitoraggio Accettazione, Validato per IFRS9 | E81: BAPRATCT | F81: BAPCT_IMP_TIPO_USCITA_1 BAPCT_IMP_TIPO_USCITA_2 BAPCT_IMP_TIPO_USCITA_3 BAPCT_IMP_TIPO_USCITA_4 BAPCT_IMP_TIPO_USCITA_5 | G81: Somma dei campi | H81: BAPRATCT | I81: BAPCT_IMP_TIPO_USCITA_1 BAPCT_IMP_TIPO_USCITA_2 BAPCT_IMP_TIPO_USCITA_3 BAPCT_IMP_TIPO_USCITA_4 BAPCT_IMP_TIPO_USCITA_5 | J81: Somma dei campi
A82: Negatività (Svalutazioni, Morosità, Protesti e Insolvenze) | B82: NM_MOROSITA | C82: Numero morosità cliente. Rappresenta l'informazione generata in istruttoria e non viene modificata in postvendita | D82: In Validazione per Campioni, Validato per IFRS9 | K82: + OP 556 impatti IFRS9
B83: EU_MOROSITA | C83: Importo Morosità. Rappresenta l'informazione generata in istruttoria e non viene modificata in postvendita | D83: In Validazione per Campioni, Validato per IFRS9 | K83: + OP 556 impatti IFRS9
B84: EU_MOROSITA_COOBLIGATO | C84: Importo Morosità Coobligato. Rappresenta l'informazione generata in istruttoria e non viene modificata in postvendita | D84: In Validazione per Campioni, Validato per IFRS9 | K84: + OP 556 impatti IFRS9
B85: NM_PROTESTI | C85: Numero protesti cliente. Rappresenta l'informazione generata in istruttoria e non viene modificata in postvendita | D85: In Validazione per Campioni, Validato per IFRS9 | K85: + OP 556 impatti IFRS9
B86: NM_PROTESTI_COOBLIGATO | C86: Numero protesti coobligato. Rappresenta l'informazione generata in istruttoria e non viene modificata in postvendita | D86: In Validazione per Campioni, Validato per IFRS9 | K86: + OP 556 impatti IFRS9
B87: DT_ULTIMO_PROTESTO | C87: Data ultimo Protesto. Rappresenta l'informazione generata in istruttoria e non viene modificata in postvendita | D87: In Validazione per Campioni, Validato per IFRS9 | K87: + OP 556 impatti IFRS9
B88: EU_PROTESTI_CLIENTE | C88: Importo protesti (valore complessivo dei titoli di credito non pagati). Rappresenta l'informazione generata in istruttoria e non viene modificata in postvendita | D88: In Validazione per Campioni, Validato per IFRS9 | K88: + OP 556 impatti IFRS9
B89: EU_PROTESTI_COOBLIGATO | C89: Importo protesti coobligato. Rappresenta l'informazione generata in istruttoria e non viene modificata in postvendita | D89: In Validazione per Campioni, Validato per IFRS9 | K89: + OP 556 impatti IFRS9
A90: Informazioni Carta | B90: TP_ORGANIZZAZIONE_CARTA | C90: Tipo organizzazione carta. Rappresenta l'informazione generata in istruttoria e non viene modificata in postvendita | D90: In Validazione per Campioni, Validato per IFRS9 | K90: + OP 556 impatti IFRS9
B91: CD_ORGANIZZAZIONE_CARTA | C91: Codice Organizzazione Carta. Rappresenta l'informazione generata in istruttoria e non viene modificata in postvendita | D91: In Validazione per Campioni, Validato per IFRS9 | K91: + OP 556 impatti IFRS9
B92: CD_BLOCCO | C92: Presenza di Blocco Carta. Rappresenta l'informazione generata in istruttoria e non viene modificata in postvendita | D92: In Validazione per Campioni, Validato per IFRS9 | H92: BAPRATCT | I92: BAPCT_BLOCCO
B93: DS_BLOCCO | C93: Tipologia di blocco da gestire . Rappresenta l'informazione generata in istruttoria e non viene modificata in postvendita | D93: In Validazione per Campioni, Validato per IFRS9 | H93: BAPRATCT | I93: BAPCT_TIPO_BLOCCO
A94: Modalità di pagamento | B94: NM_CESSIONE_BUSTA_PAGA_CLIENTE | C94: Numero cessione del quinto busta paga. Rappresenta l'informazione generata in istruttoria e non viene modificata in postvendita | D94: In Validazione per Campioni, Validato per IFRS9 | K94: + OP 556 impatti IFRS9
B95: TP_PAGAMENTO | C95: Tipo pagamento allo score. Rappresenta l'informazione generata in istruttoria e non viene modificata in postvendita | D95: In Validazione per Campioni, Monitoraggio Accettazione, Validato per IFRS9, SCD | K95: + OP 556 impatti IFRS9
B96: TP_RIPAGAMENTO | C96: Tipo Ripagamento allo score. Rappresenta l'informazione generata in istruttoria e non viene modificata in postvendita | D96: In Validazione per Campioni, Validato per IFRS9 | K96: + OP 556 impatti IFRS9
A97: Prodotto | B97: CD_TAB_FINANZ | C97: Tabella finanziaria rilevato in fase di sitruttoria. Rappresenta l'informazione generata in istruttoria e non viene modificata in postvendita | D97: In Validazione per Campioni, Validato per IFRS9 | K97: + OP 556 impatti IFRS9
B98: CD_TIPO_TASSO | C98: Tipo tasso rilevato in fase di sitruttoria. Rappresenta l'informazione generata in istruttoria e non viene modificata in postvendita | D98: In Validazione per Campioni, Validato per IFRS9 | K98: + OP 556 impatti IFRS9
B99: NM_RATE | C99: Numero rate / Numero rate primo periodo. Rappresenta l'informazione generata in istruttoria e non viene modificata in postvendita | D99: In validazione per Monitoraggio Accettazione, Validato per IFRS9 | K99: + OP 556 impatti IFRS9
B100: NM_RATE_2 | C100: Numero rate secondo periodo. Rappresenta l'informazione generata in istruttoria e non viene modificata in postvendita | D100: In validazione per Monitoraggio Accettazione,Validato per IFRS9 | K100: + OP 556 impatti IFRS9
A101: Score | B101: CD_CBSCORE_CRIF_CLIE | C101: CB score Crif Plus Cliente (da gen 2011 versione Perform). Rappresenta l'informazione generata in istruttoria e non viene modificata in postvendita | D101: In Validazione per Campioni, Monitoraggio Accettazione, Validato per IFRS9 | K101: + OP 556 impatti IFRS9
B102: CD_CBSCORE_CRIF_COBLGT | C102: Score Comportamentale Crif Coobligato allo score della Pratica. Rappresenta l'informazione generata in istruttoria e non viene modificata in postvendita | D102: In validazione per Monitoraggio Accettazione,Validato per IFRS9 | K102: op 556 impatti IFRS9
B103: CD_CBSCORE_CRIF_ULT_CO | C103: CB Score Crif Ultimo Contratto Consumo. Rappresenta l'informazione generata in istruttoria e non viene modificata in postvendita | D103: In Validazione per Campioni, in validazione IFRS9 | K103: + OP 556 impatti IFRS9
...

Sheet Catalogo Categorie Campi
A1: Entità DM Nome
A2: Nome Entità L2 | B2: ID_ENTITA_L2 | C2: Categoria Campo | D2: ID Categoria campo | E2: Descrizione Breve | F2: Note
A3: PRATICA | B3: IDL2_1 | C3: Tempo | D3: IDL2_1_1 | E3: Campi relativi alla storicizzazione, versionamento o loggatura
A4: PRATICA | B4: IDL2_1 | C4: Controparte | D4: IDL2_1_2 | E4: Informazioni e/o identificativi della/e controparti associate alla pratica
A5: PRATICA | B5: IDL2_1 | C5: Configurazione prodotto | D5: IDL2_1_3 | E5: Elenco di campi che utili alla configurazione del prodotto
A6: PRATICA | B6: IDL2_1 | C6: Attributo | D6: IDL2_1_4
A7: PRATICA | B7: IDL2_1 | C7: Stato pratica | D7: IDL2_1_5 | E7: Campi che tracciano lo stato della pratica
A8: PRATICA | B8: IDL2_1 | C8: Società Veicolo | D8: IDL2_1_6 | E8: Informazioni sulla società Veicolo della pratica
A9: PRATICA | B9: IDL2_1 | C9: Catena di Intermediazione | D9: IDL2_1_7 | E9: Campi riguardo la Catena di Intermediazione
A10: PRATICA | B10: IDL2_1 | C10: Date Pratica | D10: IDL2_1_8 | E10: Date associate alla pratica
A11: PRATICA | B11: IDL2_1 | C11: Score Pratica | D11: IDL2_1_9 | E11: Informazioni sugli score attribuiti alla pratica in fase di istruttoria
A12: PRATICA | B12: IDL2_1 | C12: Tassi e Rendimenti | D12: IDL2_1_10 | E12: Elenco dei tassi associati alla pratica
A13: PRATICA | B13: IDL2_1 | C13: Canale di acquisizione | D13: IDL2_1_11 | E13: Informazioni sul canale di acquisizione
A14: PRATICA | B14: IDL2_1 | C14: Utenti operatori pratica | D14: IDL2_1_12 | E14: Utenti che hanno apportato modifiche alla pratica nel suo processo
A15: PRATICA | B15: IDL2_1 | C15: Carta | D15: IDL2_1_14 | E15: Informazioni relative alla carta e al suo utilizzo
A16: PRATICA | B16: IDL2_1 | C16: Firme | D16: IDL2_1_15 | E16: Informazioni relative alla firma della pratica
A17: PRATICA | B17: IDL2_1 | C17: Flag | D17: IDL2_1_16 | E17: Flag associati alla pratica
A18: PRATICA | B18: IDL2_1 | C18: Importi Pratica | D18: IDL2_1_17 | E18: Elenco degli Importi Associati ad una pratica
A19: PRATICA | B19: IDL2_1 | C19: Pagamento | D19: IDL2_1_18 | E19: Informazioni relative ai pagamenti e ai metodi di pagamento
A20: PRATICA | B20: IDL2_1 | C20: Rate | D20: IDL2_1_19
A21: PRATICA | B21: IDL2_1 | C21: Conto corrente | D21: IDL2_1_20
A22: PRATICA | B22: IDL2_1 | C22: Parametri | D22: IDL2_1_21 | E22: Parametrizzazioni legate alla pratica
A23: PRATICA | B23: IDL2_1 | C23: Identificativo Auto | D23: IDL2_1_22 | E23: Infromazioni relative alle auto
A24: PRATICA | B24: IDL2_1 | C24: Cartolarizzazione | D24: IDL2_1_24
A25: CONTROPARTE | B25: IDL2_2 | C25: Identificativo Controparte | D25: IDL2_2_1 | E25: Identificativo/i univoco/i della controparte
A26: CONTROPARTE | B26: IDL2_2 | C26: Tempo | D26: IDL2_2_2 | E26: Campi relativi alla storicizzazione, versionamento o loggatura
A27: CONTROPARTE | B27: IDL2_2 | C27: Dati anagrafici personali | D27: IDL2_2_3 | E27: Dati anagrafici personali della controparte
A28: CONTROPARTE | B28: IDL2_2 | C28: Dati anagrafici non personali | D28: IDL2_2_3 | E28: Dati anagrafici non personali della controparte
A29: CONTROPARTE | B29: IDL2_2 | C29: Dati Residenza | D29: IDL2_2_4 | E29: Insieme di campi che identificano l'indirizzo di Residenza nel caso di persone fisiche
A30: CONTROPARTE | B30: IDL2_2 | C30: Dati Domicilio | D30: IDL2_2_5 | E30: Insieme di campi che identificano l'indirizzo di Domicilio nel caso di persone fisiche
A31: CONTROPARTE | B31: IDL2_2 | C31: Contatti | D31: IDL2_2_6 | E31: Insieme di campi con i contatti di riferimento
A32: CONTROPARTE | B32: IDL2_2 | C32: Dati Impiego | D32: IDL2_2_7 | E32: Dati sull'impiego lavorativo della controparte nel caso di persone fisiche
A33: SALDO_M | B33: IDL2_3 | C33: Identificativo pratica | D33: IDL2_3_1 | E33: Identificativo/i univoco/i della pratica alla quale il saldo in questione è associato
A34: SALDO_M | B34: IDL2_3 | C34: Tempo | D34: IDL2_3_2 | E34: Campi relativi alla storicizzazione, versionamento o loggatura
A35: SALDO_M | B35: IDL2_3 | C35: Identificativo saldo | D35: IDL2_3_3 | E35: Campi identificare la tipologia di saldo
A36: SALDO_M | B36: IDL2_3 | C36: Importi Saldo (Importi Saldo Contabile/Importi Saldo Gestionale) | D36: IDL2_3_4 | E36: Saldo (contabile e gestionale) e relative componenti, che avranno in base alla tipologia del saldo (se contabile o gestionale), diversa regola funzionale
... A47: CANALE ESITO | B47: IDL2_8 | C47: Canale Esito | D47: IDL2_8_3 | E47: Informazioni sulla classificazione in Web / Non Web del canale di Esito - "Atterraggio" della pratica
A48: PRATICA_M | B48: IDL2_10 | C48: Identificativo Pratica | D48: IDL2_10_1
A49: PRATICA_M | B49: IDL2_10 | C49: Tempo | D49: IDL2_10_2
A50: PRATICA_M | B50: IDL2_10 | C50: Controparti | D50: IDL2_10_3
A51: PRATICA_M | B51: IDL2_10 | C51: Configurazione prodotto | D51: IDL2_10_4
A52: PRATICA_M | B52: IDL2_10 | C52: Attributo | D52: IDL2_10_5
A53: PRATICA_M | B53: IDL2_10 | C53: Stato pratica | D53: IDL2_10_6
A54: PRATICA_M | B54: IDL2_10 | C54: Società Veicolo | D54: IDL2_10_7
A55: PRATICA_M | B55: IDL2_10 | C55: Catena di Intermediazione | D55: IDL2_10_8
A56: PRATICA_M | B56: IDL2_10 | C56: Date Pratica | D56: IDL2_10_9
A57: PRATICA_M | B57: IDL2_10 | C57: Tassi e Rendimenti | D57: IDL2_10_10
A58: PRATICA_M | B58: IDL2_10 | C58: Canale di acquisizione | D58: IDL2_10_11
A59: PRATICA_M | B59: IDL2_10 | C59: Utenti operatori pratica | D59: IDL2_10_12
... A70: PRATICA_M | B70: IDL2_10 | C70: CQS | D70: IDL2_10_23
A71: SVALUTAZIONI_M | B71: IDL2_11 | C71: Identificativo Pratica | D71: IDL2_11_1 | E71: informazioni identificative della pratica
A72: SVALUTAZIONI_M | B72: IDL2_11 | C72: Tempo | D72: IDL2_11_2 | E72: Informazioni per contestualizzare temporalmente le informazioni
A73: SVALUTAZIONI_M | B73: IDL2_11 | C73: Stato Pratica Svalz | D73: IDL2_11_3 | E73: Stato della pratica svalutata
A74: SVALUTAZIONI_M | B74: IDL2_11 | C74: Dinamiche Importi | D74: IDL2_11_4 | E74: Dinamiche di svalutazione
A75: SVALUTAZIONI_M | B75: IDL2_11 | C75: Stage | D75: IDL2_11_4 | E75: Informazioni sullo stage in cui si trova la pratica.
A76: FORBEARANCE_M | B76: IDL2_12 | C76: Identificativo Pratica | D76: IDL2_12_1 | E76: Informazioni identificative della pratica
A77: FORBEARANCE_M | B77: IDL2_12 | C77: Tempo | D77: IDL2_12_2 | E77: Tempo
A78: FORBEARANCE_M | B78: IDL2_12 | C78: Identificativo Controparte | D78: IDL2_12_3 | E78: Informazioni identificative della controparte
A79: FORBEARANCE_M | B79: IDL2_12 | C79: Forbearance | D79: IDL2_12_4 | E79: Informazioni relative alla forbearance
A80: FORBEARANCE_M | B80: IDL2_12 | C80: Ristrutturazione | D80: IDL2_12_5 | E80: Ristrutturazioni effettuate sulla pratica
A81: FORBEARANCE_M | B81: IDL2_12 | C81: VAN | D81: IDL2_12_6 | E81: Van A e Van B
A82: FORBEARANCE_M | B82: IDL2_12 | C82: DO | D82: IDL2_12_7 | E82: Percentuale DO
A83: BOLLETTINI | B83: IDL2_13 | C83: Identificativo Pratica | D83: IDL2_13_1
A84: BOLLETTINI | B84: IDL2_13 | C84: Tipo Bollettino | D84: IDL2_13_2
A85: BOLLETTINI | B85: IDL2_13 | C85: Nastro | D85: IDL2_13_3
A86: BOLLETTINI | B86: IDL2_13 | C86: Identificativo Pratica | D86: IDL2_13_4
A87: BOLLETTINI | B87: IDL2_13 | C87: Rata di Riferimento | D87: IDL2_13_5
A88: BOLLETTINI | B88: IDL2_13 | C88: Conto Corrente | D88: IDL2_13_6
A89: BOLLETTINI | B89: IDL2_13 | C89: Provenienza | D89: IDL2_13_7
A90: BOLLETTINI | B90: IDL2_13 | C90: Date | D90: IDL2_13_8
A91: BOLLETTINI | B91: IDL2_13 | C91: Importo | D91: IDL2_13_9
A92: BOLLETTINI | B92: IDL2_13 | C92: Flag | D92: IDL2_13_10
A93: CAMBIALI | B93: IDL2_14 | C93: Identificativo Cambiale | D93: IDL2_14_1
A94: CAMBIALI | B94: IDL2_14 | C94: Flusso | D94: IDL2_14_2
... A137: STAKE_BKI_M | B137: IDL2_21 | C137: Tempo | D137: IDL2_21_2
A138: STAKE_BKI_M | B138: IDL2_21 | C138: Stage Banca D'Italia | D138: IDL2_21_3 | E138: stage Banca d'Italia = Stage Ifrs9
A139: QUALITA_CREDITIZIA_M | B139: IDL2_22 | C139: Identificativo Pratica | D139: IDL2_22_1
A140: QUALITA_CREDITIZIA_M | B140: IDL2_22 | C140: Tempo | D140: IDL2_22_2
A141: QUALITA_CREDITIZIA_M | B141: IDL2_22 | C141: Qualità Creditizia | D141: IDL2_22_3
A142: PRATICHE_TRUFFA | B142: IDL2_23 | C142: Identificativo Pratica | D142: IDL2_23_1
A143: PRATICHE_TRUFFA | B143: IDL2_23 | C143: Tempo | D143: IDL2_23_2
A144: PRATICHE_TRUFFA | B144: IDL2_23 | C144: Attributi Truffa | D144: IDL2_23_3
A145: DOC_ISTRUTTORIA | B145: IDL2_24 | C145: Identificativo Doc | D145: IDL2_24_1
A146: DOC_ISTRUTTORIA | B146: IDL2_24 | C146: Identificativo Pratica | D146: IDL2_24_2
A147: DOC_ISTRUTTORIA | B147: IDL2_24 | C147: Tempo | D147: IDL2_24_3
A148: DOC_ISTRUTTORIA | B148: IDL2_24 | C148: Tipo Documento | D148: IDL2_24_4
A149: DOC_ISTRUTTORIA | B149: IDL2_24 | C149: Date Doc | D149: IDL2_24_5
A150: DOC_IRREGOLARITA | B150: IDL2_25 | C150: Identificativo Doc | D150: IDL2_25_1
... A165: UTILIZZI_CARTE | B165: IDL2_28 | C165: Date Utilizzo | D165: IDL2_28_6
A166: MANUAL_ADJUSTMENT_O | B166: IDL2_29 | C166: Identificativo Manual Adjustment | D166: IDL2_29_1 | E166: Informazioni identificative del Manual adjustment
A167: MANUAL_ADJUSTMENT_O | B167: IDL2_29 | C167: Valore | D167: IDL2_29_2 | E167: Valore del Manual adjustment condiviso
A168: MANUAL_ADJUSTMENT_O | B168: IDL2_29 | C168: Tempo | D168: IDL2_29_3 | E168: Informazioni relative alla durata del manual adjustement
A169: CONTR_DFLT_EBA_INTS_M | B169: IDL2_30 | C169: Identificativo pratica | D169: IDL2_30_1 | E169: Informazioni identificative della pratica
A170: CONTR_DFLT_EBA_INTS_M | B170: IDL2_30 | C170: Identificativo controparte | D170: IDL2_30_2 | E170: Informazioni identificative della controparte
A171: CONTR_DFLT_EBA_INTS_M | B171: IDL2_30 | C171: Default EBA | D171: IDL2_30_3 | E171: Informazioni relative al Default EBA
A172: CONTR_DFLT_EBA_INTS_M | B172: IDL2_30 | C172: Date default EBA | D172: IDL2_30_4 | E172: Data di ingresso e uscita del Default EBA
A173: CONTR_DFLT_EBA_INTS_M | B173: IDL2_30 | C173: Tempo | D173: IDL2_30_5 | E173: Informazioni relative al periodo di osservazione
A174: CONTR_DFLT_EBA_INTS_M | B174: IDL2_30 | C174: Flag | D174: IDL2_30_6 | E174: Informazioni relative ai flag associati alla pratica
A175: CONTR_DFLT_EBA_INTS_M | B175: IDL2_30 | C175: Configurazione prodotto | D175: IDL2_30_7 | E175: Elenco di campi che utili alla configurazione del prodotto
A176: CLI_DFLT_EBA_INTS_M | B176: IDL2_31 | C176: Identificativo controparte | D176: IDL2_31_1 | E176: Informazioni identificative della controparte
...

Sheet DataQualityInterna
A2: Riga Campo | B2: Tutti Campi AT Valorizzati | C2: CAMPO DA SORGENTE NON MAIN vs CHIAVI DI AGGANCIO | D2: CAMPO DA SORGENTE NON MAIN, CAMPO CALCOLATO vs REGOLA TECNICA | E2: FORMATO ammesso
A3: PRATICA | B3: Per Utilizzare Cambiare l'Entità in cella A2 dal menù a tendina
A4: {=_xlfn.SEQUENCE(COUNTA(INDIRECT("'"&A3&"'!$B:$B"))-1) +2} -> 3 | B4: {=_xlfn.LET( _xlpm.AA, INDEX(INDIRECT("'"&A$3&"'!$1:$1048576"), ROW(), MATCH("FLAG_PK", INDIRECT("'"&A$3&"'!$2:$2"), 0)), _xlpm.BB, INDEX(INDIRECT("'"&A$3&"'!$1:$1048576"), ROW(), MATCH("FORMATO", INDIRECT("'"&A$3&"'!$2:$2"), 0)), _xlpm.CC, INDEX(INDIRECT("'"&A$3&"'!$1:$1048576"), ROW(), MATCH("LENGTH", INDIRECT("'"&A$3&"'!$2:$2"), 0)), _xlpm.DD, INDEX(INDIRECT("'"&A$3&"'!$1:$1048576"), ROW(), MATCH("DECIMAL", INDIRECT("'"&A$3&"'!$2:$2"), 0)), _xlpm.FF, INDEX(INDIRECT("'"&A$3&"'!$1:$1048576"), ROW(), MATCH("CAMPO CALCOLATO", INDIRECT("'"&A$3&"'!$2:$2"), 0)), _xlpm.GG, INDEX(INDIRECT("'"&A$3&"'!$1:$1048576"), ROW(), MATCH("CAMPO DA SORGENTE NON MAIN", INDIRECT("'"&A$3&"'!$2:$2"), 0)), _xlpm.HH, INDEX(INDIRECT("'"&A$3&"'!$1:$1048576"), ROW(), MATCH("REGOLA TECNICA", INDIRECT("'"&A$3&"'!$2:$2"), 0)), _xlpm.II, INDEX(INDIRECT("'"&A$3&"'!$1:$1048576"), ROW(), MATCH("CHIAVI DI AGGANCIO", INDIRECT("'"&A$3&"'!$2:$2"), 0)), _xlpm.LL, INDEX(INDIRECT("'"&A$3&"'!$1:$1048576"), ROW(), MATCH("DATI SENSIBILI", INDIRECT("'"&A$3&"'!$2:$2"), 0)), IF(_xlpm.AA="","❌ (FLAG_PK)", IF(_xlpm.BB="","❌ (FORMATO)", IF(_xlpm.CC="","❌ (LENGTH)", IF(_xlpm.DD="","❌ (DECIMAL)", IF(_xlpm.FF="","❌ (CAMPO CALCOLATO)", IF(_xlpm.GG="","❌ (CAMPO DA SORGENTE NON MAIN)", IF(_xlpm.HH="","❌ (REGOLA TECNICA)", IF(_xlpm.II="","❌ (CHIAVI DI AGGANCIO)", IF(_xlpm.LL="","❌ (DATI SENSIBILI)", "✅"))))))))) )} -> #N/A | C4: {=IF( INDEX(INDIRECT("'"&A$3&"'!$1:$1048576"), ROW(), MATCH("CAMPO DA SORGENTE NON MAIN", INDIRECT("'"&A$3&"'!$2:$2"), 0))="S", IF(INDEX(INDIRECT("'"&A$3&"'!$1:$1048576"), ROW(), MATCH("CHIAVI DI AGGANCIO", INDIRECT("'"&A$3&"'!$2:$2"), 0))="NA", "❌", "✅"), IF( INDEX(INDIRECT("'"&A$3&"'!$1:$1048576"), ROW(), MATCH("CAMPO DA SORGENTE NON MAIN", INDIRECT("'"&A$3&"'!$2:$2"), 0))="N", IF(INDEX(INDIRECT("'"&A$3&"'!$1:$1048576"), ROW(), MATCH("CHIAVI DI AGGANCIO", INDIRECT("'"&A$3&"'!$2:$2"), 0))<>"NA", "❌", "✅"), "⚠️" ) )} -> #N/A | D4: {=_xlfn.LET( _xlpm.CC, INDEX(INDIRECT("'"&A$3&"'!$1:$1048576"), ROW(), MATCH("CAMPO CALCOLATO", INDIRECT("'"&A$3&"'!$2:$2"), 0)), _xlpm.CDSM, INDEX(INDIRECT("'"&A$3&"'!$1:$1048576"), ROW(), MATCH("CAMPO DA SORGENTE NON MAIN", INDIRECT("'"&A$3&"'!$2:$2"), 0)), _xlpm.RT, INDEX(INDIRECT("'"&A$3&"'!$1:$1048576"), ROW(), MATCH("REGOLA TECNICA", INDIRECT("'"&A$3&"'!$2:$2"), 0)), IF(AND(OR(_xlpm.CC="S", _xlpm.CDSM="S"), OR(_xlpm.RT="NA", _xlpm.RT="")), "❌", IF(AND(_xlpm.CC="N", _xlpm.CDSM="N", _xlpm.RT<>"NA"), "❌", IF(AND(_xlpm.CC="N", _xlpm.CDSM="N"), "✅", IF(AND(OR(_xlpm.CC="S", _xlpm.CDSM="S"), _xlpm.RT<>"NA"), "✅", "⚠️")))) )} -> #N/A | E4: {=_xlfn.LET( _xlpm.CC, INDEX(INDIRECT("'"&A$3&"'!$1:$1048576"), ROW(), MATCH("FORMATO", INDIRECT("'"&A$3&"'!$2:$2"), 0)), IF(_xlpm.CC="NUMBER", "✅", IF(_xlpm.CC="DATE", "✅", IF(_xlpm.CC="VARCHAR", "✅", IF(_xlpm.CC="TIMESTAMP", "✅", "❌")))) )} -> #N/A
A5: 4 | B5: {=_xlfn.LET( _xlpm.AA, INDEX(INDIRECT("'"&A$3&"'!$1:$1048576"), ROW(), MATCH("FLAG_PK", INDIRECT("'"&A$3&"'!$2:$2"), 0)), _xlpm.BB, INDEX(INDIRECT("'"&A$3&"'!$1:$1048576"), ROW(), MATCH("FORMATO", INDIRECT("'"&A$3&"'!$2:$2"), 0)), _xlpm.CC, INDEX(INDIRECT("'"&A$3&"'!$1:$1048576"), ROW(), MATCH("LENGTH", INDIRECT("'"&A$3&"'!$2:$2"), 0)), _xlpm.DD, INDEX(INDIRECT("'"&A$3&"'!$1:$1048576"), ROW(), MATCH("DECIMAL", INDIRECT("'"&A$3&"'!$2:$2"), 0)), _xlpm.FF, INDEX(INDIRECT("'"&A$3&"'!$1:$1048576"), ROW(), MATCH("CAMPO CALCOLATO", INDIRECT("'"&A$3&"'!$2:$2"), 0)), _xlpm.GG, INDEX(INDIRECT("'"&A$3&"'!$1:$1048576"), ROW(), MATCH("CAMPO DA SORGENTE NON MAIN", INDIRECT("'"&A$3&"'!$2:$2"), 0)), _xlpm.HH, INDEX(INDIRECT("'"&A$3&"'!$1:$1048576"), ROW(), MATCH("REGOLA TECNICA", INDIRECT("'"&A$3&"'!$2:$2"), 0)), _xlpm.II, INDEX(INDIRECT("'"&A$3&"'!$1:$1048576"), ROW(), MATCH("CHIAVI DI AGGANCIO", INDIRECT("'"&A$3&"'!$2:$2"), 0)), _xlpm.LL, INDEX(INDIRECT("'"&A$3&"'!$1:$1048576"), ROW(), MATCH("DATI SENSIBILI", INDIRECT("'"&A$3&"'!$2:$2"), 0)), IF(_xlpm.AA="","❌ (FLAG_PK)", IF(_xlpm.BB="","❌ (FORMATO)", IF(_xlpm.CC="","❌ (LENGTH)", IF(_xlpm.DD="","❌ (DECIMAL)", IF(_xlpm.FF="","❌ (CAMPO CALCOLATO)", IF(_xlpm.GG="","❌ (CAMPO DA SORGENTE NON MAIN)", IF(_xlpm.HH="","❌ (REGOLA TECNICA)", IF(_xlpm.II="","❌ (CHIAVI DI AGGANCIO)", IF(_xlpm.LL="","❌ (DATI SENSIBILI)", "✅"))))))))) )} -> #N/A | C5: {=IF( INDEX(INDIRECT("'"&A$3&"'!$1:$1048576"), ROW(), MATCH("CAMPO DA SORGENTE NON MAIN", INDIRECT("'"&A$3&"'!$2:$2"), 0))="S", IF(INDEX(INDIRECT("'"&A$3&"'!$1:$1048576"), ROW(), MATCH("CHIAVI DI AGGANCIO", INDIRECT("'"&A$3&"'!$2:$2"), 0))="NA", "❌", "✅"), IF( INDEX(INDIRECT("'"&A$3&"'!$1:$1048576"), ROW(), MATCH("CAMPO DA SORGENTE NON MAIN", INDIRECT("'"&A$3&"'!$2:$2"), 0))="N", IF(INDEX(INDIRECT("'"&A$3&"'!$1:$1048576"), ROW(), MATCH("CHIAVI DI AGGANCIO", INDIRECT("'"&A$3&"'!$2:$2"), 0))<>"NA", "❌", "✅"), "⚠️" ) )} -> #N/A | D5: {=_xlfn.LET( _xlpm.CC, INDEX(INDIRECT("'"&A$3&"'!$1:$1048576"), ROW(), MATCH("CAMPO CALCOLATO", INDIRECT("'"&A$3&"'!$2:$2"), 0)), _xlpm.CDSM, INDEX(INDIRECT("'"&A$3&"'!$1:$1048576"), ROW(), MATCH("CAMPO DA SORGENTE NON MAIN", INDIRECT("'"&A$3&"'!$2:$2"), 0)), _xlpm.RT, INDEX(INDIRECT("'"&A$3&"'!$1:$1048576"), ROW(), MATCH("REGOLA TECNICA", INDIRECT("'"&A$3&"'!$2:$2"), 0)), IF(AND(OR(_xlpm.CC="S", _xlpm.CDSM="S"), OR(_xlpm.RT="NA", _xlpm.RT="")), "❌", IF(AND(_xlpm.CC="N", _xlpm.CDSM="N", _xlpm.RT<>"NA"), "❌", IF(AND(_xlpm.CC="N", _xlpm.CDSM="N"), "✅", IF(AND(OR(_xlpm.CC="S", _xlpm.CDSM="S"), _xlpm.RT<>"NA"), "✅", "⚠️")))) )} -> #N/A | E5: {=_xlfn.LET( _xlpm.CC, INDEX(INDIRECT("'"&A$3&"'!$1:$1048576"), ROW(), MATCH("FORMATO", INDIRECT("'"&A$3&"'!$2:$2"), 0)), IF(_xlpm.CC="NUMBER", "✅", IF(_xlpm.CC="DATE", "✅", IF(_xlpm.CC="VARCHAR", "✅", IF(_xlpm.CC="TIMESTAMP", "✅", "❌")))) )} -> #N/A
A6: 5 | B6: {=_xlfn.LET( _xlpm.AA, INDEX(INDIRECT("'"&A$3&"'!$1:$1048576"), ROW(), MATCH("FLAG_PK", INDIRECT("'"&A$3&"'!$2:$2"), 0)), _xlpm.BB, INDEX(INDIRECT("'"&A$3&"'!$1:$1048576"), ROW(), MATCH("FORMATO", INDIRECT("'"&A$3&"'!$2:$2"), 0)), _xlpm.CC, INDEX(INDIRECT("'"&A$3&"'!$1:$1048576"), ROW(), MATCH("LENGTH", INDIRECT("'"&A$3&"'!$2:$2"), 0)), _xlpm.DD, INDEX(INDIRECT("'"&A$3&"'!$1:$1048576"), ROW(), MATCH("DECIMAL", INDIRECT("'"&A$3&"'!$2:$2"), 0)), _xlpm.FF, INDEX(INDIRECT("'"&A$3&"'!$1:$1048576"), ROW(), MATCH("CAMPO CALCOLATO", INDIRECT("'"&A$3&"'!$2:$2"), 0)), _xlpm.GG, INDEX(INDIRECT("'"&A$3&"'!$1:$1048576"), ROW(), MATCH("CAMPO DA SORGENTE NON MAIN", INDIRECT("'"&A$3&"'!$2:$2"), 0)), _xlpm.HH, INDEX(INDIRECT("'"&A$3&"'!$1:$1048576"), ROW(), MATCH("REGOLA TECNICA", INDIRECT("'"&A$3&"'!$2:$2"), 0)), _xlpm.II, INDEX(INDIRECT("'"&A$3&"'!$1:$1048576"), ROW(), MATCH("CHIAVI DI AGGANCIO", INDIRECT("'"&A$3&"'!$2:$2"), 0)), _xlpm.LL, INDEX(INDIRECT("'"&A$3&"'!$1:$1048576"), ROW(), MATCH("DATI SENSIBILI", INDIRECT("'"&A$3&"'!$2:$2"), 0)), IF(_xlpm.AA="","❌ (FLAG_PK)", IF(_xlpm.BB="","❌ (FORMATO)", IF(_xlpm.CC="","❌ (LENGTH)", IF(_xlpm.DD="","❌ (DECIMAL)", IF(_xlpm.FF="","❌ (CAMPO CALCOLATO)", IF(_xlpm.GG="","❌ (CAMPO DA SORGENTE NON MAIN)", IF(_xlpm.HH="","❌ (REGOLA TECNICA)", IF(_xlpm.II="","❌ (CHIAVI DI AGGANCIO)", IF(_xlpm.LL="","❌ (DATI SENSIBILI)", "✅"))))))))) )} -> #N/A | C6: {=IF( INDEX(INDIRECT("'"&A$3&"'!$1:$1048576"), ROW(), MATCH("CAMPO DA SORGENTE NON MAIN", INDIRECT("'"&A$3&"'!$2:$2"), 0))="S", IF(INDEX(INDIRECT("'"&A$3&"'!$1:$1048576"), ROW(), MATCH("CHIAVI DI AGGANCIO", INDIRECT("'"&A$3&"'!$2:$2"), 0))="NA", "❌", "✅"), IF( INDEX(INDIRECT("'"&A$3&"'!$1:$1048576"), ROW(), MATCH("CAMPO DA SORGENTE NON MAIN", INDIRECT("'"&A$3&"'!$2:$2"), 0))="N", IF(INDEX(INDIRECT("'"&A$3&"'!$1:$1048576"), ROW(), MATCH("CHIAVI DI AGGANCIO", INDIRECT("'"&A$3&"'!$2:$2"), 0))<>"NA", "❌", "✅"), "⚠️" ) )} -> #N/A | D6: {=_xlfn.LET( _xlpm.CC, INDEX(INDIRECT("'"&A$3&"'!$1:$1048576"), ROW(), MATCH("CAMPO CALCOLATO", INDIRECT("'"&A$3&"'!$2:$2"), 0)), _xlpm.CDSM, INDEX(INDIRECT("'"&A$3&"'!$1:$1048576"), ROW(), MATCH("CAMPO DA SORGENTE NON MAIN", INDIRECT("'"&A$3&"'!$2:$2"), 0)), _xlpm.RT, INDEX(INDIRECT("'"&A$3&"'!$1:$1048576"), ROW(), MATCH("REGOLA TECNICA", INDIRECT("'"&A$3&"'!$2:$2"), 0)), IF(AND(OR(_xlpm.CC="S", _xlpm.CDSM="S"), OR(_xlpm.RT="NA", _xlpm.RT="")), "❌", IF(AND(_xlpm.CC="N", _xlpm.CDSM="N", _xlpm.RT<>"NA"), "❌", IF(AND(_xlpm.CC="N", _xlpm.CDSM="N"), "✅", IF(AND(OR(_xlpm.CC="S", _xlpm.CDSM="S"), _xlpm.RT<>"NA"), "✅", "⚠️")))) )} -> #N/A | E6: {=_xlfn.LET( _xlpm.CC, INDEX(INDIRECT("'"&A$3&"'!$1:$1048576"), ROW(), MATCH("FORMATO", INDIRECT("'"&A$3&"'!$2:$2"), 0)), IF(_xlpm.CC="NUMBER", "✅", IF(_xlpm.CC="DATE", "✅", IF(_xlpm.CC="VARCHAR", "✅", IF(_xlpm.CC="TIMESTAMP", "✅", "❌")))) )} -> #N/A
A7: 6 | B7: {=_xlfn.LET( _xlpm.AA, INDEX(INDIRECT("'"&A$3&"'!$1:$1048576"), ROW(), MATCH("FLAG_PK", INDIRECT("'"&A$3&"'!$2:$2"), 0)), _xlpm.BB, INDEX(INDIRECT("'"&A$3&"'!$1:$1048576"), ROW(), MATCH("FORMATO", INDIRECT("'"&A$3&"'!$2:$2"), 0)), _xlpm.CC, INDEX(INDIRECT("'"&A$3&"'!$1:$1048576"), ROW(), MATCH("LENGTH", INDIRECT("'"&A$3&"'!$2:$2"), 0)), _xlpm.DD, INDEX(INDIRECT("'"&A$3&"'!$1:$1048576"), ROW(), MATCH("DECIMAL", INDIRECT("'"&A$3&"'!$2:$2"), 0)), _xlpm.FF, INDEX(INDIRECT("'"&A$3&"'!$1:$1048576"), ROW(), MATCH("CAMPO CALCOLATO", INDIRECT("'"&A$3&"'!$2:$2"), 0)), _xlpm.GG, INDEX(INDIRECT("'"&A$3&"'!$1:$1048576"), ROW(), MATCH("CAMPO DA SORGENTE NON MAIN", INDIRECT("'"&A$3&"'!$2:$2"), 0)), _xlpm.HH, INDEX(INDIRECT("'"&A$3&"'!$1:$1048576"), ROW(), MATCH("REGOLA TECNICA", INDIRECT("'"&A$3&"'!$2:$2"), 0)), _xlpm.II, INDEX(INDIRECT("'"&A$3&"'!$1:$1048576"), ROW(), MATCH("CHIAVI DI AGGANCIO", INDIRECT("'"&A$3&"'!$2:$2"), 0)), _xlpm.LL, INDEX(INDIRECT("'"&A$3&"'!$1:$1048576"), ROW(), MATCH("DATI SENSIBILI", INDIRECT("'"&A$3&"'!$2:$2"), 0)), IF(_xlpm.AA="","❌ (FLAG_PK)", IF(_xlpm.BB="","❌ (FORMATO)", IF(_xlpm.CC="","❌ (LENGTH)", IF(_xlpm.DD="","❌ (DECIMAL)", IF(_xlpm.FF="","❌ (CAMPO CALCOLATO)", IF(_xlpm.GG="","❌ (CAMPO DA SORGENTE NON MAIN)", IF(_xlpm.HH="","❌ (REGOLA TECNICA)", IF(_xlpm.II="","❌ (CHIAVI DI AGGANCIO)", IF(_xlpm.LL="","❌ (DATI SENSIBILI)", "✅"))))))))) )} -> #N/A | C7: {=IF( INDEX(INDIRECT("'"&A$3&"'!$1:$1048576"), ROW(), MATCH("CAMPO DA SORGENTE NON MAIN", INDIRECT("'"&A$3&"'!$2:$2"), 0))="S", IF(INDEX(INDIRECT("'"&A$3&"'!$1:$1048576"), ROW(), MATCH("CHIAVI DI AGGANCIO", INDIRECT("'"&A$3&"'!$2:$2"), 0))="NA", "❌", "✅"), IF( INDEX(INDIRECT("'"&A$3&"'!$1:$1048576"), ROW(), MATCH("CAMPO DA SORGENTE NON MAIN", INDIRECT("'"&A$3&"'!$2:$2"), 0))="N", IF(INDEX(INDIRECT("'"&A$3&"'!$1:$1048576"), ROW(), MATCH("CHIAVI DI AGGANCIO", INDIRECT("'"&A$3&"'!$2:$2"), 0))<>"NA", "❌", "✅"), "⚠️" ) )} -> #N/A | D7: {=_xlfn.LET( _xlpm.CC, INDEX(INDIRECT("'"&A$3&"'!$1:$1048576"), ROW(), MATCH("CAMPO CALCOLATO", INDIRECT("'"&A$3&"'!$2:$2"), 0)), _xlpm.CDSM, INDEX(INDIRECT("'"&A$3&"'!$1:$1048576"), ROW(), MATCH("CAMPO DA SORGENTE NON MAIN", INDIRECT("'"&A$3&"'!$2:$2"), 0)), _xlpm.RT, INDEX(INDIRECT("'"&A$3&"'!$1:$1048576"), ROW(), MATCH("REGOLA TECNICA", INDIRECT("'"&A$3&"'!$2:$2"), 0)), IF(AND(OR(_xlpm.CC="S", _xlpm.CDSM="S"), OR(_xlpm.RT="NA", _xlpm.RT="")), "❌", IF(AND(_xlpm.CC="N", _xlpm.CDSM="N", _xlpm.RT<>"NA"), "❌", IF(AND(_xlpm.CC="N", _xlpm.CDSM="N"), "✅", IF(AND(OR(_xlpm.CC="S", _xlpm.CDSM="S"), _xlpm.RT<>"NA"), "✅", "⚠️")))) )} -> #N/A | E7: {=_xlfn.LET( _xlpm.CC, INDEX(INDIRECT("'"&A$3&"'!$1:$1048576"), ROW(), MATCH("FORMATO", INDIRECT("'"&A$3&"'!$2:$2"), 0)), IF(_xlpm.CC="NUMBER", "✅", IF(_xlpm.CC="DATE", "✅", IF(_xlpm.CC="VARCHAR", "✅", IF(_xlpm.CC="TIMESTAMP", "✅", "❌")))) )} -> #N/A
A8: 7 | B8: {=_xlfn.LET( _xlpm.AA, INDEX(INDIRECT("'"&A$3&"'!$1:$1048576"), ROW(), MATCH("FLAG_PK", INDIRECT("'"&A$3&"'!$2:$2"), 0)), _xlpm.BB, INDEX(INDIRECT("'"&A$3&"'!$1:$1048576"), ROW(), MATCH("FORMATO", INDIRECT("'"&A$3&"'!$2:$2"), 0)), _xlpm.CC, INDEX(INDIRECT("'"&A$3&"'!$1:$1048576"), ROW(), MATCH("LENGTH", INDIRECT("'"&A$3&"'!$2:$2"), 0)), _xlpm.DD, INDEX(INDIRECT("'"&A$3&"'!$1:$1048576"), ROW(), MATCH("DECIMAL", INDIRECT("'"&A$3&"'!$2:$2"), 0)), _xlpm.FF, INDEX(INDIRECT("'"&A$3&"'!$1:$1048576"), ROW(), MATCH("CAMPO CALCOLATO", INDIRECT("'"&A$3&"'!$2:$2"), 0)), _xlpm.GG, INDEX(INDIRECT("'"&A$3&"'!$1:$1048576"), ROW(), MATCH("CAMPO DA SORGENTE NON MAIN", INDIRECT("'"&A$3&"'!$2:$2"), 0)), _xlpm.HH, INDEX(INDIRECT("'"&A$3&"'!$1:$1048576"), ROW(), MATCH("REGOLA TECNICA", INDIRECT("'"&A$3&"'!$2:$2"), 0)), _xlpm.II, INDEX(INDIRECT("'"&A$3&"'!$1:$1048576"), ROW(), MATCH("CHIAVI DI AGGANCIO", INDIRECT("'"&A$3&"'!$2:$2"), 0)), _xlpm.LL, INDEX(INDIRECT("'"&A$3&"'!$1:$1048576"), ROW(), MATCH("DATI SENSIBILI", INDIRECT("'"&A$3&"'!$2:$2"), 0)), IF(_xlpm.AA="","❌ (FLAG_PK)", IF(_xlpm.BB="","❌ (FORMATO)", IF(_xlpm.CC="","❌ (LENGTH)", IF(_xlpm.DD="","❌ (DECIMAL)", IF(_xlpm.FF="","❌ (CAMPO CALCOLATO)", IF(_xlpm.GG="","❌ (CAMPO DA SORGENTE NON MAIN)", IF(_xlpm.HH="","❌ (REGOLA TECNICA)", IF(_xlpm.II="","❌ (CHIAVI DI AGGANCIO)", IF(_xlpm.LL="","❌ (DATI SENSIBILI)", "✅"))))))))) )} -> #N/A | C8: {=IF( INDEX(INDIRECT("'"&A$3&"'!$1:$1048576"), ROW(), MATCH("CAMPO DA SORGENTE NON MAIN", INDIRECT("'"&A$3&"'!$2:$2"), 0))="S", IF(INDEX(INDIRECT("'"&A$3&"'!$1:$1048576"), ROW(), MATCH("CHIAVI DI AGGANCIO", INDIRECT("'"&A$3&"'!$2:$2"), 0))="NA", "❌", "✅"), IF( INDEX(INDIRECT("'"&A$3&"'!$1:$1048576"), ROW(), MATCH("CAMPO DA SORGENTE NON MAIN", INDIRECT("'"&A$3&"'!$2:$2"), 0))="N", IF(INDEX(INDIRECT("'"&A$3&"'!$1:$1048576"), ROW(), MATCH("CHIAVI DI AGGANCIO", INDIRECT("'"&A$3&"'!$2:$2"), 0))<>"NA", "❌", "✅"), "⚠️" ) )} -> #N/A | D8: {=_xlfn.LET( _xlpm.CC, INDEX(INDIRECT("'"&A$3&"'!$1:$1048576"), ROW(), MATCH("CAMPO CALCOLATO", INDIRECT("'"&A$3&"'!$2:$2"), 0)), _xlpm.CDSM, INDEX(INDIRECT("'"&A$3&"'!$1:$1048576"), ROW(), MATCH("CAMPO DA SORGENTE NON MAIN", INDIRECT("'"&A$3&"'!$2:$2"), 0)), _xlpm.RT, INDEX(INDIRECT("'"&A$3&"'!$1:$1048576"), ROW(), MATCH("REGOLA TECNICA", INDIRECT("'"&A$3&"'!$2:$2"), 0)), IF(AND(OR(_xlpm.CC="S", _xlpm.CDSM="S"), OR(_xlpm.RT="NA", _xlpm.RT="")), "❌", IF(AND(_xlpm.CC="N", _xlpm.CDSM="N", _xlpm.RT<>"NA"), "❌", IF(AND(_xlpm.CC="N", _xlpm.CDSM="N"), "✅", IF(AND(OR(_xlpm.CC="S", _xlpm.CDSM="S"), _xlpm.RT<>"NA"), "✅", "⚠️")))) )} -> #N/A | E8: {=_xlfn.LET( _xlpm.CC, INDEX(INDIRECT("'"&A$3&"'!$1:$1048576"), ROW(), MATCH("FORMATO", INDIRECT("'"&A$3&"'!$2:$2"), 0)), IF(_xlpm.CC="NUMBER", "✅", IF(_xlpm.CC="DATE", "✅", IF(_xlpm.CC="VARCHAR", "✅", IF(_xlpm.CC="TIMESTAMP", "✅", "❌")))) )} -> #N/A
A9: 8 | B9: {=_xlfn.LET( _xlpm.AA, INDEX(INDIRECT("'"&A$3&"'!$1:$1048576"), ROW(), MATCH("FLAG_PK", INDIRECT("'"&A$3&"'!$2:$2"), 0)), _xlpm.BB, INDEX(INDIRECT("'"&A$3&"'!$1:$1048576"), ROW(), MATCH("FORMATO", INDIRECT("'"&A$3&"'!$2:$2"), 0)), _xlpm.CC, INDEX(INDIRECT("'"&A$3&"'!$1:$1048576"), ROW(), MATCH("LENGTH", INDIRECT("'"&A$3&"'!$2:$2"), 0)), _xlpm.DD, INDEX(INDIRECT("'"&A$3&"'!$1:$1048576"), ROW(), MATCH("DECIMAL", INDIRECT("'"&A$3&"'!$2:$2"), 0)), _xlpm.FF, INDEX(INDIRECT("'"&A$3&"'!$1:$1048576"), ROW(), MATCH("CAMPO CALCOLATO", INDIRECT("'"&A$3&"'!$2:$2"), 0)), _xlpm.GG, INDEX(INDIRECT("'"&A$3&"'!$1:$1048576"), ROW(), MATCH("CAMPO DA SORGENTE NON MAIN", INDIRECT("'"&A$3&"'!$2:$2"), 0)), _xlpm.HH, INDEX(INDIRECT("'"&A$3&"'!$1:$1048576"), ROW(), MATCH("REGOLA TECNICA", INDIRECT("'"&A$3&"'!$2:$2"), 0)), _xlpm.II, INDEX(INDIRECT("'"&A$3&"'!$1:$1048576"), ROW(), MATCH("CHIAVI DI AGGANCIO", INDIRECT("'"&A$3&"'!$2:$2"), 0)), _xlpm.LL, INDEX(INDIRECT("'"&A$3&"'!$1:$1048576"), ROW(), MATCH("DATI SENSIBILI", INDIRECT("'"&A$3&"'!$2:$2"), 0)), IF(_xlpm.AA="","❌ (FLAG_PK)", IF(_xlpm.BB="","❌ (FORMATO)", IF(_xlpm.CC="","❌ (LENGTH)", IF(_xlpm.DD="","❌ (DECIMAL)", IF(_xlpm.FF="","❌ (CAMPO CALCOLATO)", IF(_xlpm.GG="","❌ (CAMPO DA SORGENTE NON MAIN)", IF(_xlpm.HH="","❌ (REGOLA TECNICA)", IF(_xlpm.II="","❌ (CHIAVI DI AGGANCIO)", IF(_xlpm.LL="","❌ (DATI SENSIBILI)", "✅"))))))))) )} -> #N/A | C9: {=IF( INDEX(INDIRECT("'"&A$3&"'!$1:$1048576"), ROW(), MATCH("CAMPO DA SORGENTE NON MAIN", INDIRECT("'"&A$3&"'!$2:$2"), 0))="S", IF(INDEX(INDIRECT("'"&A$3&"'!$1:$1048576"), ROW(), MATCH("CHIAVI DI AGGANCIO", INDIRECT("'"&A$3&"'!$2:$2"), 0))="NA", "❌", "✅"), IF( INDEX(INDIRECT("'"&A$3&"'!$1:$1048576"), ROW(), MATCH("CAMPO DA SORGENTE NON MAIN", INDIRECT("'"&A$3&"'!$2:$2"), 0))="N", IF(INDEX(INDIRECT("'"&A$3&"'!$1:$1048576"), ROW(), MATCH("CHIAVI DI AGGANCIO", INDIRECT("'"&A$3&"'!$2:$2"), 0))<>"NA", "❌", "✅"), "⚠️" ) )} -> #N/A | D9: {=_xlfn.LET( _xlpm.CC, INDEX(INDIRECT("'"&A$3&"'!$1:$1048576"), ROW(), MATCH("CAMPO CALCOLATO", INDIRECT("'"&A$3&"'!$2:$2"), 0)), _xlpm.CDSM, INDEX(INDIRECT("'"&A$3&"'!$1:$1048576"), ROW(), MATCH("CAMPO DA SORGENTE NON MAIN", INDIRECT("'"&A$3&"'!$2:$2"), 0)), _xlpm.RT, INDEX(INDIRECT("'"&A$3&"'!$1:$1048576"), ROW(), MATCH("REGOLA TECNICA", INDIRECT("'"&A$3&"'!$2:$2"), 0)), IF(AND(OR(_xlpm.CC="S", _xlpm.CDSM="S"), OR(_xlpm.RT="NA", _xlpm.RT="")), "❌", IF(AND(_xlpm.CC="N", _xlpm.CDSM="N", _xlpm.RT<>"NA"), "❌", IF(AND(_xlpm.CC="N", _xlpm.CDSM="N"), "✅", IF(AND(OR(_xlpm.CC="S", _xlpm.CDSM="S"), _xlpm.RT<>"NA"), "✅", "⚠️")))) )} -> #N/A | E9: {=_xlfn.LET( _xlpm.CC, INDEX(INDIRECT("'"&A$3&"'!$1:$1048576"), ROW(), MATCH("FORMATO", INDIRECT("'"&A$3&"'!$2:$2"), 0)), IF(_xlpm.CC="NUMBER", "✅", IF(_xlpm.CC="DATE", "✅", IF(_xlpm.CC="VARCHAR", "✅", IF(_xlpm.CC="TIMESTAMP", "✅", "❌")))) )} -> #N/A
A10: 9 | B10: {=_xlfn.LET( _xlpm.AA, INDEX(INDIRECT("'"&A$3&"'!$1:$1048576"), ROW(), MATCH("FLAG_PK", INDIRECT("'"&A$3&"'!$2:$2"), 0)), _xlpm.BB, INDEX(INDIRECT("'"&A$3&"'!$1:$1048576"), ROW(), MATCH("FORMATO", INDIRECT("'"&A$3&"'!$2:$2"), 0)), _xlpm.CC, INDEX(INDIRECT("'"&A$3&"'!$1:$1048576"), ROW(), MATCH("LENGTH", INDIRECT("'"&A$3&"'!$2:$2"), 0)), _xlpm.DD, INDEX(INDIRECT("'"&A$3&"'!$1:$1048576"), ROW(), MATCH("DECIMAL", INDIRECT("'"&A$3&"'!$2:$2"), 0)), _xlpm.FF, INDEX(INDIRECT("'"&A$3&"'!$1:$1048576"), ROW(), MATCH("CAMPO CALCOLATO", INDIRECT("'"&A$3&"'!$2:$2"), 0)), _xlpm.GG, INDEX(INDIRECT("'"&A$3&"'!$1:$1048576"), ROW(), MATCH("CAMPO DA SORGENTE NON MAIN", INDIRECT("'"&A$3&"'!$2:$2"), 0)), _xlpm.HH, INDEX(INDIRECT("'"&A$3&"'!$1:$1048576"), ROW(), MATCH("REGOLA TECNICA", INDIRECT("'"&A$3&"'!$2:$2"), 0)), _xlpm.II, INDEX(INDIRECT("'"&A$3&"'!$1:$1048576"), ROW(), MATCH("CHIAVI DI AGGANCIO", INDIRECT("'"&A$3&"'!$2:$2"), 0)), _xlpm.LL, INDEX(INDIRECT("'"&A$3&"'!$1:$1048576"), ROW(), MATCH("DATI SENSIBILI", INDIRECT("'"&A$3&"'!$2:$2"), 0)), IF(_xlpm.AA="","❌ (FLAG_PK)", IF(_xlpm.BB="","❌ (FORMATO)", IF(_xlpm.CC="","❌ (LENGTH)", IF(_xlpm.DD="","❌ (DECIMAL)", IF(_xlpm.FF="","❌ (CAMPO CALCOLATO)", IF(_xlpm.GG="","❌ (CAMPO DA SORGENTE NON MAIN)", IF(_xlpm.HH="","❌ (REGOLA TECNICA)", IF(_xlpm.II="","❌ (CHIAVI DI AGGANCIO)", IF(_xlpm.LL="","❌ (DATI SENSIBILI)", "✅"))))))))) )} -> #N/A | C10: {=IF( INDEX(INDIRECT("'"&A$3&"'!$1:$1048576"), ROW(), MATCH("CAMPO DA SORGENTE NON MAIN", INDIRECT("'"&A$3&"'!$2:$2"), 0))="S", IF(INDEX(INDIRECT("'"&A$3&"'!$1:$1048576"), ROW(), MATCH("CHIAVI DI AGGANCIO", INDIRECT("'"&A$3&"'!$2:$2"), 0))="NA", "❌", "✅"), IF( INDEX(INDIRECT("'"&A$3&"'!$1:$1048576"), ROW(), MATCH("CAMPO DA SORGENTE NON MAIN", INDIRECT("'"&A$3&"'!$2:$2"), 0))="N", IF(INDEX(INDIRECT("'"&A$3&"'!$1:$1048576"), ROW(), MATCH("CHIAVI DI AGGANCIO", INDIRECT("'"&A$3&"'!$2:$2"), 0))<>"NA", "❌", "✅"), "⚠️" ) )} -> #N/A | D10: {=_xlfn.LET( _xlpm.CC, INDEX(INDIRECT("'"&A$3&"'!$1:$1048576"), ROW(), MATCH("CAMPO CALCOLATO", INDIRECT("'"&A$3&"'!$2:$2"), 0)), _xlpm.CDSM, INDEX(INDIRECT("'"&A$3&"'!$1:$1048576"), ROW(), MATCH("CAMPO DA SORGENTE NON MAIN", INDIRECT("'"&A$3&"'!$2:$2"), 0)), _xlpm.RT, INDEX(INDIRECT("'"&A$3&"'!$1:$1048576"), ROW(), MATCH("REGOLA TECNICA", INDIRECT("'"&A$3&"'!$2:$2"), 0)), IF(AND(OR(_xlpm.CC="S", _xlpm.CDSM="S"), OR(_xlpm.RT="NA", _xlpm.RT="")), "❌", IF(AND(_xlpm.CC="N", _xlpm.CDSM="N", _xlpm.RT<>"NA"), "❌", IF(AND(_xlpm.CC="N", _xlpm.CDSM="N"), "✅", IF(AND(OR(_xlpm.CC="S", _xlpm.CDSM="S"), _xlpm.RT<>"NA"), "✅", "⚠️")))) )} -> #N/A | E10: {=_xlfn.LET( _xlpm.CC, INDEX(INDIRECT("'"&A$3&"'!$1:$1048576"), ROW(), MATCH("FORMATO", INDIRECT("'"&A$3&"'!$2:$2"), 0)), IF(_xlpm.CC="NUMBER", "✅", IF(_xlpm.CC="DATE", "✅", IF(_xlpm.CC="VARCHAR", "✅", IF(_xlpm.CC="TIMESTAMP", "✅", "❌")))) )} -> #N/A
A11: 10 | B11: {=_xlfn.LET( _xlpm.AA, INDEX(INDIRECT("'"&A$3&"'!$1:$1048576"), ROW(), MATCH("FLAG_PK", INDIRECT("'"&A$3&"'!$2:$2"), 0)), _xlpm.BB, INDEX(INDIRECT("'"&A$3&"'!$1:$1048576"), ROW(), MATCH("FORMATO", INDIRECT("'"&A$3&"'!$2:$2"), 0)), _xlpm.CC, INDEX(INDIRECT("'"&A$3&"'!$1:$1048576"), ROW(), MATCH("LENGTH", INDIRECT("'"&A$3&"'!$2:$2"), 0)), _xlpm.DD, INDEX(INDIRECT("'"&A$3&"'!$1:$1048576"), ROW(), MATCH("DECIMAL", INDIRECT("'"&A$3&"'!$2:$2"), 0)), _xlpm.FF, INDEX(INDIRECT("'"&A$3&"'!$1:$1048576"), ROW(), MATCH("CAMPO CALCOLATO", INDIRECT("'"&A$3&"'!$2:$2"), 0)), _xlpm.GG, INDEX(INDIRECT("'"&A$3&"'!$1:$1048576"), ROW(), MATCH("CAMPO DA SORGENTE NON MAIN", INDIRECT("'"&A$3&"'!$2:$2"), 0)), _xlpm.HH, INDEX(INDIRECT("'"&A$3&"'!$1:$1048576"), ROW(), MATCH("REGOLA TECNICA", INDIRECT("'"&A$3&"'!$2:$2"), 0)), _xlpm.II, INDEX(INDIRECT("'"&A$3&"'!$1:$1048576"), ROW(), MATCH("CHIAVI DI AGGANCIO", INDIRECT("'"&A$3&"'!$2:$2"), 0)), _xlpm.LL, INDEX(INDIRECT("'"&A$3&"'!$1:$1048576"), ROW(), MATCH("DATI SENSIBILI", INDIRECT("'"&A$3&"'!$2:$2"), 0)), IF(_xlpm.AA="","❌ (FLAG_PK)", IF(_xlpm.BB="","❌ (FORMATO)", IF(_xlpm.CC="","❌ (LENGTH)", IF(_xlpm.DD="","❌ (DECIMAL)", IF(_xlpm.FF="","❌ (CAMPO CALCOLATO)", IF(_xlpm.GG="","❌ (CAMPO DA SORGENTE NON MAIN)", IF(_xlpm.HH="","❌ (REGOLA TECNICA)", IF(_xlpm.II="","❌ (CHIAVI DI AGGANCIO)", IF(_xlpm.LL="","❌ (DATI SENSIBILI)", "✅"))))))))) )} -> #N/A | C11: {=IF( INDEX(INDIRECT("'"&A$3&"'!$1:$1048576"), ROW(), MATCH("CAMPO DA SORGENTE NON MAIN", INDIRECT("'"&A$3&"'!$2:$2"), 0))="S", IF(INDEX(INDIRECT("'"&A$3&"'!$1:$1048576"), ROW(), MATCH("CHIAVI DI AGGANCIO", INDIRECT("'"&A$3&"'!$2:$2"), 0))="NA", "❌", "✅"), IF( INDEX(INDIRECT("'"&A$3&"'!$1:$1048576"), ROW(), MATCH("CAMPO DA SORGENTE NON MAIN", INDIRECT("'"&A$3&"'!$2:$2"), 0))="N", IF(INDEX(INDIRECT("'"&A$3&"'!$1:$1048576"), ROW(), MATCH("CHIAVI DI AGGANCIO", INDIRECT("'"&A$3&"'!$2:$2"), 0))<>"NA", "❌", "✅"), "⚠️" ) )} -> #N/A | D11: {=_xlfn.LET( _xlpm.CC, INDEX(INDIRECT("'"&A$3&"'!$1:$1048576"), ROW(), MATCH("CAMPO CALCOLATO", INDIRECT("'"&A$3&"'!$2:$2"), 0)), _xlpm.CDSM, INDEX(INDIRECT("'"&A$3&"'!$1:$1048576"), ROW(), MATCH("CAMPO DA SORGENTE NON MAIN", INDIRECT("'"&A$3&"'!$2:$2"), 0)), _xlpm.RT, INDEX(INDIRECT("'"&A$3&"'!$1:$1048576"), ROW(), MATCH("REGOLA TECNICA", INDIRECT("'"&A$3&"'!$2:$2"), 0)), IF(AND(OR(_xlpm.CC="S", _xlpm.CDSM="S"), OR(_xlpm.RT="NA", _xlpm.RT="")), "❌", IF(AND(_xlpm.CC="N", _xlpm.CDSM="N", _xlpm.RT<>"NA"), "❌", IF(AND(_xlpm.CC="N", _xlpm.CDSM="N"), "✅", IF(AND(OR(_xlpm.CC="S", _xlpm.CDSM="S"), _xlpm.RT<>"NA"), "✅", "⚠️")))) )} -> #N/A | E11: {=_xlfn.LET( _xlpm.CC, INDEX(INDIRECT("'"&A$3&"'!$1:$1048576"), ROW(), MATCH("FORMATO", INDIRECT("'"&A$3&"'!$2:$2"), 0)), IF(_xlpm.CC="NUMBER", "✅", IF(_xlpm.CC="DATE", "✅", IF(_xlpm.CC="VARCHAR", "✅", IF(_xlpm.CC="TIMESTAMP", "✅", "❌")))) )} -> #N/A
A12: 11 | B12: {=_xlfn.LET( _xlpm.AA, INDEX(INDIRECT("'"&A$3&"'!$1:$1048576"), ROW(), MATCH("FLAG_PK", INDIRECT("'"&A$3&"'!$2:$2"), 0)), _xlpm.BB, INDEX(INDIRECT("'"&A$3&"'!$1:$1048576"), ROW(), MATCH("FORMATO", INDIRECT("'"&A$3&"'!$2:$2"), 0)), _xlpm.CC, INDEX(INDIRECT("'"&A$3&"'!$1:$1048576"), ROW(), MATCH("LENGTH", INDIRECT("'"&A$3&"'!$2:$2"), 0)), _xlpm.DD, INDEX(INDIRECT("'"&A$3&"'!$1:$1048576"), ROW(), MATCH("DECIMAL", INDIRECT("'"&A$3&"'!$2:$2"), 0)), _xlpm.FF, INDEX(INDIRECT("'"&A$3&"'!$1:$1048576"), ROW(), MATCH("CAMPO CALCOLATO", INDIRECT("'"&A$3&"'!$2:$2"), 0)), _xlpm.GG, INDEX(INDIRECT("'"&A$3&"'!$1:$1048576"), ROW(), MATCH("CAMPO DA SORGENTE NON MAIN", INDIRECT("'"&A$3&"'!$2:$2"), 0)), _xlpm.HH, INDEX(INDIRECT("'"&A$3&"'!$1:$1048576"), ROW(), MATCH("REGOLA TECNICA", INDIRECT("'"&A$3&"'!$2:$2"), 0)), _xlpm.II, INDEX(INDIRECT("'"&A$3&"'!$1:$1048576"), ROW(), MATCH("CHIAVI DI AGGANCIO", INDIRECT("'"&A$3&"'!$2:$2"), 0)), _xlpm.LL, INDEX(INDIRECT("'"&A$3&"'!$1:$1048576"), ROW(), MATCH("DATI SENSIBILI", INDIRECT("'"&A$3&"'!$2:$2"), 0)), IF(_xlpm.AA="","❌ (FLAG_PK)", IF(_xlpm.BB="","❌ (FORMATO)", IF(_xlpm.CC="","❌ (LENGTH)", IF(_xlpm.DD="","❌ (DECIMAL)", IF(_xlpm.FF="","❌ (CAMPO CALCOLATO)", IF(_xlpm.GG="","❌ (CAMPO DA SORGENTE NON MAIN)", IF(_xlpm.HH="","❌ (REGOLA TECNICA)", IF(_xlpm.II="","❌ (CHIAVI DI AGGANCIO)", IF(_xlpm.LL="","❌ (DATI SENSIBILI)", "✅"))))))))) )} -> #N/A | C12: {=IF( INDEX(INDIRECT("'"&A$3&"'!$1:$1048576"), ROW(), MATCH("CAMPO DA SORGENTE NON MAIN", INDIRECT("'"&A$3&"'!$2:$2"), 0))="S", IF(INDEX(INDIRECT("'"&A$3&"'!$1:$1048576"), ROW(), MATCH("CHIAVI DI AGGANCIO", INDIRECT("'"&A$3&"'!$2:$2"), 0))="NA", "❌", "✅"), IF( INDEX(INDIRECT("'"&A$3&"'!$1:$1048576"), ROW(), MATCH("CAMPO DA SORGENTE NON MAIN", INDIRECT("'"&A$3&"'!$2:$2"), 0))="N", IF(INDEX(INDIRECT("'"&A$3&"'!$1:$1048576"), ROW(), MATCH("CHIAVI DI AGGANCIO", INDIRECT("'"&A$3&"'!$2:$2"), 0))<>"NA", "❌", "✅"), "⚠️" ) )} -> #N/A | D12: {=_xlfn.LET( _xlpm.CC, INDEX(INDIRECT("'"&A$3&"'!$1:$1048576"), ROW(), MATCH("CAMPO CALCOLATO", INDIRECT("'"&A$3&"'!$2:$2"), 0)), _xlpm.CDSM, INDEX(INDIRECT("'"&A$3&"'!$1:$1048576"), ROW(), MATCH("CAMPO DA SORGENTE NON MAIN", INDIRECT("'"&A$3&"'!$2:$2"), 0)), _xlpm.RT, INDEX(INDIRECT("'"&A$3&"'!$1:$1048576"), ROW(), MATCH("REGOLA TECNICA", INDIRECT("'"&A$3&"'!$2:$2"), 0)), IF(AND(OR(_xlpm.CC="S", _xlpm.CDSM="S"), OR(_xlpm.RT="NA", _xlpm.RT="")), "❌", IF(AND(_xlpm.CC="N", _xlpm.CDSM="N", _xlpm.RT<>"NA"), "❌", IF(AND(_xlpm.CC="N", _xlpm.CDSM="N"), "✅", IF(AND(OR(_xlpm.CC="S", _xlpm.CDSM="S"), _xlpm.RT<>"NA"), "✅", "⚠️")))) )} -> #N/A | E12: {=_xlfn.LET( _xlpm.CC, INDEX(INDIRECT("'"&A$3&"'!$1:$1048576"), ROW(), MATCH("FORMATO", INDIRECT("'"&A$3&"'!$2:$2"), 0)), IF(_xlpm.CC="NUMBER", "✅", IF(_xlpm.CC="DATE", "✅", IF(_xlpm.CC="VARCHAR", "✅", IF(_xlpm.CC="TIMESTAMP", "✅", "❌")))) )} -> #N/A
A13: 12 | B13: {=_xlfn.LET( _xlpm.AA, INDEX(INDIRECT("'"&A$3&"'!$1:$1048576"), ROW(), MATCH("FLAG_PK", INDIRECT("'"&A$3&"'!$2:$2"), 0)), _xlpm.BB, INDEX(INDIRECT("'"&A$3&"'!$1:$1048576"), ROW(), MATCH("FORMATO", INDIRECT("'"&A$3&"'!$2:$2"), 0)), _xlpm.CC, INDEX(INDIRECT("'"&A$3&"'!$1:$1048576"), ROW(), MATCH("LENGTH", INDIRECT("'"&A$3&"'!$2:$2"), 0)), _xlpm.DD, INDEX(INDIRECT("'"&A$3&"'!$1:$1048576"), ROW(), MATCH("DECIMAL", INDIRECT("'"&A$3&"'!$2:$2"), 0)), _xlpm.FF, INDEX(INDIRECT("'"&A$3&"'!$1:$1048576"), ROW(), MATCH("CAMPO CALCOLATO", INDIRECT("'"&A$3&"'!$2:$2"), 0)), _xlpm.GG, INDEX(INDIRECT("'"&A$3&"'!$1:$1048576"), ROW(), MATCH("CAMPO DA SORGENTE NON MAIN", INDIRECT("'"&A$3&"'!$2:$2"), 0)), _xlpm.HH, INDEX(INDIRECT("'"&A$3&"'!$1:$1048576"), ROW(), MATCH("REGOLA TECNICA", INDIRECT("'"&A$3&"'!$2:$2"), 0)), _xlpm.II, INDEX(INDIRECT("'"&A$3&"'!$1:$1048576"), ROW(), MATCH("CHIAVI DI AGGANCIO", INDIRECT("'"&A$3&"'!$2:$2"), 0)), _xlpm.LL, INDEX(INDIRECT("'"&A$3&"'!$1:$1048576"), ROW(), MATCH("DATI SENSIBILI", INDIRECT("'"&A$3&"'!$2:$2"), 0)), IF(_xlpm.AA="","❌ (FLAG_PK)", IF(_xlpm.BB="","❌ (FORMATO)", IF(_xlpm.CC="","❌ (LENGTH)", IF(_xlpm.DD="","❌ (DECIMAL)", IF(_xlpm.FF="","❌ (CAMPO CALCOLATO)", IF(_xlpm.GG="","❌ (CAMPO DA SORGENTE NON MAIN)", IF(_xlpm.HH="","❌ (REGOLA TECNICA)", IF(_xlpm.II="","❌ (CHIAVI DI AGGANCIO)", IF(_xlpm.LL="","❌ (DATI SENSIBILI)", "✅"))))))))) )} -> #N/A | C13: {=IF( INDEX(INDIRECT("'"&A$3&"'!$1:$1048576"), ROW(), MATCH("CAMPO DA SORGENTE NON MAIN", INDIRECT("'"&A$3&"'!$2:$2"), 0))="S", IF(INDEX(INDIRECT("'"&A$3&"'!$1:$1048576"), ROW(), MATCH("CHIAVI DI AGGANCIO", INDIRECT("'"&A$3&"'!$2:$2"), 0))="NA", "❌", "✅"), IF( INDEX(INDIRECT("'"&A$3&"'!$1:$1048576"), ROW(), MATCH("CAMPO DA SORGENTE NON MAIN", INDIRECT("'"&A$3&"'!$2:$2"), 0))="N", IF(INDEX(INDIRECT("'"&A$3&"'!$1:$1048576"), ROW(), MATCH("CHIAVI DI AGGANCIO", INDIRECT("'"&A$3&"'!$2:$2"), 0))<>"NA", "❌", "✅"), "⚠️" ) )} -> #N/A | D13: {=_xlfn.LET( _xlpm.CC, INDEX(INDIRECT("'"&A$3&"'!$1:$1048576"), ROW(), MATCH("CAMPO CALCOLATO", INDIRECT("'"&A$3&"'!$2:$2"), 0)), _xlpm.CDSM, INDEX(INDIRECT("'"&A$3&"'!$1:$1048576"), ROW(), MATCH("CAMPO DA SORGENTE NON MAIN", INDIRECT("'"&A$3&"'!$2:$2"), 0)), _xlpm.RT, INDEX(INDIRECT("'"&A$3&"'!$1:$1048576"), ROW(), MATCH("REGOLA TECNICA", INDIRECT("'"&A$3&"'!$2:$2"), 0)), IF(AND(OR(_xlpm.CC="S", _xlpm.CDSM="S"), OR(_xlpm.RT="NA", _xlpm.RT="")), "❌", IF(AND(_xlpm.CC="N", _xlpm.CDSM="N", _xlpm.RT<>"NA"), "❌", IF(AND(_xlpm.CC="N", _xlpm.CDSM="N"), "✅", IF(AND(OR(_xlpm.CC="S", _xlpm.CDSM="S"), _xlpm.RT<>"NA"), "✅", "⚠️")))) )} -> #N/A | E13: {=_xlfn.LET( _xlpm.CC, INDEX(INDIRECT("'"&A$3&"'!$1:$1048576"), ROW(), MATCH("FORMATO", INDIRECT("'"&A$3&"'!$2:$2"), 0)), IF(_xlpm.CC="NUMBER", "✅", IF(_xlpm.CC="DATE", "✅", IF(_xlpm.CC="VARCHAR", "✅", IF(_xlpm.CC="TIMESTAMP", "✅", "❌")))) )} -> #N/A
A14: 13 | B14: {=_xlfn.LET( _xlpm.AA, INDEX(INDIRECT("'"&A$3&"'!$1:$1048576"), ROW(), MATCH("FLAG_PK", INDIRECT("'"&A$3&"'!$2:$2"), 0)), _xlpm.BB, INDEX(INDIRECT("'"&A$3&"'!$1:$1048576"), ROW(), MATCH("FORMATO", INDIRECT("'"&A$3&"'!$2:$2"), 0)), _xlpm.CC, INDEX(INDIRECT("'"&A$3&"'!$1:$1048576"), ROW(), MATCH("LENGTH", INDIRECT("'"&A$3&"'!$2:$2"), 0)), _xlpm.DD, INDEX(INDIRECT("'"&A$3&"'!$1:$1048576"), ROW(), MATCH("DECIMAL", INDIRECT("'"&A$3&"'!$2:$2"), 0)), _xlpm.FF, INDEX(INDIRECT("'"&A$3&"'!$1:$1048576"), ROW(), MATCH("CAMPO CALCOLATO", INDIRECT("'"&A$3&"'!$2:$2"), 0)), _xlpm.GG, INDEX(INDIRECT("'"&A$3&"'!$1:$1048576"), ROW(), MATCH("CAMPO DA SORGENTE NON MAIN", INDIRECT("'"&A$3&"'!$2:$2"), 0)), _xlpm.HH, INDEX(INDIRECT("'"&A$3&"'!$1:$1048576"), ROW(), MATCH("REGOLA TECNICA", INDIRECT("'"&A$3&"'!$2:$2"), 0)), _xlpm.II, INDEX(INDIRECT("'"&A$3&"'!$1:$1048576"), ROW(), MATCH("CHIAVI DI AGGANCIO", INDIRECT("'"&A$3&"'!$2:$2"), 0)), _xlpm.LL, INDEX(INDIRECT("'"&A$3&"'!$1:$1048576"), ROW(), MATCH("DATI SENSIBILI", INDIRECT("'"&A$3&"'!$2:$2"), 0)), IF(_xlpm.AA="","❌ (FLAG_PK)", IF(_xlpm.BB="","❌ (FORMATO)", IF(_xlpm.CC="","❌ (LENGTH)", IF(_xlpm.DD="","❌ (DECIMAL)", IF(_xlpm.FF="","❌ (CAMPO CALCOLATO)", IF(_xlpm.GG="","❌ (CAMPO DA SORGENTE NON MAIN)", IF(_xlpm.HH="","❌ (REGOLA TECNICA)", IF(_xlpm.II="","❌ (CHIAVI DI AGGANCIO)", IF(_xlpm.LL="","❌ (DATI SENSIBILI)", "✅"))))))))) )} -> #N/A | C14: {=IF( INDEX(INDIRECT("'"&A$3&"'!$1:$1048576"), ROW(), MATCH("CAMPO DA SORGENTE NON MAIN", INDIRECT("'"&A$3&"'!$2:$2"), 0))="S", IF(INDEX(INDIRECT("'"&A$3&"'!$1:$1048576"), ROW(), MATCH("CHIAVI DI AGGANCIO", INDIRECT("'"&A$3&"'!$2:$2"), 0))="NA", "❌", "✅"), IF( INDEX(INDIRECT("'"&A$3&"'!$1:$1048576"), ROW(), MATCH("CAMPO DA SORGENTE NON MAIN", INDIRECT("'"&A$3&"'!$2:$2"), 0))="N", IF(INDEX(INDIRECT("'"&A$3&"'!$1:$1048576"), ROW(), MATCH("CHIAVI DI AGGANCIO", INDIRECT("'"&A$3&"'!$2:$2"), 0))<>"NA", "❌", "✅"), "⚠️" ) )} -> #N/A | D14: {=_xlfn.LET( _xlpm.CC, INDEX(INDIRECT("'"&A$3&"'!$1:$1048576"), ROW(), MATCH("CAMPO CALCOLATO", INDIRECT("'"&A$3&"'!$2:$2"), 0)), _xlpm.CDSM, INDEX(INDIRECT("'"&A$3&"'!$1:$1048576"), ROW(), MATCH("CAMPO DA SORGENTE NON MAIN", INDIRECT("'"&A$3&"'!$2:$2"), 0)), _xlpm.RT, INDEX(INDIRECT("'"&A$3&"'!$1:$1048576"), ROW(), MATCH("REGOLA TECNICA", INDIRECT("'"&A$3&"'!$2:$2"), 0)), IF(AND(OR(_xlpm.CC="S", _xlpm.CDSM="S"), OR(_xlpm.RT="NA", _xlpm.RT="")), "❌", IF(AND(_xlpm.CC="N", _xlpm.CDSM="N", _xlpm.RT<>"NA"), "❌", IF(AND(_xlpm.CC="N", _xlpm.CDSM="N"), "✅", IF(AND(OR(_xlpm.CC="S", _xlpm.CDSM="S"), _xlpm.RT<>"NA"), "✅", "⚠️")))) )} -> #N/A | E14: {=_xlfn.LET( _xlpm.CC, INDEX(INDIRECT("'"&A$3&"'!$1:$1048576"), ROW(), MATCH("FORMATO", INDIRECT("'"&A$3&"'!$2:$2"), 0)), IF(_xlpm.CC="NUMBER", "✅", IF(_xlpm.CC="DATE", "✅", IF(_xlpm.CC="VARCHAR", "✅", IF(_xlpm.CC="TIMESTAMP", "✅", "❌")))) )} -> #N/A
A15: 14 | B15: {=_xlfn.LET( _xlpm.AA, INDEX(INDIRECT("'"&A$3&"'!$1:$1048576"), ROW(), MATCH("FLAG_PK", INDIRECT("'"&A$3&"'!$2:$2"), 0)), _xlpm.BB, INDEX(INDIRECT("'"&A$3&"'!$1:$1048576"), ROW(), MATCH("FORMATO", INDIRECT("'"&A$3&"'!$2:$2"), 0)), _xlpm.CC, INDEX(INDIRECT("'"&A$3&"'!$1:$1048576"), ROW(), MATCH("LENGTH", INDIRECT("'"&A$3&"'!$2:$2"), 0)), _xlpm.DD, INDEX(INDIRECT("'"&A$3&"'!$1:$1048576"), ROW(), MATCH("DECIMAL", INDIRECT("'"&A$3&"'!$2:$2"), 0)), _xlpm.FF, INDEX(INDIRECT("'"&A$3&"'!$1:$1048576"), ROW(), MATCH("CAMPO CALCOLATO", INDIRECT("'"&A$3&"'!$2:$2"), 0)), _xlpm.GG, INDEX(INDIRECT("'"&A$3&"'!$1:$1048576"), ROW(), MATCH("CAMPO DA SORGENTE NON MAIN", INDIRECT("'"&A$3&"'!$2:$2"), 0)), _xlpm.HH, INDEX(INDIRECT("'"&A$3&"'!$1:$1048576"), ROW(), MATCH("REGOLA TECNICA", INDIRECT("'"&A$3&"'!$2:$2"), 0)), _xlpm.II, INDEX(INDIRECT("'"&A$3&"'!$1:$1048576"), ROW(), MATCH("CHIAVI DI AGGANCIO", INDIRECT("'"&A$3&"'!$2:$2"), 0)), _xlpm.LL, INDEX(INDIRECT("'"&A$3&"'!$1:$1048576"), ROW(), MATCH("DATI SENSIBILI", INDIRECT("'"&A$3&"'!$2:$2"), 0)), IF(_xlpm.AA="","❌ (FLAG_PK)", IF(_xlpm.BB="","❌ (FORMATO)", IF(_xlpm.CC="","❌ (LENGTH)", IF(_xlpm.DD="","❌ (DECIMAL)", IF(_xlpm.FF="","❌ (CAMPO CALCOLATO)", IF(_xlpm.GG="","❌ (CAMPO DA SORGENTE NON MAIN)", IF(_xlpm.HH="","❌ (REGOLA TECNICA)", IF(_xlpm.II="","❌ (CHIAVI DI AGGANCIO)", IF(_xlpm.LL="","❌ (DATI SENSIBILI)", "✅"))))))))) )} -> #N/A | C15: {=IF( INDEX(INDIRECT("'"&A$3&"'!$1:$1048576"), ROW(), MATCH("CAMPO DA SORGENTE NON MAIN", INDIRECT("'"&A$3&"'!$2:$2"), 0))="S", IF(INDEX(INDIRECT("'"&A$3&"'!$1:$1048576"), ROW(), MATCH("CHIAVI DI AGGANCIO", INDIRECT("'"&A$3&"'!$2:$2"), 0))="NA", "❌", "✅"), IF( INDEX(INDIRECT("'"&A$3&"'!$1:$1048576"), ROW(), MATCH("CAMPO DA SORGENTE NON MAIN", INDIRECT("'"&A$3&"'!$2:$2"), 0))="N", IF(INDEX(INDIRECT("'"&A$3&"'!$1:$1048576"), ROW(), MATCH("CHIAVI DI AGGANCIO", INDIRECT("'"&A$3&"'!$2:$2"), 0))<>"NA", "❌", "✅"), "⚠️" ) )} -> #N/A | D15: {=_xlfn.LET( _xlpm.CC, INDEX(INDIRECT("'"&A$3&"'!$1:$1048576"), ROW(), MATCH("CAMPO CALCOLATO", INDIRECT("'"&A$3&"'!$2:$2"), 0)), _xlpm.CDSM, INDEX(INDIRECT("'"&A$3&"'!$1:$1048576"), ROW(), MATCH("CAMPO DA SORGENTE NON MAIN", INDIRECT("'"&A$3&"'!$2:$2"), 0)), _xlpm.RT, INDEX(INDIRECT("'"&A$3&"'!$1:$1048576"), ROW(), MATCH("REGOLA TECNICA", INDIRECT("'"&A$3&"'!$2:$2"), 0)), IF(AND(OR(_xlpm.CC="S", _xlpm.CDSM="S"), OR(_xlpm.RT="NA", _xlpm.RT="")), "❌", IF(AND(_xlpm.CC="N", _xlpm.CDSM="N", _xlpm.RT<>"NA"), "❌", IF(AND(_xlpm.CC="N", _xlpm.CDSM="N"), "✅", IF(AND(OR(_xlpm.CC="S", _xlpm.CDSM="S"), _xlpm.RT<>"NA"), "✅", "⚠️")))) )} -> #N/A | E15: {=_xlfn.LET( _xlpm.CC, INDEX(INDIRECT("'"&A$3&"'!$1:$1048576"), ROW(), MATCH("FORMATO", INDIRECT("'"&A$3&"'!$2:$2"), 0)), IF(_xlpm.CC="NUMBER", "✅", IF(_xlpm.CC="DATE", "✅", IF(_xlpm.CC="VARCHAR", "✅", IF(_xlpm.CC="TIMESTAMP", "✅", "❌")))) )} -> #N/A
A16: 15 | B16: {=_xlfn.LET( _xlpm.AA, INDEX(INDIRECT("'"&A$3&"'!$1:$1048576"), ROW(), MATCH("FLAG_PK", INDIRECT("'"&A$3&"'!$2:$2"), 0)), _xlpm.BB, INDEX(INDIRECT("'"&A$3&"'!$1:$1048576"), ROW(), MATCH("FORMATO", INDIRECT("'"&A$3&"'!$2:$2"), 0)), _xlpm.CC, INDEX(INDIRECT("'"&A$3&"'!$1:$1048576"), ROW(), MATCH("LENGTH", INDIRECT("'"&A$3&"'!$2:$2"), 0)), _xlpm.DD, INDEX(INDIRECT("'"&A$3&"'!$1:$1048576"), ROW(), MATCH("DECIMAL", INDIRECT("'"&A$3&"'!$2:$2"), 0)), _xlpm.FF, INDEX(INDIRECT("'"&A$3&"'!$1:$1048576"), ROW(), MATCH("CAMPO CALCOLATO", INDIRECT("'"&A$3&"'!$2:$2"), 0)), _xlpm.GG, INDEX(INDIRECT("'"&A$3&"'!$1:$1048576"), ROW(), MATCH("CAMPO DA SORGENTE NON MAIN", INDIRECT("'"&A$3&"'!$2:$2"), 0)), _xlpm.HH, INDEX(INDIRECT("'"&A$3&"'!$1:$1048576"), ROW(), MATCH("REGOLA TECNICA", INDIRECT("'"&A$3&"'!$2:$2"), 0)), _xlpm.II, INDEX(INDIRECT("'"&A$3&"'!$1:$1048576"), ROW(), MATCH("CHIAVI DI AGGANCIO", INDIRECT("'"&A$3&"'!$2:$2"), 0)), _xlpm.LL, INDEX(INDIRECT("'"&A$3&"'!$1:$1048576"), ROW(), MATCH("DATI SENSIBILI", INDIRECT("'"&A$3&"'!$2:$2"), 0)), IF(_xlpm.AA="","❌ (FLAG_PK)", IF(_xlpm.BB="","❌ (FORMATO)", IF(_xlpm.CC="","❌ (LENGTH)", IF(_xlpm.DD="","❌ (DECIMAL)", IF(_xlpm.FF="","❌ (CAMPO CALCOLATO)", IF(_xlpm.GG="","❌ (CAMPO DA SORGENTE NON MAIN)", IF(_xlpm.HH="","❌ (REGOLA TECNICA)", IF(_xlpm.II="","❌ (CHIAVI DI AGGANCIO)", IF(_xlpm.LL="","❌ (DATI SENSIBILI)", "✅"))))))))) )} -> #N/A | C16: {=IF( INDEX(INDIRECT("'"&A$3&"'!$1:$1048576"), ROW(), MATCH("CAMPO DA SORGENTE NON MAIN", INDIRECT("'"&A$3&"'!$2:$2"), 0))="S", IF(INDEX(INDIRECT("'"&A$3&"'!$1:$1048576"), ROW(), MATCH("CHIAVI DI AGGANCIO", INDIRECT("'"&A$3&"'!$2:$2"), 0))="NA", "❌", "✅"), IF( INDEX(INDIRECT("'"&A$3&"'!$1:$1048576"), ROW(), MATCH("CAMPO DA SORGENTE NON MAIN", INDIRECT("'"&A$3&"'!$2:$2"), 0))="N", IF(INDEX(INDIRECT("'"&A$3&"'!$1:$1048576"), ROW(), MATCH("CHIAVI DI AGGANCIO", INDIRECT("'"&A$3&"'!$2:$2"), 0))<>"NA", "❌", "✅"), "⚠️" ) )} -> #N/A | D16: {=_xlfn.LET( _xlpm.CC, INDEX(INDIRECT("'"&A$3&"'!$1:$1048576"), ROW(), MATCH("CAMPO CALCOLATO", INDIRECT("'"&A$3&"'!$2:$2"), 0)), _xlpm.CDSM, INDEX(INDIRECT("'"&A$3&"'!$1:$1048576"), ROW(), MATCH("CAMPO DA SORGENTE NON MAIN", INDIRECT("'"&A$3&"'!$2:$2"), 0)), _xlpm.RT, INDEX(INDIRECT("'"&A$3&"'!$1:$1048576"), ROW(), MATCH("REGOLA TECNICA", INDIRECT("'"&A$3&"'!$2:$2"), 0)), IF(AND(OR(_xlpm.CC="S", _xlpm.CDSM="S"), OR(_xlpm.RT="NA", _xlpm.RT="")), "❌", IF(AND(_xlpm.CC="N", _xlpm.CDSM="N", _xlpm.RT<>"NA"), "❌", IF(AND(_xlpm.CC="N", _xlpm.CDSM="N"), "✅", IF(AND(OR(_xlpm.CC="S", _xlpm.CDSM="S"), _xlpm.RT<>"NA"), "✅", "⚠️")))) )} -> #N/A | E16: {=_xlfn.LET( _xlpm.CC, INDEX(INDIRECT("'"&A$3&"'!$1:$1048576"), ROW(), MATCH("FORMATO", INDIRECT("'"&A$3&"'!$2:$2"), 0)), IF(_xlpm.CC="NUMBER", "✅", IF(_xlpm.CC="DATE", "✅", IF(_xlpm.CC="VARCHAR", "✅", IF(_xlpm.CC="TIMESTAMP", "✅", "❌")))) )} -> #N/A
... A109: 108 | B109: {=_xlfn.LET( _xlpm.AA, INDEX(INDIRECT("'"&A$3&"'!$1:$1048576"), ROW(), MATCH("FLAG_PK", INDIRECT("'"&A$3&"'!$2:$2"), 0)), _xlpm.BB, INDEX(INDIRECT("'"&A$3&"'!$1:$1048576"), ROW(), MATCH("FORMATO", INDIRECT("'"&A$3&"'!$2:$2"), 0)), _xlpm.CC, INDEX(INDIRECT("'"&A$3&"'!$1:$1048576"), ROW(), MATCH("LENGTH", INDIRECT("'"&A$3&"'!$2:$2"), 0)), _xlpm.DD, INDEX(INDIRECT("'"&A$3&"'!$1:$1048576"), ROW(), MATCH("DECIMAL", INDIRECT("'"&A$3&"'!$2:$2"), 0)), _xlpm.FF, INDEX(INDIRECT("'"&A$3&"'!$1:$1048576"), ROW(), MATCH("CAMPO CALCOLATO", INDIRECT("'"&A$3&"'!$2:$2"), 0)), _xlpm.GG, INDEX(INDIRECT("'"&A$3&"'!$1:$1048576"), ROW(), MATCH("CAMPO DA SORGENTE NON MAIN", INDIRECT("'"&A$3&"'!$2:$2"), 0)), _xlpm.HH, INDEX(INDIRECT("'"&A$3&"'!$1:$1048576"), ROW(), MATCH("REGOLA TECNICA", INDIRECT("'"&A$3&"'!$2:$2"), 0)), _xlpm.II, INDEX(INDIRECT("'"&A$3&"'!$1:$1048576"), ROW(), MATCH("CHIAVI DI AGGANCIO", INDIRECT("'"&A$3&"'!$2:$2"), 0)), _xlpm.LL, INDEX(INDIRECT("'"&A$3&"'!$1:$1048576"), ROW(), MATCH("DATI SENSIBILI", INDIRECT("'"&A$3&"'!$2:$2"), 0)), IF(_xlpm.AA="","❌ (FLAG_PK)", IF(_xlpm.BB="","❌ (FORMATO)", IF(_xlpm.CC="","❌ (LENGTH)", IF(_xlpm.DD="","❌ (DECIMAL)", IF(_xlpm.FF="","❌ (CAMPO CALCOLATO)", IF(_xlpm.GG="","❌ (CAMPO DA SORGENTE NON MAIN)", IF(_xlpm.HH="","❌ (REGOLA TECNICA)", IF(_xlpm.II="","❌ (CHIAVI DI AGGANCIO)", IF(_xlpm.LL="","❌ (DATI SENSIBILI)", "✅"))))))))) )} -> #N/A | C109: {=IF( INDEX(INDIRECT("'"&A$3&"'!$1:$1048576"), ROW(), MATCH("CAMPO DA SORGENTE NON MAIN", INDIRECT("'"&A$3&"'!$2:$2"), 0))="S", IF(INDEX(INDIRECT("'"&A$3&"'!$1:$1048576"), ROW(), MATCH("CHIAVI DI AGGANCIO", INDIRECT("'"&A$3&"'!$2:$2"), 0))="NA", "❌", "✅"), IF( INDEX(INDIRECT("'"&A$3&"'!$1:$1048576"), ROW(), MATCH("CAMPO DA SORGENTE NON MAIN", INDIRECT("'"&A$3&"'!$2:$2"), 0))="N", IF(INDEX(INDIRECT("'"&A$3&"'!$1:$1048576"), ROW(), MATCH("CHIAVI DI AGGANCIO", INDIRECT("'"&A$3&"'!$2:$2"), 0))<>"NA", "❌", "✅"), "⚠️" ) )} -> #N/A | D109: {=_xlfn.LET( _xlpm.CC, INDEX(INDIRECT("'"&A$3&"'!$1:$1048576"), ROW(), MATCH("CAMPO CALCOLATO", INDIRECT("'"&A$3&"'!$2:$2"), 0)), _xlpm.CDSM, INDEX(INDIRECT("'"&A$3&"'!$1:$1048576"), ROW(), MATCH("CAMPO DA SORGENTE NON MAIN", INDIRECT("'"&A$3&"'!$2:$2"), 0)), _xlpm.RT, INDEX(INDIRECT("'"&A$3&"'!$1:$1048576"), ROW(), MATCH("REGOLA TECNICA", INDIRECT("'"&A$3&"'!$2:$2"), 0)), IF(AND(OR(_xlpm.CC="S", _xlpm.CDSM="S"), OR(_xlpm.RT="NA", _xlpm.RT="")), "❌", IF(AND(_xlpm.CC="N", _xlpm.CDSM="N", _xlpm.RT<>"NA"), "❌", IF(AND(_xlpm.CC="N", _xlpm.CDSM="N"), "✅", IF(AND(OR(_xlpm.CC="S", _xlpm.CDSM="S"), _xlpm.RT<>"NA"), "✅", "⚠️")))) )} -> #N/A | E109: {=_xlfn.LET( _xlpm.CC, INDEX(INDIRECT("'"&A$3&"'!$1:$1048576"), ROW(), MATCH("FORMATO", INDIRECT("'"&A$3&"'!$2:$2"), 0)), IF(_xlpm.CC="NUMBER", "✅", IF(_xlpm.CC="DATE", "✅", IF(_xlpm.CC="VARCHAR", "✅", IF(_xlpm.CC="TIMESTAMP", "✅", "❌")))) )} -> #N/A
B110: {=_xlfn.LET( _xlpm.AA, INDEX(INDIRECT("'"&A$3&"'!$1:$1048576"), ROW(), MATCH("FLAG_PK", INDIRECT("'"&A$3&"'!$2:$2"), 0)), _xlpm.BB, INDEX(INDIRECT("'"&A$3&"'!$1:$1048576"), ROW(), MATCH("FORMATO", INDIRECT("'"&A$3&"'!$2:$2"), 0)), _xlpm.CC, INDEX(INDIRECT("'"&A$3&"'!$1:$1048576"), ROW(), MATCH("LENGTH", INDIRECT("'"&A$3&"'!$2:$2"), 0)), _xlpm.DD, INDEX(INDIRECT("'"&A$3&"'!$1:$1048576"), ROW(), MATCH("DECIMAL", INDIRECT("'"&A$3&"'!$2:$2"), 0)), _xlpm.FF, INDEX(INDIRECT("'"&A$3&"'!$1:$1048576"), ROW(), MATCH("CAMPO CALCOLATO", INDIRECT("'"&A$3&"'!$2:$2"), 0)), _xlpm.GG, INDEX(INDIRECT("'"&A$3&"'!$1:$1048576"), ROW(), MATCH("CAMPO DA SORGENTE NON MAIN", INDIRECT("'"&A$3&"'!$2:$2"), 0)), _xlpm.HH, INDEX(INDIRECT("'"&A$3&"'!$1:$1048576"), ROW(), MATCH("REGOLA TECNICA", INDIRECT("'"&A$3&"'!$2:$2"), 0)), _xlpm.II, INDEX(INDIRECT("'"&A$3&"'!$1:$1048576"), ROW(), MATCH("CHIAVI DI AGGANCIO", INDIRECT("'"&A$3&"'!$2:$2"), 0)), _xlpm.LL, INDEX(INDIRECT("'"&A$3&"'!$1:$1048576"), ROW(), MATCH("DATI SENSIBILI", INDIRECT("'"&A$3&"'!$2:$2"), 0)), IF(_xlpm.AA="","❌ (FLAG_PK)", IF(_xlpm.BB="","❌ (FORMATO)", IF(_xlpm.CC="","❌ (LENGTH)", IF(_xlpm.DD="","❌ (DECIMAL)", IF(_xlpm.FF="","❌ (CAMPO CALCOLATO)", IF(_xlpm.GG="","❌ (CAMPO DA SORGENTE NON MAIN)", IF(_xlpm.HH="","❌ (REGOLA TECNICA)", IF(_xlpm.II="","❌ (CHIAVI DI AGGANCIO)", IF(_xlpm.LL="","❌ (DATI SENSIBILI)", "✅"))))))))) )} -> #N/A | C110: {=IF( INDEX(INDIRECT("'"&A$3&"'!$1:$1048576"), ROW(), MATCH("CAMPO DA SORGENTE NON MAIN", INDIRECT("'"&A$3&"'!$2:$2"), 0))="S", IF(INDEX(INDIRECT("'"&A$3&"'!$1:$1048576"), ROW(), MATCH("CHIAVI DI AGGANCIO", INDIRECT("'"&A$3&"'!$2:$2"), 0))="NA", "❌", "✅"), IF( INDEX(INDIRECT("'"&A$3&"'!$1:$1048576"), ROW(), MATCH("CAMPO DA SORGENTE NON MAIN", INDIRECT("'"&A$3&"'!$2:$2"), 0))="N", IF(INDEX(INDIRECT("'"&A$3&"'!$1:$1048576"), ROW(), MATCH("CHIAVI DI AGGANCIO", INDIRECT("'"&A$3&"'!$2:$2"), 0))<>"NA", "❌", "✅"), "⚠️" ) )} -> #N/A | D110: {=_xlfn.LET( _xlpm.CC, INDEX(INDIRECT("'"&A$3&"'!$1:$1048576"), ROW(), MATCH("CAMPO CALCOLATO", INDIRECT("'"&A$3&"'!$2:$2"), 0)), _xlpm.CDSM, INDEX(INDIRECT("'"&A$3&"'!$1:$1048576"), ROW(), MATCH("CAMPO DA SORGENTE NON MAIN", INDIRECT("'"&A$3&"'!$2:$2"), 0)), _xlpm.RT, INDEX(INDIRECT("'"&A$3&"'!$1:$1048576"), ROW(), MATCH("REGOLA TECNICA", INDIRECT("'"&A$3&"'!$2:$2"), 0)), IF(AND(OR(_xlpm.CC="S", _xlpm.CDSM="S"), OR(_xlpm.RT="NA", _xlpm.RT="")), "❌", IF(AND(_xlpm.CC="N", _xlpm.CDSM="N", _xlpm.RT<>"NA"), "❌", IF(AND(_xlpm.CC="N", _xlpm.CDSM="N"), "✅", IF(AND(OR(_xlpm.CC="S", _xlpm.CDSM="S"), _xlpm.RT<>"NA"), "✅", "⚠️")))) )} -> #N/A | E110: {=_xlfn.LET( _xlpm.CC, INDEX(INDIRECT("'"&A$3&"'!$1:$1048576"), ROW(), MATCH("FORMATO", INDIRECT("'"&A$3&"'!$2:$2"), 0)), IF(_xlpm.CC="NUMBER", "✅", IF(_xlpm.CC="DATE", "✅", IF(_xlpm.CC="VARCHAR", "✅", IF(_xlpm.CC="TIMESTAMP", "✅", "❌")))) )} -> #N/A
B111: {=_xlfn.LET( _xlpm.AA, INDEX(INDIRECT("'"&A$3&"'!$1:$1048576"), ROW(), MATCH("FLAG_PK", INDIRECT("'"&A$3&"'!$2:$2"), 0)), _xlpm.BB, INDEX(INDIRECT("'"&A$3&"'!$1:$1048576"), ROW(), MATCH("FORMATO", INDIRECT("'"&A$3&"'!$2:$2"), 0)), _xlpm.CC, INDEX(INDIRECT("'"&A$3&"'!$1:$1048576"), ROW(), MATCH("LENGTH", INDIRECT("'"&A$3&"'!$2:$2"), 0)), _xlpm.DD, INDEX(INDIRECT("'"&A$3&"'!$1:$1048576"), ROW(), MATCH("DECIMAL", INDIRECT("'"&A$3&"'!$2:$2"), 0)), _xlpm.FF, INDEX(INDIRECT("'"&A$3&"'!$1:$1048576"), ROW(), MATCH("CAMPO CALCOLATO", INDIRECT("'"&A$3&"'!$2:$2"), 0)), _xlpm.GG, INDEX(INDIRECT("'"&A$3&"'!$1:$1048576"), ROW(), MATCH("CAMPO DA SORGENTE NON MAIN", INDIRECT("'"&A$3&"'!$2:$2"), 0)), _xlpm.HH, INDEX(INDIRECT("'"&A$3&"'!$1:$1048576"), ROW(), MATCH("REGOLA TECNICA", INDIRECT("'"&A$3&"'!$2:$2"), 0)), _xlpm.II, INDEX(INDIRECT("'"&A$3&"'!$1:$1048576"), ROW(), MATCH("CHIAVI DI AGGANCIO", INDIRECT("'"&A$3&"'!$2:$2"), 0)), _xlpm.LL, INDEX(INDIRECT("'"&A$3&"'!$1:$1048576"), ROW(), MATCH("DATI SENSIBILI", INDIRECT("'"&A$3&"'!$2:$2"), 0)), IF(_xlpm.AA="","❌ (FLAG_PK)", IF(_xlpm.BB="","❌ (FORMATO)", IF(_xlpm.CC="","❌ (LENGTH)", IF(_xlpm.DD="","❌ (DECIMAL)", IF(_xlpm.FF="","❌ (CAMPO CALCOLATO)", IF(_xlpm.GG="","❌ (CAMPO DA SORGENTE NON MAIN)", IF(_xlpm.HH="","❌ (REGOLA TECNICA)", IF(_xlpm.II="","❌ (CHIAVI DI AGGANCIO)", IF(_xlpm.LL="","❌ (DATI SENSIBILI)", "✅"))))))))) )} -> #N/A | C111: {=IF( INDEX(INDIRECT("'"&A$3&"'!$1:$1048576"), ROW(), MATCH("CAMPO DA SORGENTE NON MAIN", INDIRECT("'"&A$3&"'!$2:$2"), 0))="S", IF(INDEX(INDIRECT("'"&A$3&"'!$1:$1048576"), ROW(), MATCH("CHIAVI DI AGGANCIO", INDIRECT("'"&A$3&"'!$2:$2"), 0))="NA", "❌", "✅"), IF( INDEX(INDIRECT("'"&A$3&"'!$1:$1048576"), ROW(), MATCH("CAMPO DA SORGENTE NON MAIN", INDIRECT("'"&A$3&"'!$2:$2"), 0))="N", IF(INDEX(INDIRECT("'"&A$3&"'!$1:$1048576"), ROW(), MATCH("CHIAVI DI AGGANCIO", INDIRECT("'"&A$3&"'!$2:$2"), 0))<>"NA", "❌", "✅"), "⚠️" ) )} -> #N/A | D111: {=_xlfn.LET( _xlpm.CC, INDEX(INDIRECT("'"&A$3&"'!$1:$1048576"), ROW(), MATCH("CAMPO CALCOLATO", INDIRECT("'"&A$3&"'!$2:$2"), 0)), _xlpm.CDSM, INDEX(INDIRECT("'"&A$3&"'!$1:$1048576"), ROW(), MATCH("CAMPO DA SORGENTE NON MAIN", INDIRECT("'"&A$3&"'!$2:$2"), 0)), _xlpm.RT, INDEX(INDIRECT("'"&A$3&"'!$1:$1048576"), ROW(), MATCH("REGOLA TECNICA", INDIRECT("'"&A$3&"'!$2:$2"), 0)), IF(AND(OR(_xlpm.CC="S", _xlpm.CDSM="S"), OR(_xlpm.RT="NA", _xlpm.RT="")), "❌", IF(AND(_xlpm.CC="N", _xlpm.CDSM="N", _xlpm.RT<>"NA"), "❌", IF(AND(_xlpm.CC="N", _xlpm.CDSM="N"), "✅", IF(AND(OR(_xlpm.CC="S", _xlpm.CDSM="S"), _xlpm.RT<>"NA"), "✅", "⚠️")))) )} -> #N/A | E111: {=_xlfn.LET( _xlpm.CC, INDEX(INDIRECT("'"&A$3&"'!$1:$1048576"), ROW(), MATCH("FORMATO", INDIRECT("'"&A$3&"'!$2:$2"), 0)), IF(_xlpm.CC="NUMBER", "✅", IF(_xlpm.CC="DATE", "✅", IF(_xlpm.CC="VARCHAR", "✅", IF(_xlpm.CC="TIMESTAMP", "✅", "❌")))) )} -> #N/A
B112: {=_xlfn.LET( _xlpm.AA, INDEX(INDIRECT("'"&A$3&"'!$1:$1048576"), ROW(), MATCH("FLAG_PK", INDIRECT("'"&A$3&"'!$2:$2"), 0)), _xlpm.BB, INDEX(INDIRECT("'"&A$3&"'!$1:$1048576"), ROW(), MATCH("FORMATO", INDIRECT("'"&A$3&"'!$2:$2"), 0)), _xlpm.CC, INDEX(INDIRECT("'"&A$3&"'!$1:$1048576"), ROW(), MATCH("LENGTH", INDIRECT("'"&A$3&"'!$2:$2"), 0)), _xlpm.DD, INDEX(INDIRECT("'"&A$3&"'!$1:$1048576"), ROW(), MATCH("DECIMAL", INDIRECT("'"&A$3&"'!$2:$2"), 0)), _xlpm.FF, INDEX(INDIRECT("'"&A$3&"'!$1:$1048576"), ROW(), MATCH("CAMPO CALCOLATO", INDIRECT("'"&A$3&"'!$2:$2"), 0)), _xlpm.GG, INDEX(INDIRECT("'"&A$3&"'!$1:$1048576"), ROW(), MATCH("CAMPO DA SORGENTE NON MAIN", INDIRECT("'"&A$3&"'!$2:$2"), 0)), _xlpm.HH, INDEX(INDIRECT("'"&A$3&"'!$1:$1048576"), ROW(), MATCH("REGOLA TECNICA", INDIRECT("'"&A$3&"'!$2:$2"), 0)), _xlpm.II, INDEX(INDIRECT("'"&A$3&"'!$1:$1048576"), ROW(), MATCH("CHIAVI DI AGGANCIO", INDIRECT("'"&A$3&"'!$2:$2"), 0)), _xlpm.LL, INDEX(INDIRECT("'"&A$3&"'!$1:$1048576"), ROW(), MATCH("DATI SENSIBILI", INDIRECT("'"&A$3&"'!$2:$2"), 0)), IF(_xlpm.AA="","❌ (FLAG_PK)", IF(_xlpm.BB="","❌ (FORMATO)", IF(_xlpm.CC="","❌ (LENGTH)", IF(_xlpm.DD="","❌ (DECIMAL)", IF(_xlpm.FF="","❌ (CAMPO CALCOLATO)", IF(_xlpm.GG="","❌ (CAMPO DA SORGENTE NON MAIN)", IF(_xlpm.HH="","❌ (REGOLA TECNICA)", IF(_xlpm.II="","❌ (CHIAVI DI AGGANCIO)", IF(_xlpm.LL="","❌ (DATI SENSIBILI)", "✅"))))))))) )} -> #N/A | C112: {=IF( INDEX(INDIRECT("'"&A$3&"'!$1:$1048576"), ROW(), MATCH("CAMPO DA SORGENTE NON MAIN", INDIRECT("'"&A$3&"'!$2:$2"), 0))="S", IF(INDEX(INDIRECT("'"&A$3&"'!$1:$1048576"), ROW(), MATCH("CHIAVI DI AGGANCIO", INDIRECT("'"&A$3&"'!$2:$2"), 0))="NA", "❌", "✅"), IF( INDEX(INDIRECT("'"&A$3&"'!$1:$1048576"), ROW(), MATCH("CAMPO DA SORGENTE NON MAIN", INDIRECT("'"&A$3&"'!$2:$2"), 0))="N", IF(INDEX(INDIRECT("'"&A$3&"'!$1:$1048576"), ROW(), MATCH("CHIAVI DI AGGANCIO", INDIRECT("'"&A$3&"'!$2:$2"), 0))<>"NA", "❌", "✅"), "⚠️" ) )} -> #N/A | D112: {=_xlfn.LET( _xlpm.CC, INDEX(INDIRECT("'"&A$3&"'!$1:$1048576"), ROW(), MATCH("CAMPO CALCOLATO", INDIRECT("'"&A$3&"'!$2:$2"), 0)), _xlpm.CDSM, INDEX(INDIRECT("'"&A$3&"'!$1:$1048576"), ROW(), MATCH("CAMPO DA SORGENTE NON MAIN", INDIRECT("'"&A$3&"'!$2:$2"), 0)), _xlpm.RT, INDEX(INDIRECT("'"&A$3&"'!$1:$1048576"), ROW(), MATCH("REGOLA TECNICA", INDIRECT("'"&A$3&"'!$2:$2"), 0)), IF(AND(OR(_xlpm.CC="S", _xlpm.CDSM="S"), OR(_xlpm.RT="NA", _xlpm.RT="")), "❌", IF(AND(_xlpm.CC="N", _xlpm.CDSM="N", _xlpm.RT<>"NA"), "❌", IF(AND(_xlpm.CC="N", _xlpm.CDSM="N"), "✅", IF(AND(OR(_xlpm.CC="S", _xlpm.CDSM="S"), _xlpm.RT<>"NA"), "✅", "⚠️")))) )} -> #N/A | E112: {=_xlfn.LET( _xlpm.CC, INDEX(INDIRECT("'"&A$3&"'!$1:$1048576"), ROW(), MATCH("FORMATO", INDIRECT("'"&A$3&"'!$2:$2"), 0)), IF(_xlpm.CC="NUMBER", "✅", IF(_xlpm.CC="DATE", "✅", IF(_xlpm.CC="VARCHAR", "✅", IF(_xlpm.CC="TIMESTAMP", "✅", "❌")))) )} -> #N/A
B113: {=_xlfn.LET( _xlpm.AA, INDEX(INDIRECT("'"&A$3&"'!$1:$1048576"), ROW(), MATCH("FLAG_PK", INDIRECT("'"&A$3&"'!$2:$2"), 0)), _xlpm.BB, INDEX(INDIRECT("'"&A$3&"'!$1:$1048576"), ROW(), MATCH("FORMATO", INDIRECT("'"&A$3&"'!$2:$2"), 0)), _xlpm.CC, INDEX(INDIRECT("'"&A$3&"'!$1:$1048576"), ROW(), MATCH("LENGTH", INDIRECT("'"&A$3&"'!$2:$2"), 0)), _xlpm.DD, INDEX(INDIRECT("'"&A$3&"'!$1:$1048576"), ROW(), MATCH("DECIMAL", INDIRECT("'"&A$3&"'!$2:$2"), 0)), _xlpm.FF, INDEX(INDIRECT("'"&A$3&"'!$1:$1048576"), ROW(), MATCH("CAMPO CALCOLATO", INDIRECT("'"&A$3&"'!$2:$2"), 0)), _xlpm.GG, INDEX(INDIRECT("'"&A$3&"'!$1:$1048576"), ROW(), MATCH("CAMPO DA SORGENTE NON MAIN", INDIRECT("'"&A$3&"'!$2:$2"), 0)), _xlpm.HH, INDEX(INDIRECT("'"&A$3&"'!$1:$1048576"), ROW(), MATCH("REGOLA TECNICA", INDIRECT("'"&A$3&"'!$2:$2"), 0)), _xlpm.II, INDEX(INDIRECT("'"&A$3&"'!$1:$1048576"), ROW(), MATCH("CHIAVI DI AGGANCIO", INDIRECT("'"&A$3&"'!$2:$2"), 0)), _xlpm.LL, INDEX(INDIRECT("'"&A$3&"'!$1:$1048576"), ROW(), MATCH("DATI SENSIBILI", INDIRECT("'"&A$3&"'!$2:$2"), 0)), IF(_xlpm.AA="","❌ (FLAG_PK)", IF(_xlpm.BB="","❌ (FORMATO)", IF(_xlpm.CC="","❌ (LENGTH)", IF(_xlpm.DD="","❌ (DECIMAL)", IF(_xlpm.FF="","❌ (CAMPO CALCOLATO)", IF(_xlpm.GG="","❌ (CAMPO DA SORGENTE NON MAIN)", IF(_xlpm.HH="","❌ (REGOLA TECNICA)", IF(_xlpm.II="","❌ (CHIAVI DI AGGANCIO)", IF(_xlpm.LL="","❌ (DATI SENSIBILI)", "✅"))))))))) )} -> #N/A | C113: {=IF( INDEX(INDIRECT("'"&A$3&"'!$1:$1048576"), ROW(), MATCH("CAMPO DA SORGENTE NON MAIN", INDIRECT("'"&A$3&"'!$2:$2"), 0))="S", IF(INDEX(INDIRECT("'"&A$3&"'!$1:$1048576"), ROW(), MATCH("CHIAVI DI AGGANCIO", INDIRECT("'"&A$3&"'!$2:$2"), 0))="NA", "❌", "✅"), IF( INDEX(INDIRECT("'"&A$3&"'!$1:$1048576"), ROW(), MATCH("CAMPO DA SORGENTE NON MAIN", INDIRECT("'"&A$3&"'!$2:$2"), 0))="N", IF(INDEX(INDIRECT("'"&A$3&"'!$1:$1048576"), ROW(), MATCH("CHIAVI DI AGGANCIO", INDIRECT("'"&A$3&"'!$2:$2"), 0))<>"NA", "❌", "✅"), "⚠️" ) )} -> #N/A | D113: {=_xlfn.LET( _xlpm.CC, INDEX(INDIRECT("'"&A$3&"'!$1:$1048576"), ROW(), MATCH("CAMPO CALCOLATO", INDIRECT("'"&A$3&"'!$2:$2"), 0)), _xlpm.CDSM, INDEX(INDIRECT("'"&A$3&"'!$1:$1048576"), ROW(), MATCH("CAMPO DA SORGENTE NON MAIN", INDIRECT("'"&A$3&"'!$2:$2"), 0)), _xlpm.RT, INDEX(INDIRECT("'"&A$3&"'!$1:$1048576"), ROW(), MATCH("REGOLA TECNICA", INDIRECT("'"&A$3&"'!$2:$2"), 0)), IF(AND(OR(_xlpm.CC="S", _xlpm.CDSM="S"), OR(_xlpm.RT="NA", _xlpm.RT="")), "❌", IF(AND(_xlpm.CC="N", _xlpm.CDSM="N", _xlpm.RT<>"NA"), "❌", IF(AND(_xlpm.CC="N", _xlpm.CDSM="N"), "✅", IF(AND(OR(_xlpm.CC="S", _xlpm.CDSM="S"), _xlpm.RT<>"NA"), "✅", "⚠️")))) )} -> #N/A | E113: {=_xlfn.LET( _xlpm.CC, INDEX(INDIRECT("'"&A$3&"'!$1:$1048576"), ROW(), MATCH("FORMATO", INDIRECT("'"&A$3&"'!$2:$2"), 0)), IF(_xlpm.CC="NUMBER", "✅", IF(_xlpm.CC="DATE", "✅", IF(_xlpm.CC="VARCHAR", "✅", IF(_xlpm.CC="TIMESTAMP", "✅", "❌")))) )} -> #N/A
B114: {=_xlfn.LET( _xlpm.AA, INDEX(INDIRECT("'"&A$3&"'!$1:$1048576"), ROW(), MATCH("FLAG_PK", INDIRECT("'"&A$3&"'!$2:$2"), 0)), _xlpm.BB, INDEX(INDIRECT("'"&A$3&"'!$1:$1048576"), ROW(), MATCH("FORMATO", INDIRECT("'"&A$3&"'!$2:$2"), 0)), _xlpm.CC, INDEX(INDIRECT("'"&A$3&"'!$1:$1048576"), ROW(), MATCH("LENGTH", INDIRECT("'"&A$3&"'!$2:$2"), 0)), _xlpm.DD, INDEX(INDIRECT("'"&A$3&"'!$1:$1048576"), ROW(), MATCH("DECIMAL", INDIRECT("'"&A$3&"'!$2:$2"), 0)), _xlpm.FF, INDEX(INDIRECT("'"&A$3&"'!$1:$1048576"), ROW(), MATCH("CAMPO CALCOLATO", INDIRECT("'"&A$3&"'!$2:$2"), 0)), _xlpm.GG, INDEX(INDIRECT("'"&A$3&"'!$1:$1048576"), ROW(), MATCH("CAMPO DA SORGENTE NON MAIN", INDIRECT("'"&A$3&"'!$2:$2"), 0)), _xlpm.HH, INDEX(INDIRECT("'"&A$3&"'!$1:$1048576"), ROW(), MATCH("REGOLA TECNICA", INDIRECT("'"&A$3&"'!$2:$2"), 0)), _xlpm.II, INDEX(INDIRECT("'"&A$3&"'!$1:$1048576"), ROW(), MATCH("CHIAVI DI AGGANCIO", INDIRECT("'"&A$3&"'!$2:$2"), 0)), _xlpm.LL, INDEX(INDIRECT("'"&A$3&"'!$1:$1048576"), ROW(), MATCH("DATI SENSIBILI", INDIRECT("'"&A$3&"'!$2:$2"), 0)), IF(_xlpm.AA="","❌ (FLAG_PK)", IF(_xlpm.BB="","❌ (FORMATO)", IF(_xlpm.CC="","❌ (LENGTH)", IF(_xlpm.DD="","❌ (DECIMAL)", IF(_xlpm.FF="","❌ (CAMPO CALCOLATO)", IF(_xlpm.GG="","❌ (CAMPO DA SORGENTE NON MAIN)", IF(_xlpm.HH="","❌ (REGOLA TECNICA)", IF(_xlpm.II="","❌ (CHIAVI DI AGGANCIO)", IF(_xlpm.LL="","❌ (DATI SENSIBILI)", "✅"))))))))) )} -> #N/A | C114: {=IF( INDEX(INDIRECT("'"&A$3&"'!$1:$1048576"), ROW(), MATCH("CAMPO DA SORGENTE NON MAIN", INDIRECT("'"&A$3&"'!$2:$2"), 0))="S", IF(INDEX(INDIRECT("'"&A$3&"'!$1:$1048576"), ROW(), MATCH("CHIAVI DI AGGANCIO", INDIRECT("'"&A$3&"'!$2:$2"), 0))="NA", "❌", "✅"), IF( INDEX(INDIRECT("'"&A$3&"'!$1:$1048576"), ROW(), MATCH("CAMPO DA SORGENTE NON MAIN", INDIRECT("'"&A$3&"'!$2:$2"), 0))="N", IF(INDEX(INDIRECT("'"&A$3&"'!$1:$1048576"), ROW(), MATCH("CHIAVI DI AGGANCIO", INDIRECT("'"&A$3&"'!$2:$2"), 0))<>"NA", "❌", "✅"), "⚠️" ) )} -> #N/A | D114: {=_xlfn.LET( _xlpm.CC, INDEX(INDIRECT("'"&A$3&"'!$1:$1048576"), ROW(), MATCH("CAMPO CALCOLATO", INDIRECT("'"&A$3&"'!$2:$2"), 0)), _xlpm.CDSM, INDEX(INDIRECT("'"&A$3&"'!$1:$1048576"), ROW(), MATCH("CAMPO DA SORGENTE NON MAIN", INDIRECT("'"&A$3&"'!$2:$2"), 0)), _xlpm.RT, INDEX(INDIRECT("'"&A$3&"'!$1:$1048576"), ROW(), MATCH("REGOLA TECNICA", INDIRECT("'"&A$3&"'!$2:$2"), 0)), IF(AND(OR(_xlpm.CC="S", _xlpm.CDSM="S"), OR(_xlpm.RT="NA", _xlpm.RT="")), "❌", IF(AND(_xlpm.CC="N", _xlpm.CDSM="N", _xlpm.RT<>"NA"), "❌", IF(AND(_xlpm.CC="N", _xlpm.CDSM="N"), "✅", IF(AND(OR(_xlpm.CC="S", _xlpm.CDSM="S"), _xlpm.RT<>"NA"), "✅", "⚠️")))) )} -> #N/A | E114: {=_xlfn.LET( _xlpm.CC, INDEX(INDIRECT("'"&A$3&"'!$1:$1048576"), ROW(), MATCH("FORMATO", INDIRECT("'"&A$3&"'!$2:$2"), 0)), IF(_xlpm.CC="NUMBER", "✅", IF(_xlpm.CC="DATE", "✅", IF(_xlpm.CC="VARCHAR", "✅", IF(_xlpm.CC="TIMESTAMP", "✅", "❌")))) )} -> #N/A
B115: {=_xlfn.LET( _xlpm.AA, INDEX(INDIRECT("'"&A$3&"'!$1:$1048576"), ROW(), MATCH("FLAG_PK", INDIRECT("'"&A$3&"'!$2:$2"), 0)), _xlpm.BB, INDEX(INDIRECT("'"&A$3&"'!$1:$1048576"), ROW(), MATCH("FORMATO", INDIRECT("'"&A$3&"'!$2:$2"), 0)), _xlpm.CC, INDEX(INDIRECT("'"&A$3&"'!$1:$1048576"), ROW(), MATCH("LENGTH", INDIRECT("'"&A$3&"'!$2:$2"), 0)), _xlpm.DD, INDEX(INDIRECT("'"&A$3&"'!$1:$1048576"), ROW(), MATCH("DECIMAL", INDIRECT("'"&A$3&"'!$2:$2"), 0)), _xlpm.FF, INDEX(INDIRECT("'"&A$3&"'!$1:$1048576"), ROW(), MATCH("CAMPO CALCOLATO", INDIRECT("'"&A$3&"'!$2:$2"), 0)), _xlpm.GG, INDEX(INDIRECT("'"&A$3&"'!$1:$1048576"), ROW(), MATCH("CAMPO DA SORGENTE NON MAIN", INDIRECT("'"&A$3&"'!$2:$2"), 0)), _xlpm.HH, INDEX(INDIRECT("'"&A$3&"'!$1:$1048576"), ROW(), MATCH("REGOLA TECNICA", INDIRECT("'"&A$3&"'!$2:$2"), 0)), _xlpm.II, INDEX(INDIRECT("'"&A$3&"'!$1:$1048576"), ROW(), MATCH("CHIAVI DI AGGANCIO", INDIRECT("'"&A$3&"'!$2:$2"), 0)), _xlpm.LL, INDEX(INDIRECT("'"&A$3&"'!$1:$1048576"), ROW(), MATCH("DATI SENSIBILI", INDIRECT("'"&A$3&"'!$2:$2"), 0)), IF(_xlpm.AA="","❌ (FLAG_PK)", IF(_xlpm.BB="","❌ (FORMATO)", IF(_xlpm.CC="","❌ (LENGTH)", IF(_xlpm.DD="","❌ (DECIMAL)", IF(_xlpm.FF="","❌ (CAMPO CALCOLATO)", IF(_xlpm.GG="","❌ (CAMPO DA SORGENTE NON MAIN)", IF(_xlpm.HH="","❌ (REGOLA TECNICA)", IF(_xlpm.II="","❌ (CHIAVI DI AGGANCIO)", IF(_xlpm.LL="","❌ (DATI SENSIBILI)", "✅"))))))))) )} -> #N/A | C115: {=IF( INDEX(INDIRECT("'"&A$3&"'!$1:$1048576"), ROW(), MATCH("CAMPO DA SORGENTE NON MAIN", INDIRECT("'"&A$3&"'!$2:$2"), 0))="S", IF(INDEX(INDIRECT("'"&A$3&"'!$1:$1048576"), ROW(), MATCH("CHIAVI DI AGGANCIO", INDIRECT("'"&A$3&"'!$2:$2"), 0))="NA", "❌", "✅"), IF( INDEX(INDIRECT("'"&A$3&"'!$1:$1048576"), ROW(), MATCH("CAMPO DA SORGENTE NON MAIN", INDIRECT("'"&A$3&"'!$2:$2"), 0))="N", IF(INDEX(INDIRECT("'"&A$3&"'!$1:$1048576"), ROW(), MATCH("CHIAVI DI AGGANCIO", INDIRECT("'"&A$3&"'!$2:$2"), 0))<>"NA", "❌", "✅"), "⚠️" ) )} -> #N/A | D115: {=_xlfn.LET( _xlpm.CC, INDEX(INDIRECT("'"&A$3&"'!$1:$1048576"), ROW(), MATCH("CAMPO CALCOLATO", INDIRECT("'"&A$3&"'!$2:$2"), 0)), _xlpm.CDSM, INDEX(INDIRECT("'"&A$3&"'!$1:$1048576"), ROW(), MATCH("CAMPO DA SORGENTE NON MAIN", INDIRECT("'"&A$3&"'!$2:$2"), 0)), _xlpm.RT, INDEX(INDIRECT("'"&A$3&"'!$1:$1048576"), ROW(), MATCH("REGOLA TECNICA", INDIRECT("'"&A$3&"'!$2:$2"), 0)), IF(AND(OR(_xlpm.CC="S", _xlpm.CDSM="S"), OR(_xlpm.RT="NA", _xlpm.RT="")), "❌", IF(AND(_xlpm.CC="N", _xlpm.CDSM="N", _xlpm.RT<>"NA"), "❌", IF(AND(_xlpm.CC="N", _xlpm.CDSM="N"), "✅", IF(AND(OR(_xlpm.CC="S", _xlpm.CDSM="S"), _xlpm.RT<>"NA"), "✅", "⚠️")))) )} -> #N/A | E115: {=_xlfn.LET( _xlpm.CC, INDEX(INDIRECT("'"&A$3&"'!$1:$1048576"), ROW(), MATCH("FORMATO", INDIRECT("'"&A$3&"'!$2:$2"), 0)), IF(_xlpm.CC="NUMBER", "✅", IF(_xlpm.CC="DATE", "✅", IF(_xlpm.CC="VARCHAR", "✅", IF(_xlpm.CC="TIMESTAMP", "✅", "❌")))) )} -> #N/A
B116: {=_xlfn.LET( _xlpm.AA, INDEX(INDIRECT("'"&A$3&"'!$1:$1048576"), ROW(), MATCH("FLAG_PK", INDIRECT("'"&A$3&"'!$2:$2"), 0)), _xlpm.BB, INDEX(INDIRECT("'"&A$3&"'!$1:$1048576"), ROW(), MATCH("FORMATO", INDIRECT("'"&A$3&"'!$2:$2"), 0)), _xlpm.CC, INDEX(INDIRECT("'"&A$3&"'!$1:$1048576"), ROW(), MATCH("LENGTH", INDIRECT("'"&A$3&"'!$2:$2"), 0)), _xlpm.DD, INDEX(INDIRECT("'"&A$3&"'!$1:$1048576"), ROW(), MATCH("DECIMAL", INDIRECT("'"&A$3&"'!$2:$2"), 0)), _xlpm.FF, INDEX(INDIRECT("'"&A$3&"'!$1:$1048576"), ROW(), MATCH("CAMPO CALCOLATO", INDIRECT("'"&A$3&"'!$2:$2"), 0)), _xlpm.GG, INDEX(INDIRECT("'"&A$3&"'!$1:$1048576"), ROW(), MATCH("CAMPO DA SORGENTE NON MAIN", INDIRECT("'"&A$3&"'!$2:$2"), 0)), _xlpm.HH, INDEX(INDIRECT("'"&A$3&"'!$1:$1048576"), ROW(), MATCH("REGOLA TECNICA", INDIRECT("'"&A$3&"'!$2:$2"), 0)), _xlpm.II, INDEX(INDIRECT("'"&A$3&"'!$1:$1048576"), ROW(), MATCH("CHIAVI DI AGGANCIO", INDIRECT("'"&A$3&"'!$2:$2"), 0)), _xlpm.LL, INDEX(INDIRECT("'"&A$3&"'!$1:$1048576"), ROW(), MATCH("DATI SENSIBILI", INDIRECT("'"&A$3&"'!$2:$2"), 0)), IF(_xlpm.AA="","❌ (FLAG_PK)", IF(_xlpm.BB="","❌ (FORMATO)", IF(_xlpm.CC="","❌ (LENGTH)", IF(_xlpm.DD="","❌ (DECIMAL)", IF(_xlpm.FF="","❌ (CAMPO CALCOLATO)", IF(_xlpm.GG="","❌ (CAMPO DA SORGENTE NON MAIN)", IF(_xlpm.HH="","❌ (REGOLA TECNICA)", IF(_xlpm.II="","❌ (CHIAVI DI AGGANCIO)", IF(_xlpm.LL="","❌ (DATI SENSIBILI)", "✅"))))))))) )} -> #N/A | C116: {=IF( INDEX(INDIRECT("'"&A$3&"'!$1:$1048576"), ROW(), MATCH("CAMPO DA SORGENTE NON MAIN", INDIRECT("'"&A$3&"'!$2:$2"), 0))="S", IF(INDEX(INDIRECT("'"&A$3&"'!$1:$1048576"), ROW(), MATCH("CHIAVI DI AGGANCIO", INDIRECT("'"&A$3&"'!$2:$2"), 0))="NA", "❌", "✅"), IF( INDEX(INDIRECT("'"&A$3&"'!$1:$1048576"), ROW(), MATCH("CAMPO DA SORGENTE NON MAIN", INDIRECT("'"&A$3&"'!$2:$2"), 0))="N", IF(INDEX(INDIRECT("'"&A$3&"'!$1:$1048576"), ROW(), MATCH("CHIAVI DI AGGANCIO", INDIRECT("'"&A$3&"'!$2:$2"), 0))<>"NA", "❌", "✅"), "⚠️" ) )} -> #N/A | D116: {=_xlfn.LET( _xlpm.CC, INDEX(INDIRECT("'"&A$3&"'!$1:$1048576"), ROW(), MATCH("CAMPO CALCOLATO", INDIRECT("'"&A$3&"'!$2:$2"), 0)), _xlpm.CDSM, INDEX(INDIRECT("'"&A$3&"'!$1:$1048576"), ROW(), MATCH("CAMPO DA SORGENTE NON MAIN", INDIRECT("'"&A$3&"'!$2:$2"), 0)), _xlpm.RT, INDEX(INDIRECT("'"&A$3&"'!$1:$1048576"), ROW(), MATCH("REGOLA TECNICA", INDIRECT("'"&A$3&"'!$2:$2"), 0)), IF(AND(OR(_xlpm.CC="S", _xlpm.CDSM="S"), OR(_xlpm.RT="NA", _xlpm.RT="")), "❌", IF(AND(_xlpm.CC="N", _xlpm.CDSM="N", _xlpm.RT<>"NA"), "❌", IF(AND(_xlpm.CC="N", _xlpm.CDSM="N"), "✅", IF(AND(OR(_xlpm.CC="S", _xlpm.CDSM="S"), _xlpm.RT<>"NA"), "✅", "⚠️")))) )} -> #N/A | E116: {=_xlfn.LET( _xlpm.CC, INDEX(INDIRECT("'"&A$3&"'!$1:$1048576"), ROW(), MATCH("FORMATO", INDIRECT("'"&A$3&"'!$2:$2"), 0)), IF(_xlpm.CC="NUMBER", "✅", IF(_xlpm.CC="DATE", "✅", IF(_xlpm.CC="VARCHAR", "✅", IF(_xlpm.CC="TIMESTAMP", "✅", "❌")))) )} -> #N/A
B117: {=_xlfn.LET( _xlpm.AA, INDEX(INDIRECT("'"&A$3&"'!$1:$1048576"), ROW(), MATCH("FLAG_PK", INDIRECT("'"&A$3&"'!$2:$2"), 0)), _xlpm.BB, INDEX(INDIRECT("'"&A$3&"'!$1:$1048576"), ROW(), MATCH("FORMATO", INDIRECT("'"&A$3&"'!$2:$2"), 0)), _xlpm.CC, INDEX(INDIRECT("'"&A$3&"'!$1:$1048576"), ROW(), MATCH("LENGTH", INDIRECT("'"&A$3&"'!$2:$2"), 0)), _xlpm.DD, INDEX(INDIRECT("'"&A$3&"'!$1:$1048576"), ROW(), MATCH("DECIMAL", INDIRECT("'"&A$3&"'!$2:$2"), 0)), _xlpm.FF, INDEX(INDIRECT("'"&A$3&"'!$1:$1048576"), ROW(), MATCH("CAMPO CALCOLATO", INDIRECT("'"&A$3&"'!$2:$2"), 0)), _xlpm.GG, INDEX(INDIRECT("'"&A$3&"'!$1:$1048576"), ROW(), MATCH("CAMPO DA SORGENTE NON MAIN", INDIRECT("'"&A$3&"'!$2:$2"), 0)), _xlpm.HH, INDEX(INDIRECT("'"&A$3&"'!$1:$1048576"), ROW(), MATCH("REGOLA TECNICA", INDIRECT("'"&A$3&"'!$2:$2"), 0)), _xlpm.II, INDEX(INDIRECT("'"&A$3&"'!$1:$1048576"), ROW(), MATCH("CHIAVI DI AGGANCIO", INDIRECT("'"&A$3&"'!$2:$2"), 0)), _xlpm.LL, INDEX(INDIRECT("'"&A$3&"'!$1:$1048576"), ROW(), MATCH("DATI SENSIBILI", INDIRECT("'"&A$3&"'!$2:$2"), 0)), IF(_xlpm.AA="","❌ (FLAG_PK)", IF(_xlpm.BB="","❌ (FORMATO)", IF(_xlpm.CC="","❌ (LENGTH)", IF(_xlpm.DD="","❌ (DECIMAL)", IF(_xlpm.FF="","❌ (CAMPO CALCOLATO)", IF(_xlpm.GG="","❌ (CAMPO DA SORGENTE NON MAIN)", IF(_xlpm.HH="","❌ (REGOLA TECNICA)", IF(_xlpm.II="","❌ (CHIAVI DI AGGANCIO)", IF(_xlpm.LL="","❌ (DATI SENSIBILI)", "✅"))))))))) )} -> #N/A | C117: {=IF( INDEX(INDIRECT("'"&A$3&"'!$1:$1048576"), ROW(), MATCH("CAMPO DA SORGENTE NON MAIN", INDIRECT("'"&A$3&"'!$2:$2"), 0))="S", IF(INDEX(INDIRECT("'"&A$3&"'!$1:$1048576"), ROW(), MATCH("CHIAVI DI AGGANCIO", INDIRECT("'"&A$3&"'!$2:$2"), 0))="NA", "❌", "✅"), IF( INDEX(INDIRECT("'"&A$3&"'!$1:$1048576"), ROW(), MATCH("CAMPO DA SORGENTE NON MAIN", INDIRECT("'"&A$3&"'!$2:$2"), 0))="N", IF(INDEX(INDIRECT("'"&A$3&"'!$1:$1048576"), ROW(), MATCH("CHIAVI DI AGGANCIO", INDIRECT("'"&A$3&"'!$2:$2"), 0))<>"NA", "❌", "✅"), "⚠️" ) )} -> #N/A | D117: {=_xlfn.LET( _xlpm.CC, INDEX(INDIRECT("'"&A$3&"'!$1:$1048576"), ROW(), MATCH("CAMPO CALCOLATO", INDIRECT("'"&A$3&"'!$2:$2"), 0)), _xlpm.CDSM, INDEX(INDIRECT("'"&A$3&"'!$1:$1048576"), ROW(), MATCH("CAMPO DA SORGENTE NON MAIN", INDIRECT("'"&A$3&"'!$2:$2"), 0)), _xlpm.RT, INDEX(INDIRECT("'"&A$3&"'!$1:$1048576"), ROW(), MATCH("REGOLA TECNICA", INDIRECT("'"&A$3&"'!$2:$2"), 0)), IF(AND(OR(_xlpm.CC="S", _xlpm.CDSM="S"), OR(_xlpm.RT="NA", _xlpm.RT="")), "❌", IF(AND(_xlpm.CC="N", _xlpm.CDSM="N", _xlpm.RT<>"NA"), "❌", IF(AND(_xlpm.CC="N", _xlpm.CDSM="N"), "✅", IF(AND(OR(_xlpm.CC="S", _xlpm.CDSM="S"), _xlpm.RT<>"NA"), "✅", "⚠️")))) )} -> #N/A | E117: {=_xlfn.LET( _xlpm.CC, INDEX(INDIRECT("'"&A$3&"'!$1:$1048576"), ROW(), MATCH("FORMATO", INDIRECT("'"&A$3&"'!$2:$2"), 0)), IF(_xlpm.CC="NUMBER", "✅", IF(_xlpm.CC="DATE", "✅", IF(_xlpm.CC="VARCHAR", "✅", IF(_xlpm.CC="TIMESTAMP", "✅", "❌")))) )} -> #N/A
B118: {=_xlfn.LET( _xlpm.AA, INDEX(INDIRECT("'"&A$3&"'!$1:$1048576"), ROW(), MATCH("FLAG_PK", INDIRECT("'"&A$3&"'!$2:$2"), 0)), _xlpm.BB, INDEX(INDIRECT("'"&A$3&"'!$1:$1048576"), ROW(), MATCH("FORMATO", INDIRECT("'"&A$3&"'!$2:$2"), 0)), _xlpm.CC, INDEX(INDIRECT("'"&A$3&"'!$1:$1048576"), ROW(), MATCH("LENGTH", INDIRECT("'"&A$3&"'!$2:$2"), 0)), _xlpm.DD, INDEX(INDIRECT("'"&A$3&"'!$1:$1048576"), ROW(), MATCH("DECIMAL", INDIRECT("'"&A$3&"'!$2:$2"), 0)), _xlpm.FF, INDEX(INDIRECT("'"&A$3&"'!$1:$1048576"), ROW(), MATCH("CAMPO CALCOLATO", INDIRECT("'"&A$3&"'!$2:$2"), 0)), _xlpm.GG, INDEX(INDIRECT("'"&A$3&"'!$1:$1048576"), ROW(), MATCH("CAMPO DA SORGENTE NON MAIN", INDIRECT("'"&A$3&"'!$2:$2"), 0)), _xlpm.HH, INDEX(INDIRECT("'"&A$3&"'!$1:$1048576"), ROW(), MATCH("REGOLA TECNICA", INDIRECT("'"&A$3&"'!$2:$2"), 0)), _xlpm.II, INDEX(INDIRECT("'"&A$3&"'!$1:$1048576"), ROW(), MATCH("CHIAVI DI AGGANCIO", INDIRECT("'"&A$3&"'!$2:$2"), 0)), _xlpm.LL, INDEX(INDIRECT("'"&A$3&"'!$1:$1048576"), ROW(), MATCH("DATI SENSIBILI", INDIRECT("'"&A$3&"'!$2:$2"), 0)), IF(_xlpm.AA="","❌ (FLAG_PK)", IF(_xlpm.BB="","❌ (FORMATO)", IF(_xlpm.CC="","❌ (LENGTH)", IF(_xlpm.DD="","❌ (DECIMAL)", IF(_xlpm.FF="","❌ (CAMPO CALCOLATO)", IF(_xlpm.GG="","❌ (CAMPO DA SORGENTE NON MAIN)", IF(_xlpm.HH="","❌ (REGOLA TECNICA)", IF(_xlpm.II="","❌ (CHIAVI DI AGGANCIO)", IF(_xlpm.LL="","❌ (DATI SENSIBILI)", "✅"))))))))) )} -> #N/A | C118: {=IF( INDEX(INDIRECT("'"&A$3&"'!$1:$1048576"), ROW(), MATCH("CAMPO DA SORGENTE NON MAIN", INDIRECT("'"&A$3&"'!$2:$2"), 0))="S", IF(INDEX(INDIRECT("'"&A$3&"'!$1:$1048576"), ROW(), MATCH("CHIAVI DI AGGANCIO", INDIRECT("'"&A$3&"'!$2:$2"), 0))="NA", "❌", "✅"), IF( INDEX(INDIRECT("'"&A$3&"'!$1:$1048576"), ROW(), MATCH("CAMPO DA SORGENTE NON MAIN", INDIRECT("'"&A$3&"'!$2:$2"), 0))="N", IF(INDEX(INDIRECT("'"&A$3&"'!$1:$1048576"), ROW(), MATCH("CHIAVI DI AGGANCIO", INDIRECT("'"&A$3&"'!$2:$2"), 0))<>"NA", "❌", "✅"), "⚠️" ) )} -> #N/A | D118: {=_xlfn.LET( _xlpm.CC, INDEX(INDIRECT("'"&A$3&"'!$1:$1048576"), ROW(), MATCH("CAMPO CALCOLATO", INDIRECT("'"&A$3&"'!$2:$2"), 0)), _xlpm.CDSM, INDEX(INDIRECT("'"&A$3&"'!$1:$1048576"), ROW(), MATCH("CAMPO DA SORGENTE NON MAIN", INDIRECT("'"&A$3&"'!$2:$2"), 0)), _xlpm.RT, INDEX(INDIRECT("'"&A$3&"'!$1:$1048576"), ROW(), MATCH("REGOLA TECNICA", INDIRECT("'"&A$3&"'!$2:$2"), 0)), IF(AND(OR(_xlpm.CC="S", _xlpm.CDSM="S"), OR(_xlpm.RT="NA", _xlpm.RT="")), "❌", IF(AND(_xlpm.CC="N", _xlpm.CDSM="N", _xlpm.RT<>"NA"), "❌", IF(AND(_xlpm.CC="N", _xlpm.CDSM="N"), "✅", IF(AND(OR(_xlpm.CC="S", _xlpm.CDSM="S"), _xlpm.RT<>"NA"), "✅", "⚠️")))) )} -> #N/A | E118: {=_xlfn.LET( _xlpm.CC, INDEX(INDIRECT("'"&A$3&"'!$1:$1048576"), ROW(), MATCH("FORMATO", INDIRECT("'"&A$3&"'!$2:$2"), 0)), IF(_xlpm.CC="NUMBER", "✅", IF(_xlpm.CC="DATE", "✅", IF(_xlpm.CC="VARCHAR", "✅", IF(_xlpm.CC="TIMESTAMP", "✅", "❌")))) )} -> #N/A
B119: {=_xlfn.LET( _xlpm.AA, INDEX(INDIRECT("'"&A$3&"'!$1:$1048576"), ROW(), MATCH("FLAG_PK", INDIRECT("'"&A$3&"'!$2:$2"), 0)), _xlpm.BB, INDEX(INDIRECT("'"&A$3&"'!$1:$1048576"), ROW(), MATCH("FORMATO", INDIRECT("'"&A$3&"'!$2:$2"), 0)), _xlpm.CC, INDEX(INDIRECT("'"&A$3&"'!$1:$1048576"), ROW(), MATCH("LENGTH", INDIRECT("'"&A$3&"'!$2:$2"), 0)), _xlpm.DD, INDEX(INDIRECT("'"&A$3&"'!$1:$1048576"), ROW(), MATCH("DECIMAL", INDIRECT("'"&A$3&"'!$2:$2"), 0)), _xlpm.FF, INDEX(INDIRECT("'"&A$3&"'!$1:$1048576"), ROW(), MATCH("CAMPO CALCOLATO", INDIRECT("'"&A$3&"'!$2:$2"), 0)), _xlpm.GG, INDEX(INDIRECT("'"&A$3&"'!$1:$1048576"), ROW(), MATCH("CAMPO DA SORGENTE NON MAIN", INDIRECT("'"&A$3&"'!$2:$2"), 0)), _xlpm.HH, INDEX(INDIRECT("'"&A$3&"'!$1:$1048576"), ROW(), MATCH("REGOLA TECNICA", INDIRECT("'"&A$3&"'!$2:$2"), 0)), _xlpm.II, INDEX(INDIRECT("'"&A$3&"'!$1:$1048576"), ROW(), MATCH("CHIAVI DI AGGANCIO", INDIRECT("'"&A$3&"'!$2:$2"), 0)), _xlpm.LL, INDEX(INDIRECT("'"&A$3&"'!$1:$1048576"), ROW(), MATCH("DATI SENSIBILI", INDIRECT("'"&A$3&"'!$2:$2"), 0)), IF(_xlpm.AA="","❌ (FLAG_PK)", IF(_xlpm.BB="","❌ (FORMATO)", IF(_xlpm.CC="","❌ (LENGTH)", IF(_xlpm.DD="","❌ (DECIMAL)", IF(_xlpm.FF="","❌ (CAMPO CALCOLATO)", IF(_xlpm.GG="","❌ (CAMPO DA SORGENTE NON MAIN)", IF(_xlpm.HH="","❌ (REGOLA TECNICA)", IF(_xlpm.II="","❌ (CHIAVI DI AGGANCIO)", IF(_xlpm.LL="","❌ (DATI SENSIBILI)", "✅"))))))))) )} -> #N/A | C119: {=IF( INDEX(INDIRECT("'"&A$3&"'!$1:$1048576"), ROW(), MATCH("CAMPO DA SORGENTE NON MAIN", INDIRECT("'"&A$3&"'!$2:$2"), 0))="S", IF(INDEX(INDIRECT("'"&A$3&"'!$1:$1048576"), ROW(), MATCH("CHIAVI DI AGGANCIO", INDIRECT("'"&A$3&"'!$2:$2"), 0))="NA", "❌", "✅"), IF( INDEX(INDIRECT("'"&A$3&"'!$1:$1048576"), ROW(), MATCH("CAMPO DA SORGENTE NON MAIN", INDIRECT("'"&A$3&"'!$2:$2"), 0))="N", IF(INDEX(INDIRECT("'"&A$3&"'!$1:$1048576"), ROW(), MATCH("CHIAVI DI AGGANCIO", INDIRECT("'"&A$3&"'!$2:$2"), 0))<>"NA", "❌", "✅"), "⚠️" ) )} -> #N/A | D119: {=_xlfn.LET( _xlpm.CC, INDEX(INDIRECT("'"&A$3&"'!$1:$1048576"), ROW(), MATCH("CAMPO CALCOLATO", INDIRECT("'"&A$3&"'!$2:$2"), 0)), _xlpm.CDSM, INDEX(INDIRECT("'"&A$3&"'!$1:$1048576"), ROW(), MATCH("CAMPO DA SORGENTE NON MAIN", INDIRECT("'"&A$3&"'!$2:$2"), 0)), _xlpm.RT, INDEX(INDIRECT("'"&A$3&"'!$1:$1048576"), ROW(), MATCH("REGOLA TECNICA", INDIRECT("'"&A$3&"'!$2:$2"), 0)), IF(AND(OR(_xlpm.CC="S", _xlpm.CDSM="S"), OR(_xlpm.RT="NA", _xlpm.RT="")), "❌", IF(AND(_xlpm.CC="N", _xlpm.CDSM="N", _xlpm.RT<>"NA"), "❌", IF(AND(_xlpm.CC="N", _xlpm.CDSM="N"), "✅", IF(AND(OR(_xlpm.CC="S", _xlpm.CDSM="S"), _xlpm.RT<>"NA"), "✅", "⚠️")))) )} -> #N/A | E119: {=_xlfn.LET( _xlpm.CC, INDEX(INDIRECT("'"&A$3&"'!$1:$1048576"), ROW(), MATCH("FORMATO", INDIRECT("'"&A$3&"'!$2:$2"), 0)), IF(_xlpm.CC="NUMBER", "✅", IF(_xlpm.CC="DATE", "✅", IF(_xlpm.CC="VARCHAR", "✅", IF(_xlpm.CC="TIMESTAMP", "✅", "❌")))) )} -> #N/A
B120: {=_xlfn.LET( _xlpm.AA, INDEX(INDIRECT("'"&A$3&"'!$1:$1048576"), ROW(), MATCH("FLAG_PK", INDIRECT("'"&A$3&"'!$2:$2"), 0)), _xlpm.BB, INDEX(INDIRECT("'"&A$3&"'!$1:$1048576"), ROW(), MATCH("FORMATO", INDIRECT("'"&A$3&"'!$2:$2"), 0)), _xlpm.CC, INDEX(INDIRECT("'"&A$3&"'!$1:$1048576"), ROW(), MATCH("LENGTH", INDIRECT("'"&A$3&"'!$2:$2"), 0)), _xlpm.DD, INDEX(INDIRECT("'"&A$3&"'!$1:$1048576"), ROW(), MATCH("DECIMAL", INDIRECT("'"&A$3&"'!$2:$2"), 0)), _xlpm.FF, INDEX(INDIRECT("'"&A$3&"'!$1:$1048576"), ROW(), MATCH("CAMPO CALCOLATO", INDIRECT("'"&A$3&"'!$2:$2"), 0)), _xlpm.GG, INDEX(INDIRECT("'"&A$3&"'!$1:$1048576"), ROW(), MATCH("CAMPO DA SORGENTE NON MAIN", INDIRECT("'"&A$3&"'!$2:$2"), 0)), _xlpm.HH, INDEX(INDIRECT("'"&A$3&"'!$1:$1048576"), ROW(), MATCH("REGOLA TECNICA", INDIRECT("'"&A$3&"'!$2:$2"), 0)), _xlpm.II, INDEX(INDIRECT("'"&A$3&"'!$1:$1048576"), ROW(), MATCH("CHIAVI DI AGGANCIO", INDIRECT("'"&A$3&"'!$2:$2"), 0)), _xlpm.LL, INDEX(INDIRECT("'"&A$3&"'!$1:$1048576"), ROW(), MATCH("DATI SENSIBILI", INDIRECT("'"&A$3&"'!$2:$2"), 0)), IF(_xlpm.AA="","❌ (FLAG_PK)", IF(_xlpm.BB="","❌ (FORMATO)", IF(_xlpm.CC="","❌ (LENGTH)", IF(_xlpm.DD="","❌ (DECIMAL)", IF(_xlpm.FF="","❌ (CAMPO CALCOLATO)", IF(_xlpm.GG="","❌ (CAMPO DA SORGENTE NON MAIN)", IF(_xlpm.HH="","❌ (REGOLA TECNICA)", IF(_xlpm.II="","❌ (CHIAVI DI AGGANCIO)", IF(_xlpm.LL="","❌ (DATI SENSIBILI)", "✅"))))))))) )} -> #N/A | C120: {=IF( INDEX(INDIRECT("'"&A$3&"'!$1:$1048576"), ROW(), MATCH("CAMPO DA SORGENTE NON MAIN", INDIRECT("'"&A$3&"'!$2:$2"), 0))="S", IF(INDEX(INDIRECT("'"&A$3&"'!$1:$1048576"), ROW(), MATCH("CHIAVI DI AGGANCIO", INDIRECT("'"&A$3&"'!$2:$2"), 0))="NA", "❌", "✅"), IF( INDEX(INDIRECT("'"&A$3&"'!$1:$1048576"), ROW(), MATCH("CAMPO DA SORGENTE NON MAIN", INDIRECT("'"&A$3&"'!$2:$2"), 0))="N", IF(INDEX(INDIRECT("'"&A$3&"'!$1:$1048576"), ROW(), MATCH("CHIAVI DI AGGANCIO", INDIRECT("'"&A$3&"'!$2:$2"), 0))<>"NA", "❌", "✅"), "⚠️" ) )} -> #N/A | D120: {=_xlfn.LET( _xlpm.CC, INDEX(INDIRECT("'"&A$3&"'!$1:$1048576"), ROW(), MATCH("CAMPO CALCOLATO", INDIRECT("'"&A$3&"'!$2:$2"), 0)), _xlpm.CDSM, INDEX(INDIRECT("'"&A$3&"'!$1:$1048576"), ROW(), MATCH("CAMPO DA SORGENTE NON MAIN", INDIRECT("'"&A$3&"'!$2:$2"), 0)), _xlpm.RT, INDEX(INDIRECT("'"&A$3&"'!$1:$1048576"), ROW(), MATCH("REGOLA TECNICA", INDIRECT("'"&A$3&"'!$2:$2"), 0)), IF(AND(OR(_xlpm.CC="S", _xlpm.CDSM="S"), OR(_xlpm.RT="NA", _xlpm.RT="")), "❌", IF(AND(_xlpm.CC="N", _xlpm.CDSM="N", _xlpm.RT<>"NA"), "❌", IF(AND(_xlpm.CC="N", _xlpm.CDSM="N"), "✅", IF(AND(OR(_xlpm.CC="S", _xlpm.CDSM="S"), _xlpm.RT<>"NA"), "✅", "⚠️")))) )} -> #N/A | E120: {=_xlfn.LET( _xlpm.CC, INDEX(INDIRECT("'"&A$3&"'!$1:$1048576"), ROW(), MATCH("FORMATO", INDIRECT("'"&A$3&"'!$2:$2"), 0)), IF(_xlpm.CC="NUMBER", "✅", IF(_xlpm.CC="DATE", "✅", IF(_xlpm.CC="VARCHAR", "✅", IF(_xlpm.CC="TIMESTAMP", "✅", "❌")))) )} -> #N/A
B121: {=_xlfn.LET( _xlpm.AA, INDEX(INDIRECT("'"&A$3&"'!$1:$1048576"), ROW(), MATCH("FLAG_PK", INDIRECT("'"&A$3&"'!$2:$2"), 0)), _xlpm.BB, INDEX(INDIRECT("'"&A$3&"'!$1:$1048576"), ROW(), MATCH("FORMATO", INDIRECT("'"&A$3&"'!$2:$2"), 0)), _xlpm.CC, INDEX(INDIRECT("'"&A$3&"'!$1:$1048576"), ROW(), MATCH("LENGTH", INDIRECT("'"&A$3&"'!$2:$2"), 0)), _xlpm.DD, INDEX(INDIRECT("'"&A$3&"'!$1:$1048576"), ROW(), MATCH("DECIMAL", INDIRECT("'"&A$3&"'!$2:$2"), 0)), _xlpm.FF, INDEX(INDIRECT("'"&A$3&"'!$1:$1048576"), ROW(), MATCH("CAMPO CALCOLATO", INDIRECT("'"&A$3&"'!$2:$2"), 0)), _xlpm.GG, INDEX(INDIRECT("'"&A$3&"'!$1:$1048576"), ROW(), MATCH("CAMPO DA SORGENTE NON MAIN", INDIRECT("'"&A$3&"'!$2:$2"), 0)), _xlpm.HH, INDEX(INDIRECT("'"&A$3&"'!$1:$1048576"), ROW(), MATCH("REGOLA TECNICA", INDIRECT("'"&A$3&"'!$2:$2"), 0)), _xlpm.II, INDEX(INDIRECT("'"&A$3&"'!$1:$1048576"), ROW(), MATCH("CHIAVI DI AGGANCIO", INDIRECT("'"&A$3&"'!$2:$2"), 0)), _xlpm.LL, INDEX(INDIRECT("'"&A$3&"'!$1:$1048576"), ROW(), MATCH("DATI SENSIBILI", INDIRECT("'"&A$3&"'!$2:$2"), 0)), IF(_xlpm.AA="","❌ (FLAG_PK)", IF(_xlpm.BB="","❌ (FORMATO)", IF(_xlpm.CC="","❌ (LENGTH)", IF(_xlpm.DD="","❌ (DECIMAL)", IF(_xlpm.FF="","❌ (CAMPO CALCOLATO)", IF(_xlpm.GG="","❌ (CAMPO DA SORGENTE NON MAIN)", IF(_xlpm.HH="","❌ (REGOLA TECNICA)", IF(_xlpm.II="","❌ (CHIAVI DI AGGANCIO)", IF(_xlpm.LL="","❌ (DATI SENSIBILI)", "✅"))))))))) )} -> #N/A | C121: {=IF( INDEX(INDIRECT("'"&A$3&"'!$1:$1048576"), ROW(), MATCH("CAMPO DA SORGENTE NON MAIN", INDIRECT("'"&A$3&"'!$2:$2"), 0))="S", IF(INDEX(INDIRECT("'"&A$3&"'!$1:$1048576"), ROW(), MATCH("CHIAVI DI AGGANCIO", INDIRECT("'"&A$3&"'!$2:$2"), 0))="NA", "❌", "✅"), IF( INDEX(INDIRECT("'"&A$3&"'!$1:$1048576"), ROW(), MATCH("CAMPO DA SORGENTE NON MAIN", INDIRECT("'"&A$3&"'!$2:$2"), 0))="N", IF(INDEX(INDIRECT("'"&A$3&"'!$1:$1048576"), ROW(), MATCH("CHIAVI DI AGGANCIO", INDIRECT("'"&A$3&"'!$2:$2"), 0))<>"NA", "❌", "✅"), "⚠️" ) )} -> #N/A | D121: {=_xlfn.LET( _xlpm.CC, INDEX(INDIRECT("'"&A$3&"'!$1:$1048576"), ROW(), MATCH("CAMPO CALCOLATO", INDIRECT("'"&A$3&"'!$2:$2"), 0)), _xlpm.CDSM, INDEX(INDIRECT("'"&A$3&"'!$1:$1048576"), ROW(), MATCH("CAMPO DA SORGENTE NON MAIN", INDIRECT("'"&A$3&"'!$2:$2"), 0)), _xlpm.RT, INDEX(INDIRECT("'"&A$3&"'!$1:$1048576"), ROW(), MATCH("REGOLA TECNICA", INDIRECT("'"&A$3&"'!$2:$2"), 0)), IF(AND(OR(_xlpm.CC="S", _xlpm.CDSM="S"), OR(_xlpm.RT="NA", _xlpm.RT="")), "❌", IF(AND(_xlpm.CC="N", _xlpm.CDSM="N", _xlpm.RT<>"NA"), "❌", IF(AND(_xlpm.CC="N", _xlpm.CDSM="N"), "✅", IF(AND(OR(_xlpm.CC="S", _xlpm.CDSM="S"), _xlpm.RT<>"NA"), "✅", "⚠️")))) )} -> #N/A | E121: {=_xlfn.LET( _xlpm.CC, INDEX(INDIRECT("'"&A$3&"'!$1:$1048576"), ROW(), MATCH("FORMATO", INDIRECT("'"&A$3&"'!$2:$2"), 0)), IF(_xlpm.CC="NUMBER", "✅", IF(_xlpm.CC="DATE", "✅", IF(_xlpm.CC="VARCHAR", "✅", IF(_xlpm.CC="TIMESTAMP", "✅", "❌")))) )} -> #N/A
... B251: {=_xlfn.LET( _xlpm.AA, INDEX(INDIRECT("'"&A$3&"'!$1:$1048576"), ROW(), MATCH("FLAG_PK", INDIRECT("'"&A$3&"'!$2:$2"), 0)), _xlpm.BB, INDEX(INDIRECT("'"&A$3&"'!$1:$1048576"), ROW(), MATCH("FORMATO", INDIRECT("'"&A$3&"'!$2:$2"), 0)), _xlpm.CC, INDEX(INDIRECT("'"&A$3&"'!$1:$1048576"), ROW(), MATCH("LENGTH", INDIRECT("'"&A$3&"'!$2:$2"), 0)), _xlpm.DD, INDEX(INDIRECT("'"&A$3&"'!$1:$1048576"), ROW(), MATCH("DECIMAL", INDIRECT("'"&A$3&"'!$2:$2"), 0)), _xlpm.FF, INDEX(INDIRECT("'"&A$3&"'!$1:$1048576"), ROW(), MATCH("CAMPO CALCOLATO", INDIRECT("'"&A$3&"'!$2:$2"), 0)), _xlpm.GG, INDEX(INDIRECT("'"&A$3&"'!$1:$1048576"), ROW(), MATCH("CAMPO DA SORGENTE NON MAIN", INDIRECT("'"&A$3&"'!$2:$2"), 0)), _xlpm.HH, INDEX(INDIRECT("'"&A$3&"'!$1:$1048576"), ROW(), MATCH("REGOLA TECNICA", INDIRECT("'"&A$3&"'!$2:$2"), 0)), _xlpm.II, INDEX(INDIRECT("'"&A$3&"'!$1:$1048576"), ROW(), MATCH("CHIAVI DI AGGANCIO", INDIRECT("'"&A$3&"'!$2:$2"), 0)), _xlpm.LL, INDEX(INDIRECT("'"&A$3&"'!$1:$1048576"), ROW(), MATCH("DATI SENSIBILI", INDIRECT("'"&A$3&"'!$2:$2"), 0)), IF(_xlpm.AA="","❌ (FLAG_PK)", IF(_xlpm.BB="","❌ (FORMATO)", IF(_xlpm.CC="","❌ (LENGTH)", IF(_xlpm.DD="","❌ (DECIMAL)", IF(_xlpm.FF="","❌ (CAMPO CALCOLATO)", IF(_xlpm.GG="","❌ (CAMPO DA SORGENTE NON MAIN)", IF(_xlpm.HH="","❌ (REGOLA TECNICA)", IF(_xlpm.II="","❌ (CHIAVI DI AGGANCIO)", IF(_xlpm.LL="","❌ (DATI SENSIBILI)", "✅"))))))))) )} -> #N/A | C251: {=IF( INDEX(INDIRECT("'"&A$3&"'!$1:$1048576"), ROW(), MATCH("CAMPO DA SORGENTE NON MAIN", INDIRECT("'"&A$3&"'!$2:$2"), 0))="S", IF(INDEX(INDIRECT("'"&A$3&"'!$1:$1048576"), ROW(), MATCH("CHIAVI DI AGGANCIO", INDIRECT("'"&A$3&"'!$2:$2"), 0))="NA", "❌", "✅"), IF( INDEX(INDIRECT("'"&A$3&"'!$1:$1048576"), ROW(), MATCH("CAMPO DA SORGENTE NON MAIN", INDIRECT("'"&A$3&"'!$2:$2"), 0))="N", IF(INDEX(INDIRECT("'"&A$3&"'!$1:$1048576"), ROW(), MATCH("CHIAVI DI AGGANCIO", INDIRECT("'"&A$3&"'!$2:$2"), 0))<>"NA", "❌", "✅"), "⚠️" ) )} -> #N/A | D251: {=_xlfn.LET( _xlpm.CC, INDEX(INDIRECT("'"&A$3&"'!$1:$1048576"), ROW(), MATCH("CAMPO CALCOLATO", INDIRECT("'"&A$3&"'!$2:$2"), 0)), _xlpm.CDSM, INDEX(INDIRECT("'"&A$3&"'!$1:$1048576"), ROW(), MATCH("CAMPO DA SORGENTE NON MAIN", INDIRECT("'"&A$3&"'!$2:$2"), 0)), _xlpm.RT, INDEX(INDIRECT("'"&A$3&"'!$1:$1048576"), ROW(), MATCH("REGOLA TECNICA", INDIRECT("'"&A$3&"'!$2:$2"), 0)), IF(AND(OR(_xlpm.CC="S", _xlpm.CDSM="S"), OR(_xlpm.RT="NA", _xlpm.RT="")), "❌", IF(AND(_xlpm.CC="N", _xlpm.CDSM="N", _xlpm.RT<>"NA"), "❌", IF(AND(_xlpm.CC="N", _xlpm.CDSM="N"), "✅", IF(AND(OR(_xlpm.CC="S", _xlpm.CDSM="S"), _xlpm.RT<>"NA"), "✅", "⚠️")))) )} -> #N/A | E251: {=_xlfn.LET( _xlpm.CC, INDEX(INDIRECT("'"&A$3&"'!$1:$1048576"), ROW(), MATCH("FORMATO", INDIRECT("'"&A$3&"'!$2:$2"), 0)), IF(_xlpm.CC="NUMBER", "✅", IF(_xlpm.CC="DATE", "✅", IF(_xlpm.CC="VARCHAR", "✅", IF(_xlpm.CC="TIMESTAMP", "✅", "❌")))) )} -> #N/A

Sheet VARIAZIONI_ANAGRAFICHE
A1: Operazioni eseguite: - Eliminato il campo FL_PEP perchè già presente in entità L2 SEGNALAZIONI_ANAGRAFICHE. - Eliminato il campo FL_DECEDUTO in quanto ridondante rispetto al già presente DT_DECESSO. - Eliminato il campo FL_SOVRAINDEB perchè già presente in entità L2 SEGNALAZIONI_ANAGRAFICHE. - Eliminati i campi FL_TRUFFATO, FL_TRUFFATORE, FL_MEDIATORE e FL_PROSPECT perchè riportati nell'entità L2 SEGNALAZIONI_ANAGRAFICHE. - I campi FL_SOS, FL_CONSENSI_CAI_SIMULAZIONE e FL_RICONOSCIUTO sono stati eliminati n quanto ridondanti rispetto all'entità L2 Segnalazioni_Anagrafiche (sarà comunque indirizzata verso OCS richiesta di conferma della presenza in YQNGRANT.) - In coerenza con le regole decise per la nomenclatura dei campi sono stati modificati campi CD_CONSENSO_SRQ, CD_CONSENSO_OCI, CD_CONSENSO_OIA, CD_CONSENSO_OCE, CD_CONSENSO_OEA, CD_CONSENSO_OSA, CD_CONSENSO_DSU, CD_CONSENSO_CIS, CD_CONSENSO_IPR e CD_CANCELLAZIONE_DATI_PRIVACY da CD a TP. Questo perchè sono valorizzati considerando un range definito di valori. - Eliminati i campi CD_STATO_CIVILE e DS_STATO_CIVILE in quanto sono informazioni che sono raccolte solo nell'archivio BAPRATCT, per questo motivo è stato concordato di lasciare l'informazioni nell'entità L2 SOCIODEMO_SCORE dove l'informazione era già presente. - Eliminati i campi CD_ANNULLO, DS_ANNULLO e DT_ANNULLO che da questa entità saranno spostati negli archivi L2 che gestisicono le catene di intermediazione.
D2: Y' se il campo è nella PK dell'entità, 'N' altrimenti | E2: CHAR-NUMBER-DATE (aaaa-mm-gg) - TIMESTAMP ( aaaa-mm-gg hh:mm:ss) | G2: indicare numero di decimali per i campi numeri (per i campi non numeri, o numerici interi compilare NA) | H2: Modulo ereditato della campo file flussiIN L1 | I2: Dominio del campo STATO: "Validato per processo X": campi che abbiamo validato e non ci aspettiamo di toccare più (nessun OP legato) "In Validazione per processo X": tutti gli altri stati N.B. è possibile inserire "Validato per processo generico"/ "In Validazione per processo generico" se il campo è emerso senza un legame con un processo specifico | M2: (compilare ad N per tutti i campi che ci aspettiamo presi direttamente da L1 senza ulteriri calcoli DWH, S altrimenti) | N2: (compilare ad S per tutti i campi che sono ottenuti a partire da una sorgente DIVERSA dalla tabella MAIN dell'entità N altrimenti) | O2: Da compilare solo se - CAMPO CALCOLATO = S OPPURE - CAMPO DA SORGENTE NON MAIN = S Altrimenti NA | P2: (da compilare solo se CAMPO DA SORGENTE NON MAIN =S, altrimenti NA) | Q2: Da compilare solo se Campo è un dato considerato sensibile (recuperando l’informazione da L1) = S, altrimenti NA. | R2: Valorizzato ad "S" se il campo è stato aggiunto dalla tabella main per arricchimento dell'entità; Altrimenti ad "N" | T2: NOTE REFIN
A3: CATEGORIA CAMPO | B3: NOME CAMPO | C3: DESCRIZIONE | D3: FLAG_PK | E3: FORMATO | F3: LENGTH | G3: DECIMAL | H3: Modulo tabella/e Main | I3: STATO (CAMPO VALIDATO / IN VALIDAZIONE) | J3: SORGENTE TABELLA OCS L1 | K3: SORGENTE CAMPI OCS L1 | L3: REGOLA FUNZIONALE | M3: CAMPO CALCOLATO | N3: CAMPO DA SORGENTE NON MAIN | O3: REGOLA TECNICA | P3: CHIAVI DI AGGANCIO | Q3: DATI SENSIBILI | R3: AGGIUNTO PER ARRICCHIMENTO | S3: NOTE | T3: NOTE REFIN
A4: Identificativo Controparte | B4: CD_CONTROPARTE | C4: Codice Controparte | D4: Y | E4: NUMBER | F4: 9 | G4: 0 | H4: ANA - Gestione anagrafiche | I4: In validazione per Indirizzi da Monitorare; Validato per IFRS9 | J4: CCANALOG | K4: AL_CODICE | M4: N | N4: N | O4: NA | P4: NA | Q4: NA | R4: N
A5: Tempo | B5: TS_INIZIO_VALIDITA | C5: Timestamp inizio validità, si tratta di un campo tecnico prodotto da DBT per la storicizzazione dell'entità | D5: Y | E5: TIMESTAMP | F5: 8 | G5: NA | H5: ANA - Gestione anagrafiche | I5: Aggiunto in fase di analisi tecnica | J5: CCANALOG | K5: AL_DATA_MODIFICA AL_ORA_MODIFICA | L5: Il timestamp di inizio validità del record di riferimento di una certa controparte, sarà la prima Data-Ora Modifica di ciascuna viariazione del CCANALOG | M5: N | N5: N | O5: NA | P5: NA | Q5: NA | R5: N | S5: + OP 556 per impatto IFRS9
B6: TS_FINE_VALIDITA | C6: Timestamp fine validità, si tratta di un campo tecnico prodotto da DBT per la storicizzazione dell'entità | D6: N | E6: TIMESTAMP | F6: 8 | G6: NA | H6: ANA - Gestione anagrafiche | I6: Aggiunto in fase di analisi tecnica | J6: CCANALOG | K6: AL_DATA_MODIFICA AL_ORA_MODIFICA | L6: Il timestamp di di fine validità del record di riferimento di una certa controparte, sarà pari alla Data-Ora di Inizio Validità del record di variazione successivo per quella controparte | M6: N | N6: N | O6: NA | P6: NA | Q6: NA | R6: N
A7: Progressivo | B7: PROGRESSIVO_PK | C7: Numero progressivo che ordina i record raggruppati per chiave primaria | D7: Y | E7: NUMBER | F7: 3 | G7: NA | H7: NA | I7: Aggiunto in fase di analisi tecnica | J7: NA | K7: NA | L7: ordina i record raggruppati per AL_CODICE e TS_INIZIO_VALIDITA | M7: S | N7: N | O7: SELECT ROW_NUMBER() OVER ( PARTITION BY CD_CONTROPARTE, TS_INIZIO_VALIDITA ORDER BY TS_INIZIO_VALIDITA ) AS PROGRESSIVO_PK FROM VARIAZIONI_ANAGRAFICHE | P7: NA | Q7: NA | R7: N
B8: PROGRESSIVO_CONTROPARTE | C8: Numero progressivo che ordina i record raggruppati per controparte | D8: N | E8: NUMBER | F8: 3 | G8: NA | H8: NA | I8: Aggiunto in fase di analisi tecnica | J8: NA | K8: NA | L8: ordina i record raggruppati per AL_CODICE e li ordina in base al AL_DATA_MODIFICA e AL_ORA_MODIFICA | M8: S | N8: N | O8: SELECT ROW_NUMBER() OVER ( PARTITION BY CD_CONTROPARTE ORDER BY TS_INIZIO_VALIDITA ) AS PROGRESSIVO_CONTROPARTE FROM VARIAZIONI_ANAGRAFICHE | P8: NA | Q8: NA | R8: N
A9: Dati Personali Identificativi (GDPR - dati da mascherare perchè identificativi) | B9: TP_CONTROPARTE | C9: Tipo controparte | D9: N | E9: VARCHAR | F9: 1 | G9: NA | H9: ANA - Gestione anagrafiche | I9: Validato per Fircosoft , Validato per Sic.Fin; Validato per IFRS9, In validazione per Monitoraggio Accettazione, In validazione per Comitato | J9: CCANALOG | K9: AL_TIPO_ANAGRAFICA | M9: N | N9: N | O9: NA | P9: NA | Q9: S | R9: N
B10: CD_FORMA_GIURIDICA | C10: Codice forma giuridica | D10: N | E10: VARCHAR | F10: 3 | G10: NA | H10: ANA - Gestione anagrafiche | I10: In validazione per MA | J10: CCANALOG | K10: AL_FORMA_GIURIDICA | M10: N | N10: N | O10: NA | P10: NA | Q10: S | R10: N
B11: CD_FISCALE | C11: Codice fiscale | D11: N | E11: VARCHAR | F11: 16 | G11: NA | H11: ANA - Gestione anagrafiche | I11: Validato per Fircosoft, Validato per Sic.Fin; Validato per IFRS9 | J11: CD_FISCALE | K11: AL_CODICE_FISCALE | M11: N | N11: N | O11: NA | P11: NA | Q11: S | R11: N | S11: Da mascherare
B12: FL_CF_CALCOLATO | C12: Flag che identifica se il codice fiscale è stato ricostruito | D12: N | E12: VARCHAR | F12: 1 | G12: NA | H12: ANA - Gestione anagrafiche | I12: Aggiunto da main per arricchimento | J12: CCANALOG | K12: AL_CODICE_FISC_CALC | M12: N | N12: N | O12: NA | P12: NA | Q12: NA | R12: S
B13: FL_CF_FORZATO | C13: flag che identifica se il codice fiscale è stato forzato | D13: N | E13: VARCHAR | F13: 1 | G13: NA | H13: ANA - Gestione anagrafiche | I13: Aggiunto da main per arricchimento | J13: CCANALOG | K13: AL_CODICE_FISC_FORZ | M13: N | N13: N | O13: NA | P13: NA | Q13: NA | R13: S
B14: CD_UTENTE_FORZATURA_CF | C14: Utente che ha forzato il codice fiscale | D14: N | E14: VARCHAR | F14: 10 | G14: NA | H14: ANA - Gestione anagrafiche | I14: Aggiunto da main per arricchimento | J14: CCANALOG | K14: AL_UTENTE_FORZATURA | M14: N | N14: N | O14: NA | P14: NA | Q14: NA | R14: S
B15: CD_PARTITA_IVA | C15: Partita IVA | D15: N | E15: VARCHAR | F15: 11 | G15: NA | H15: ANA - Gestione anagrafiche | I15: Validato per Fircosoft, Validato per Sic.Fin; Validato per IFRS9 | J15: CCANALOG | K15: AL_PARTITA_IVA | M15: N | N15: N | O15: NA | P15: NA | Q15: S | R15: N
B16: DS_NOME | C16: Nome | D16: N | E16: VARCHAR | F16: 30 | G16: NA | H16: ANA - Gestione anagrafiche | I16: Validato per Fircosoft, Validato per Sic.Fin;validato per Estrazioni Carte; Validato per IFRS9, Validato per vendite fuori target in validazione per vendite fuori target | J16: CCANALOG | K16: AL_NOME | M16: N | N16: N | O16: NA | P16: NA | Q16: S | R16: N
B17: DS_SECONDO_NOME | C17: Secondo Nome | D17: N | E17: VARCHAR | F17: 30 | G17: NA | H17: ANA - Gestione anagrafiche | I17: In validazione per MA | J17: CCANALOG | K17: AL_SECONDO_NOME | M17: N | N17: N | O17: NA | P17: NA | Q17: S | R17: N
B18: DS_COGNOME | C18: Cognome | D18: N | E18: VARCHAR | F18: 30 | G18: NA | H18: ANA - Gestione anagrafiche | I18: Validato per Fircosoft , Validato per Sic.Fin; validato per Estrazioni Carte; Validato per IFRS9, Validato per vendite fuori target in validazione per vendite fuori target | J18: CCANALOG | K18: AL_COGNOME | M18: N | N18: N | O18: NA | P18: NA | Q18: S | R18: N
B19: DS_COGNOME_MADRE | C19: Cognome della madre | D19: N | E19: VARCHAR | F19: 30 | G19: NA | H19: ANA - Gestione anagrafiche | I19: Aggiunto da main per arricchimento | J19: CCANALOG | K19: AL_COGNOME_MADRE | M19: N | N19: N | O19: NA | P19: NA | Q19: S | R19: S
B20: CD_RIFERIMENTO_ALTRA_ANAGRAFICA | C20: Codice di un'altra anagrafica collegata | D20: N | E20: NUMBER | F20: 9 | G20: 0 | H20: ANA - Gestione anagrafiche | I20: Aggiunto da main per arricchimento | J20: CCANALOG | K20: AL_RIFERIMENTO | M20: N | N20: N | O20: NA | P20: NA | Q20: NA | R20: S
B21: CD_MATRICOLA | C21: Codice matricola | D21: N | E21: NUMBER | F21: 8 | G21: 0 | H21: ANA - Gestione anagrafiche | I21: Aggiunto da main per arricchimento | J21: CCANALOG | K21: AL_MATRICOLA | M21: N | N21: N | O21: NA | P21: NA | Q21: NA | R21: S
B22: DS_RAGIONE_SOCIALE | C22: Ragione sociale | D22: N | E22: VARCHAR | F22: 30 | G22: NA | H22: ANA - Gestione anagrafiche | I22: Validato per Fircosoft ; Validato per IFRS9 | J22: CCANALOG | K22: AL_RAG_SOCIALE_1 | M22: N | N22: N | O22: NA | P22: NA | Q22: S | R22: N
B23: DS_RAGIONE_SOCIALE_2 | C23: Ragione sociale 2 (campo non obbligatorio) | D23: N | E23: VARCHAR | F23: 30 | G23: NA | H23: ANA - Gestione anagrafiche | I23: In validazione per MA | J23: CCANALOG | K23: AL_RAG_SOCIALE_2 | M23: N | N23: N | O23: NA | P23: NA | Q23: S | R23: N
B24: CD_CITTADINANZA | C24: Cittadinanza | D24: N | E24: VARCHAR | F24: 3 | G24: NA | H24: ANA - Gestione anagrafiche | I24: in validazione per antifrode | J24: CCANALOG | K24: AL_CITTADINANZA | M24: N | N24: N | O24: NA | P24: NA | Q24: NA | R24: N
B25: DS_CITTADINANZA | C25: Cittadinanza della controparte | D25: N | E25: VARCHAR | F25: 30 | G25: NA | H25: CRE - Credito | I25: Validato per Campioni; Validato per IFRS9 | J25: CCCRETCI | K25: CRECI_DESCRIZIONE | L25: Join tra CCANALOG e CCCRETCI sul campo CCANALOG.AL_CITTADINANZA=CCCRETCI.CRECI_CITTADINANZA | M25: N | N25: S | O25: SELECT CCCRETCI.CRECI_DESCRIZIONE FROM CCANALOG LEFT JOIN CCCRETCI ON CCANALOG.AL_CITTADINANZA=CCCRETCI.CRECI_CITTADINANZA AND CCANALOG.AL_DATA_MODIFICA BETWEEN CCRETCI.TS_INIZIO_VALIDITA AND CCRETCI.TS_FINE_VALIDITA | P25: FROM CCANALOG LEFT JOIN CCCRETCI ON CCANALOG.AL_CITTADINANZA=CCCRETCI.CRECI_CITTADINANZA AND CCANALOG.AL_DATA_MODIFICA BETWEEN CCRETCI.TS_INIZIO_VALIDITA AND CCRETCI.TS_FINE_VALIDITA | Q25: NA | R25: N | S25: + OP 556 per impatto IFRS9 | T25: Riordinato
B26: DS_CITTA_NASCITA | C26: Città di nascita | D26: N | E26: VARCHAR | F26: 30 | G26: NA | H26: ANA - Gestione anagrafiche | I26: In Validazione per MA | J26: CCANALOG | K26: AL_NASCITA_LUOGO | M26: N | N26: N | O26: NA | P26: NA | Q26: S | R26: N
B27: CD_NAZIONE_NASCITA | C27: Codice Nazione di nascita | D27: N | E27: VARCHAR | F27: 3 | G27: NA | H27: ANA - Gestione anagrafiche | I27: In Validazione per MA | J27: CCANALOG | K27: AL_NASCITA_NAZIONE | M27: N | N27: N | O27: NA | P27: NA | Q27: S | R27: N | T27: Riordinato
B28: DS_NAZIONE_NASCITA | C28: Descrizione Nazione di nascita | D28: N | E28: VARCHAR | F28: 30 | G28: NA | H28: ANA - Gestione anagrafiche | I28: Validato per Fircosoft ; Validato per IFRS9 | J28: CCANATNA | K28: ANATNA_DESCRIZIONE | L28: Join tra CCANALOG e CCANATNA sul campo CCANALOG.AL_NASCITA_NAZIONE=CCANTNA.ANATNA_NAZIONE | M28: N | N28: S | O28: SELECT CCANTNA.ANATNA_DESCRIZIONE FROM CCANALOG LEFT JOIN CCANTNA CCANALOG.AL_NASCITA_NAZIONE=CCANTNA.ANATNA_NAZIONE AND CCANALOG.AL_DATA_MODIFICA BETWEEN CCANTNA.TS_INIZIO_VALIDITA AND CCANTNA.TS_FINE_VALIDITA | P28: FROM CCANALOG LEFT JOIN CCANTNA CCANALOG.AL_NASCITA_NAZIONE=CCANTNA.ANATNA_NAZIONE AND CCANALOG.AL_DATA_MODIFICA BETWEEN CCANTNA.TS_INIZIO_VALIDITA AND CCANTNA.TS_FINE_VALIDITA | Q28: NA | R28: N | T28: Riordinato
B29: CD_PROVINCIA_NASCITA | C29: Codice provincia di nascita | D29: N | E29: VARCHAR | F29: 2 | G29: NA | H29: ANA - Gestione anagrafiche | I29: Aggiunto in fase di analisi tecnica | J29: CCANALOG | K29: AL_NASCITA_PROV | M29: N | N29: N | O29: NA | P29: NA | Q29: S | R29: N
B30: DS_PROVINCIA_NASCITA | C30: Provincia di nascita | D30: N | E30: VARCHAR | F30: 30 | G30: NA | H30: ANA - Gestione anagrafiche | I30: Validato per Fircosoft ; Validato per IFRS9 | J30: CCANATPR | K30: ANATPR_DESCRIZIONE | L30: JOIN CCANALOG.AL_NASCITA_PROV=CCANATPR.ANATPR_PROVINCIA | M30: N | N30: S | O30: SELECT ANATPR_DESCRIZIONE FROM CCANALOG LEFT JOIN CCANATPR ON CCANALOG.AL_NASCITA_PROV=CCANATPR.ANATPR_PROVINCIA AND CCANALOG.AL_DATA_MODIFICA BETWEEN CCANATPR .TS_INIZIO_VALIDITA AND CCANATPR .TS_FINE_VALIDITA | P30: FROM CCANALOG LEFT JOIN CCANATPR ON CCANALOG.AL_NASCITA_PROV=CCANATPR.ANATPR_PROVINCIA AND CCANALOG.AL_DATA_MODIFICA BETWEEN CCANATPR .TS_INIZIO_VALIDITA AND CCANATPR .TS_FINE_VALIDITA | Q30: NA | R30: N | S30: + OP 556 per impatto IFRS9 | T30: Riordinato
B31: DS_COMUNE_NASCITA | C31: Comune di nascita | D31: N | E31: VARCHAR | F31: 30 | G31: NA | H31: ANA - Gestione anagrafiche | I31: In validazione per Sic.Fin; Validato per IFRS9 | J31: CCANALOG | K31: AL_NASCITA_LUOGO | M31: N | N31: N | O31: NA | P31: NA | Q31: S | R31: N | T31: Riordinato
B32: CD_CAB_COMUNE_NASCITA | C32: Codice cab comune di nascita | D32: N | E32: VARCHAR | F32: 5 | G32: NA | H32: ANA - Gestione anagrafiche | I32: Aggiunto in fase di analisi tecnica | J32: CCANALOG | K32: AL_NASCITA_CAB_LOC | M32: N | N32: N | O32: NA | P32: NA | Q32: S | R32: N
B33: DT_NASCITA | C33: Data di nascita o data di registrazione per un'azienda | D33: N | E33: DATE | F33: 8 | G33: 0 | H33: ANA - Gestione anagrafiche | I33: Validato per Vigilanza; Validato per IFRS9 | J33: CCANALOG | K33: AL_NASCITA_DATA | M33: N | N33: N | O33: NA | P33: NA | Q33: S | R33: N | T33: Riordinato
B34: CD_SESSO | C34: Sesso | D34: N | E34: VARCHAR | F34: 1 | G34: NA | H34: ANA - Gestione anagrafiche | I34: Validato per Campioni; Validato per IFRS9 | J34: CCANALOG | K34: AL_SESSO | M34: N | N34: N | O34: NA | P34: NA | Q34: S | R34: N | T34: Spostato qui da Dati Personali NON Identificativi (Settore Attività)
B35: DT_DECESSO | C35: Data del decesso | D35: N | E35: DATE | F35: 8 | G35: NA | H35: ANA - Gestione anagrafiche | I35: In validazione per Flussi Convenzionati | J35: CCANALOG | K35: AL_DATA_CESSAZIONE | M35: N | N35: N | O35: NA | P35: NA | Q35: NA | R35: N
B36: CD_ABI | C36: Codice ABI, valorizzato solo se la controparte è un istituto finanziario | D36: N | E36: NUMBER | F36: 5 | G36: 0 | H36: ANA - Gestione anagrafiche | I36: Aggiunto da main per arricchimento | J36: CCANALOG | K36: AL_ABI | M36: N | N36: N | O36: NA | P36: NA | Q36: NA | R36: S
B37: CD_IDENTIFICATIVO | C37: Identifica il codice identificativo da gestire. | D37: N | E37: VARCHAR | F37: 13 | G37: NA | H37: ANA - Gestione anagrafiche | I37: Aggiunto da main per arricchimento | J37: CCANALOG | K37: AL_COD_IDEN | M37: N | N37: N | O37: NA | P37: NA | Q37: NA | R37: S
B38: CD_NDG | C38: Codice NDG | D38: N | E38: NUMBER | F38: 12 | G38: 0 | H38: ANA - Gestione anagrafiche | I38: Aggiunto da main per arricchimento | J38: CCANALOG | K38: AL_CODICE_NDG | M38: N | N38: N | O38: NA | P38: NA | Q38: S | R38: S
B39: CD_NDG2 | C39: Codice NDG 2 | D39: N | E39: NUMBER | F39: 12 | G39: 0 | H39: ANA - Gestione anagrafiche | I39: Aggiunto da main per arricchimento | J39: CCANALOG | K39: AL_CODICE_NDG2 | M39: N | N39: N | O39: NA | P39: NA | Q39: S | R39: S
B40: CD_NDG3 | C40: Codice NDG 3 | D40: N | E40: VARCHAR | F40: 12 | G40: NA | H40: ANA - Gestione anagrafiche | I40: Aggiunto da main per arricchimento | J40: CCANALOG | K40: AL_CODICE_NDG3 | M40: N | N40: N | O40: NA | P40: NA | Q40: S | R40: S
B41: CD_NDG_CRF | C41: Codice NDG CRF | D41: N | E41: VARCHAR | F41: 15 | G41: NA | H41: ANA - Gestione anagrafiche | I41: Aggiunto da main per arricchimento | J41: CCANALOG | K41: AL_CODICE_NDG_CRF | M41: N | N41: N | O41: NA | P41: NA | Q41: S | R41: S
A42: Settore Attività | B42: CD_INPS_MATRICOLA | C42: Matricola INPS | D42: N | E42: VARCHAR | F42: 10 | G42: NA | H42: ANA - Gestione anagrafiche | I42: Aggiunto da main per arricchimento | J42: CCANALOG | K42: AL_INPS_MATRICOLA | M42: N | N42: N | O42: NA | P42: NA | Q42: NA | R42: S
B43: CD_INAIL_PAT | C43: Codice PAT INAIL | D43: N | E43: VARCHAR | F43: 9 | G43: NA | H43: ANA - Gestione anagrafiche | I43: Aggiunto da main per arricchimento | J43: CCANALOG | K43: AL_INAIL_PAT | M43: N | N43: N | O43: NA | P43: NA | Q43: NA | R43: S
B44: CD_IPA | C44: Codice IPA | D44: N | E44: VARCHAR | F44: 20 | G44: NA | H44: ANA - Gestione anagrafiche | I44: Aggiunto da main per arricchimento | J44: CCANALOG | K44: AL_IPA | M44: N | N44: N | O44: NA | P44: NA | Q44: NA | R44: S
B45: CD_FILIALE | C45: Indica la filiale di appartenenza | D45: N | E45: VARCHAR | F45: 3 | G45: NA | H45: ANA - Gestione anagrafiche | I45: Aggiunto da main per arricchimento | J45: CCANALOG | K45: AL_FILIALE | M45: N | N45: N | O45: NA | P45: NA | Q45: NA | R45: S
B46: CD_FILIALE_STORICA | C46: Filiale storica | D46: N | E46: VARCHAR | F46: 3 | G46: NA | H46: ANA - Gestione anagrafiche | I46: Aggiunto da main per arricchimento | J46: CCANALOG | K46: AL_FILIALE_STORICA | M46: N | N46: N | O46: NA | P46: NA | Q46: NA | R46: S
B47: CD_ESENZIONE_IVA | C47: Identifica l'esenzione IVA da gestire. | D47: N | E47: VARCHAR | F47: 2 | G47: NA | H47: ANA - Gestione anagrafiche | I47: Aggiunto da main per arricchimento | J47: CCANALOG | K47: AL_ESENZIONE_IVA | M47: N | N47: N | O47: NA | P47: NA | Q47: NA | R47: S
B48: CD_SETTORE_ATTIVITA | C48: Codice settore attività | D48: N | E48: NUMBER | F48: 4 | G48: 0 | H48: ANA - Gestione anagrafiche | I48: Aggiunto da main per arricchimento | J48: CCANALOG | K48: AL_TIPO_ATTIVITA | M48: N | N48: N | O48: NA | P48: NA | Q48: NA | R48: S
B49: DS_ATECO | C49: Descrizione Ateco | D49: N | E49: VARCHAR | F49: 180 | G49: NA | H49: ANA - Gestione anagrafiche | I49: In validazione per MA | J49: CCANATAT | K49: ANATAT_DESCRIZIONE | L49: Join con CCANALOG considerando i campi CCANALOG.AL_ATECO=CCANATAT.ANATAT_ATECO | M49: N | N49: S | O49: SELECT CCANATAT.ANATAT_DESCRIZIONE FROM CCANALOG LEFT JOIN CCANATAT ON CCANALOG.AL_ATECO=CCANATAT.ANATAT_ATECO AND CCANALOG.AL_DATA_MODIFICA BETWEEN CCANATAT.TS_INIZIO_VALIDITA AND CCANATAT.TS_FINE_VALIDITA | P49: FROM CCANALOG LEFT JOIN CCANATAT ON CCANALOG.AL_ATECO=CCANATAT.ANATAT_ATECO AND CCANALOG.AL_DATA_MODIFICA BETWEEN CCANATAT.TS_INIZIO_VALIDITA AND CCANATAT.TS_FINE_VALIDITA | Q49: NA | R49: N
B50: CD_ATECO | C50: Codice Ateco | D50: N | E50: VARCHAR | F50: 6 | G50: NA | H50: ANA - Gestione anagrafiche | I50: Validato per Fircosoft , Validato per Sic.Fin; Validato per IFRS9 | J50: CCANALOG | K50: AL_ATECO | M50: N | N50: N | O50: NA | P50: NA | Q50: NA | R50: N
